Workbook

Sheet 30-07
B1: Qtde. Total chamados Status | H1: Qtde. Total chamados por categoria | R1: Mês/Ano | S1: jul/2026
H2: Status | I2: PENDENTE | R2: Data de abertura | S2: (Tudo)
B4: #VALUE! | I4: Rótulos de Coluna | R4: Rótulos de Linha | S4: Contagem de Número do Chamado
I5: 2025 | J5: 2026 | K5: - | R5: Emilly Maria | S5: 20
R6: Fabiana Lisboa | S6: 12
R7: Pamela de Sá | S7: 24
R8: Stephany Lima | S8: 37
H9: Contagem de Número de protocolo | I9: 11 | J9: 84 | K9: 95 | R9: Vanessa Araujo | S9: 4
R10: Total Geral | S10: 97
B17: Qtde. Chamados por categoria x responsável
B18: Status | C18: PENDENTE
B19: Data de abertura | C19: (Vários itens)
B21: Rótulos de Linha | C21: Contagem Chamado
B22: Emilly Maria | C22: 13
B23: Fabiana Lisboa | C23: 10
B24: Pamela de Sá | C24: 23
B25: Stephany Lima | C25: 32
B26: Vanessa Araujo | C26: 6
B27: Total Geral | C27: 84
D45: Amanda verificar

Sheet Dashboard
B2: Painel de Acompanhamento
B4: Indicadores Gerais | N4: Situação Últimos 30 Dias
B5: TOTAL DE CHAMADOS | D5: CHAMADOS ABERTOS | F5: CHAMADOS ENCERRADOS | H5: ATENDIDOS ÚLT. 7 DIAS | J5: REABERTOS | N5: ABERTOS | P5: ENCERRADOS | R5: AINDA ABERTOS
B6: =COUNTA('Compilado chamados'!D5:D1048576) -> 409 | D6: =COUNTIF('Compilado chamados'!Y5:Y1048576,"Aberto") -> 155 | F6: =COUNTIF('Compilado chamados'!Y5:Y1048576,"Encerrado") -> 254 | H6: =COUNTIFS('Compilado chamados'!Y5:Y1048576,"Encerrado",'Compilado chamados'!X5:X1048576,">="&TODAY()-7,'Compilado chamados'!X5:X1048576,"<="&TODAY()) -> 27 | J6: =COUNTIF('Compilado chamados'!L:L,"REABERTO") -> 0 | N6: =COUNTIFS('Compilado chamados'!O5:O1048576,">="&TODAY()-30,'Compilado chamados'!O5:O1048576,"<="&TODAY()) -> 35 | P6: =COUNTIFS('Compilado chamados'!Y5:Y1048576,"Encerrado",'Compilado chamados'!O5:O1048576,">="&TODAY()-30,'Compilado chamados'!O5:O1048576,"<="&TODAY()) -> 19 | R6: =COUNTIFS('Compilado chamados'!Y5:Y1048576,"Aberto",'Compilado chamados'!O5:O1048576,">="&TODAY()-30,'Compilado chamados'!O5:O1048576,"<="&TODAY()) -> 16
B9: Chamados Atendidos por Mês (Encerrados) | N9: Chamados por Classificação
B10: Mês | C10: Atendidos | O10: Atendidos | P10: Em Aberto | Q10: Abertos Últ. 30d
B11: Mar/2026 | C11: =COUNTIFS('Compilado chamados'!$Y$5:$Y$1048576,"Encerrado",'Compilado chamados'!$X$5:$X$1048576,">="&DATE(2026,3,1),'Compilado chamados'!$X$5:$X$1048576,"<"&EDATE(DATE(2026,3,1),1)) -> 1 | N11: Cancelamento e Reemissão de Nota Fiscal | O11: =COUNTIFS('Compilado chamados'!C:C,N11,'Compilado chamados'!Y:Y,"Encerrado") -> 98 | P11: =COUNTIFS('Compilado chamados'!C:C,N11,'Compilado chamados'!Y:Y,"Aberto") -> 56 | Q11: =COUNTIFS( 'Compilado chamados'!C:C,N11, 'Compilado chamados'!Y:Y,"Aberto", 'Compilado chamados'!O:O,">="&TODAY()-30, 'Compilado chamados'!O:O,"<"&TODAY()+1 ) -> 6
B12: Abr/2026 | C12: =COUNTIFS('Compilado chamados'!$Y$5:$Y$1048576,"Encerrado",'Compilado chamados'!$X$5:$X$1048576,">="&DATE(2026,4,1),'Compilado chamados'!$X$5:$X$1048576,"<"&EDATE(DATE(2026,4,1),1)) -> 1 | N12: Cobrança e Contestação | O12: =COUNTIFS('Compilado chamados'!C:C,N12,'Compilado chamados'!Y:Y,"Encerrado") -> 38 | P12: =COUNTIFS('Compilado chamados'!C:C,N12,'Compilado chamados'!Y:Y,"Aberto") -> 41 | Q12: =COUNTIFS( 'Compilado chamados'!C:C,N12, 'Compilado chamados'!Y:Y,"Aberto", 'Compilado chamados'!O:O,">="&TODAY()-30, 'Compilado chamados'!O:O,"<"&TODAY()+1 ) -> 2
B13: Mai/2026 | C13: =COUNTIFS('Compilado chamados'!$Y$5:$Y$1048576,"Encerrado",'Compilado chamados'!$X$5:$X$1048576,">="&DATE(2026,5,1),'Compilado chamados'!$X$5:$X$1048576,"<"&EDATE(DATE(2026,5,1),1)) -> 3 | N13: Pagamentos, Boletos e Recebimentos | O13: =COUNTIFS('Compilado chamados'!C:C,N13,'Compilado chamados'!Y:Y,"Encerrado") -> 50 | P13: =COUNTIFS('Compilado chamados'!C:C,N13,'Compilado chamados'!Y:Y,"Aberto") -> 22 | Q13: =COUNTIFS( 'Compilado chamados'!C:C,N13, 'Compilado chamados'!Y:Y,"Aberto", 'Compilado chamados'!O:O,">="&TODAY()-30, 'Compilado chamados'!O:O,"<"&TODAY()+1 ) -> 3
B14: Jun/2026 | C14: =COUNTIFS('Compilado chamados'!$Y$5:$Y$1048576,"Encerrado",'Compilado chamados'!$X$5:$X$1048576,">="&DATE(2026,6,1),'Compilado chamados'!$X$5:$X$1048576,"<"&EDATE(DATE(2026,6,1),1)) -> 0 | N14: Contratos, Comercial e Cadastro | O14: =COUNTIFS('Compilado chamados'!C:C,N14,'Compilado chamados'!Y:Y,"Encerrado") -> 43 | P14: =COUNTIFS('Compilado chamados'!C:C,N14,'Compilado chamados'!Y:Y,"Aberto") -> 15 | Q14: =COUNTIFS( 'Compilado chamados'!C:C,N14, 'Compilado chamados'!Y:Y,"Aberto", 'Compilado chamados'!O:O,">="&TODAY()-30, 'Compilado chamados'!O:O,"<"&TODAY()+1 ) -> 2
B15: Jul/2026 | C15: =COUNTIFS('Compilado chamados'!$Y$5:$Y$1048576,"Encerrado",'Compilado chamados'!$X$5:$X$1048576,">="&DATE(2026,7,1),'Compilado chamados'!$X$5:$X$1048576,"<"&EDATE(DATE(2026,7,1),1)) -> 74 | N15: Atendimento Administrativo e Suporte | O15: =COUNTIFS('Compilado chamados'!C:C,N15,'Compilado chamados'!Y:Y,"Encerrado") -> 18 | P15: =COUNTIFS('Compilado chamados'!C:C,N15,'Compilado chamados'!Y:Y,"Aberto") -> 11 | Q15: =COUNTIFS( 'Compilado chamados'!C:C,N15, 'Compilado chamados'!Y:Y,"Aberto", 'Compilado chamados'!O:O,">="&TODAY()-30, 'Compilado chamados'!O:O,"<"&TODAY()+1 ) -> 2
B16: Ago/2026 | C16: =COUNTIFS('Compilado chamados'!$Y$5:$Y$1048576,"Encerrado",'Compilado chamados'!$X$5:$X$1048576,">="&DATE(2026,8,1),'Compilado chamados'!$X$5:$X$1048576,"<"&EDATE(DATE(2026,8,1),1)) -> 96 | N16: Faturamento e Obrigações Fiscais | O16: =COUNTIFS('Compilado chamados'!C:C,N16,'Compilado chamados'!Y:Y,"Encerrado") -> 7 | P16: =COUNTIFS('Compilado chamados'!C:C,N16,'Compilado chamados'!Y:Y,"Aberto") -> 9 | Q16: =COUNTIFS( 'Compilado chamados'!C:C,N16, 'Compilado chamados'!Y:Y,"Aberto", 'Compilado chamados'!O:O,">="&TODAY()-30, 'Compilado chamados'!O:O,"<"&TODAY()+1 ) -> 1
B17: Set/2026 | C17: =COUNTIFS('Compilado chamados'!$Y$5:$Y$1048576,"Encerrado",'Compilado chamados'!$X$5:$X$1048576,">="&DATE(2026,9,1),'Compilado chamados'!$X$5:$X$1048576,"<"&EDATE(DATE(2026,9,1),1)) -> 78
B20: Chamados por Responsável
B21: Classificação | C21: Atendidos | D21: Encerrado Últ. 7 Dias | E21: Em Andamento | F21: Em Aberto | G21: Prioridade
B22: Vanessa Araujo | C22: =COUNTIFS('Compilado chamados'!B:B,Dashboard!B22,'Compilado chamados'!Y:Y,"Encerrado") -> 8 | D22: =COUNTIFS( 'Compilado chamados'!B:B,Dashboard!B22, 'Compilado chamados'!Y:Y,"Encerrado", 'Compilado chamados'!X:X,">="&TODAY()-7, 'Compilado chamados'!X:X,"<"&TODAY()+1 ) -> 1 | E22: =COUNTIFS('Compilado chamados'!B:B,Dashboard!B22,'Compilado chamados'!L:L,"EM ANDAMENTO") -> 0 | F22: =COUNTIFS('Compilado chamados'!B:B,Dashboard!B22,'Compilado chamados'!Y:Y,"Aberto") -> 0 | G22: =COUNTIFS('Compilado chamados'!B:B,Dashboard!B22,'Compilado chamados'!M:M,"Alta") -> 0
B23: Stephany Lima | C23: =COUNTIFS('Compilado chamados'!B:B,Dashboard!B23,'Compilado chamados'!Y:Y,"Encerrado") -> 78 | D23: =COUNTIFS( 'Compilado chamados'!B:B,Dashboard!B23, 'Compilado chamados'!Y:Y,"Encerrado", 'Compilado chamados'!X:X,">="&TODAY()-7, 'Compilado chamados'!X:X,"<"&TODAY()+1 ) -> 7 | E23: =COUNTIFS('Compilado chamados'!B:B,Dashboard!B23,'Compilado chamados'!L:L,"EM ANDAMENTO") -> 11 | F23: =COUNTIFS('Compilado chamados'!B:B,Dashboard!B23,'Compilado chamados'!Y:Y,"Aberto") -> 58 | G23: =COUNTIFS('Compilado chamados'!B:B,Dashboard!B23,'Compilado chamados'!M:M,"Alta") -> 18
B24: Pamela de Sá | C24: =COUNTIFS('Compilado chamados'!B:B,Dashboard!B24,'Compilado chamados'!Y:Y,"Encerrado") -> 28 | D24: =COUNTIFS( 'Compilado chamados'!B:B,Dashboard!B24, 'Compilado chamados'!Y:Y,"Encerrado", 'Compilado chamados'!X:X,">="&TODAY()-7, 'Compilado chamados'!X:X,"<"&TODAY()+1 ) -> 1 | E24: =COUNTIFS('Compilado chamados'!B:B,Dashboard!B24,'Compilado chamados'!L:L,"EM ANDAMENTO") -> 8 | F24: =COUNTIFS('Compilado chamados'!B:B,Dashboard!B24,'Compilado chamados'!Y:Y,"Aberto") -> 35 | G24: =COUNTIFS('Compilado chamados'!B:B,Dashboard!B24,'Compilado chamados'!M:M,"Alta") -> 7
B25: Emilly Maria | C25: =COUNTIFS('Compilado chamados'!B:B,Dashboard!B25,'Compilado chamados'!Y:Y,"Encerrado") -> 80 | D25: =COUNTIFS( 'Compilado chamados'!B:B,Dashboard!B25, 'Compilado chamados'!Y:Y,"Encerrado", 'Compilado chamados'!X:X,">="&TODAY()-7, 'Compilado chamados'!X:X,"<"&TODAY()+1 ) -> 8 | E25: =COUNTIFS('Compilado chamados'!B:B,Dashboard!B25,'Compilado chamados'!L:L,"EM ANDAMENTO") -> 5 | F25: =COUNTIFS('Compilado chamados'!B:B,Dashboard!B25,'Compilado chamados'!Y:Y,"Aberto") -> 37 | G25: =COUNTIFS('Compilado chamados'!B:B,Dashboard!B25,'Compilado chamados'!M:M,"Alta") -> 14
B26: Amanda Silva | C26: =COUNTIFS('Compilado chamados'!B:B,Dashboard!B26,'Compilado chamados'!Y:Y,"Encerrado") -> 40 | D26: =COUNTIFS( 'Compilado chamados'!B:B,Dashboard!B26, 'Compilado chamados'!Y:Y,"Encerrado", 'Compilado chamados'!X:X,">="&TODAY()-7, 'Compilado chamados'!X:X,"<"&TODAY()+1 ) -> 10 | E26: =COUNTIFS('Compilado chamados'!B:B,Dashboard!B26,'Compilado chamados'!L:L,"EM ANDAMENTO") -> 4 | F26: =COUNTIFS('Compilado chamados'!B:B,Dashboard!B26,'Compilado chamados'!Y:Y,"Aberto") -> 25 | G26: =COUNTIFS('Compilado chamados'!B:B,Dashboard!B26,'Compilado chamados'!M:M,"Alta") -> 6
B29: Atendidos nos Últimos 7 Dias
B30: Data | C30: Dia da Semana | D30: Atendidos
B31: =TODAY()-7 -> 46283 | C31: =TEXT(B31,"ddd") -> sex | D31: =COUNTIFS('Compilado chamados'!$Y$5:$Y$1048576,"Encerrado",'Compilado chamados'!$X$5:$X$1048576,B31) -> 4 | N31: Origem Chamados
B32: =TODAY()-6 -> 46284 | C32: =TEXT(B32,"ddd") -> sáb | D32: =COUNTIFS('Compilado chamados'!$Y$5:$Y$1048576,"Encerrado",'Compilado chamados'!$X$5:$X$1048576,B32) -> 0 | N32: Interno | O32: =COUNTIF('Compilado chamados'!AB:AB,N32) -> 195
B33: =TODAY()-5 -> 46285 | C33: =TEXT(B33,"ddd") -> dom | D33: =COUNTIFS('Compilado chamados'!$Y$5:$Y$1048576,"Encerrado",'Compilado chamados'!$X$5:$X$1048576,B33) -> 0 | N33: Externo | O33: =COUNTIF('Compilado chamados'!AB:AB,N33) -> 214
B34: =TODAY()-4 -> 46286 | C34: =TEXT(B34,"ddd") -> seg | D34: =COUNTIFS('Compilado chamados'!$Y$5:$Y$1048576,"Encerrado",'Compilado chamados'!$X$5:$X$1048576,B34) -> 2
B35: =TODAY()-3 -> 46287 | C35: =TEXT(B35,"ddd") -> ter | D35: =COUNTIFS('Compilado chamados'!$Y$5:$Y$1048576,"Encerrado",'Compilado chamados'!$X$5:$X$1048576,B35) -> 10
B36: =TODAY()-2 -> 46288 | C36: =TEXT(B36,"ddd") -> qua | D36: =COUNTIFS('Compilado chamados'!$Y$5:$Y$1048576,"Encerrado",'Compilado chamados'!$X$5:$X$1048576,B36) -> 5
B37: =TODAY()-1 -> 46289 | C37: =TEXT(B37,"ddd") -> qui | D37: =COUNTIFS('Compilado chamados'!$Y$5:$Y$1048576,"Encerrado",'Compilado chamados'!$X$5:$X$1048576,B37) -> 5
B38: Total 7 dias | D38: =SUM(D31:D37) -> 26

Sheet Resumo p. Respónsável
A1: Chamados em aberto por Categoria/Responsável | D1: Atendimento por Dia/Responsável
A3: Status | B3: (Vários itens) | D3: Status | E3: FINALIZADO
A5: Rótulos de Linha | B5: Contagem de Número do Chamado | D5: Contagem de Número do Chamado | E5: Rótulos de Coluna
A6: Emilly Maria | B6: 35 | E6: <09/01/2026 | F6: jan | G6: mar | H6: abr | I6: mai | J6: jul | AA6: jul Total | AB6: ago | AT6: ago Total | AU6: set | BK6: set Total | BL6: Total Geral
A7: Atendimento Administrativo e Suporte | B7: 3 | J7: 10/jul | K7: 11/jul | L7: 13/jul | M7: 14/jul | N7: 15/jul | O7: 16/jul | P7: 17/jul | Q7: 20/jul | R7: 21/jul | S7: 22/jul | T7: 23/jul | U7: 24/jul | V7: 27/jul | W7: 28/jul | X7: 29/jul | Y7: 30/jul | Z7: 31/jul | AB7: 03/ago | AC7: 04/ago | AD7: 05/ago | AE7: 06/ago | AF7: 07/ago | AG7: 08/ago | AH7: 10/ago | AI7: 11/ago | AJ7: 12/ago | AK7: 13/ago | AL7: 14/ago | AM7: 18/ago | AN7: 20/ago | AO7: 24/ago | AP7: 25/ago | AQ7: 26/ago | AR7: 27/ago | AS7: 28/ago | AU7: 02/set | AV7: 03/set | AW7: 04/set | AX7: 08/set | AY7: 09/set | AZ7: 10/set | BA7: 11/set | BB7: 14/set | BC7: 15/set | BD7: 16/set | BE7: 17/set | BF7: 18/set | BG7: 21/set | BH7: 22/set | BI7: 23/set | BJ7: 24/set
A8: Cancelamento e Reemissão de Nota Fiscal | B8: 13 | D8: Rótulos de Linha
A9: Cobrança e Contestação | B9: 8 | D9: Emilly Maria | G9: 1 | I9: 1 | M9: 3 | N9: 1 | O9: 2 | P9: 2 | Q9: 1 | S9: 1 | T9: 2 | X9: 1 | Y9: 6 | Z9: 4 | AA9: 23 | AC9: 1 | AD9: 1 | AE9: 9 | AF9: 3 | AH9: 3 | AI9: 5 | AK9: 1 | AL9: 5 | AM9: 1 | AO9: 3 | AP9: 2 | AQ9: 1 | AT9: 35 | AU9: 1 | AV9: 3 | AW9: 2 | AX9: 2 | AZ9: 1 | BA9: 2 | BC9: 1 | BH9: 5 | BI9: 1 | BJ9: 2 | BK9: 20 | BL9: 80
A10: Contratos, Comercial e Cadastro | B10: 3 | D10: Fabiana Lisboa | T10: 1 | U10: 2 | V10: 2 | W10: 1 | X10: 2 | Y10: 4 | AA10: 12 | AE10: 2 | AH10: 1 | AI10: 4 | AL10: 1 | AT10: 8 | BL10: 20
A11: Faturamento e Obrigações Fiscais | B11: 2 | D11: Pamela de Sá | P11: 1 | R11: 1 | S11: 1 | T11: 1 | W11: 2 | X11: 1 | Y11: 2 | Z11: 1 | AA11: 10 | AE11: 6 | AG11: 3 | AO11: 1 | AP11: 3 | AS11: 1 | AT11: 14 | AU11: 1 | BC11: 2 | BK11: 3 | BL11: 27
A12: Pagamentos, Boletos e Recebimentos | B12: 6 | D12: Stephany Lima | F12: 1 | H12: 1 | I12: 1 | J12: 1 | L12: 8 | M12: 2 | N12: 3 | Q12: 1 | R12: 1 | T12: 1 | U12: 1 | X12: 3 | Y12: 3 | Z12: 1 | AA12: 25 | AC12: 3 | AD12: 1 | AE12: 3 | AF12: 4 | AH12: 5 | AI12: 4 | AJ12: 5 | AN12: 2 | AQ12: 1 | AT12: 28 | AU12: 1 | AV12: 3 | AW12: 1 | AX12: 4 | AY12: 1 | BB12: 2 | BD12: 2 | BE12: 1 | BG12: 1 | BH12: 4 | BI12: 1 | BJ12: 1 | BK12: 22 | BL12: 78
A13: Pamela de Sá | B13: 36 | D13: Vanessa Araujo | K13: 1 | U13: 1 | W13: 1 | Y13: 1 | AA13: 4 | AH13: 1 | AI13: 1 | AQ13: 1 | AT13: 3 | BF13: 1 | BK13: 1 | BL13: 8
A14: Atendimento Administrativo e Suporte | B14: 4 | D14: Amanda Silva | E14: 1 | I14: 1 | AB14: 1 | AC14: 2 | AD14: 1 | AE14: 1 | AR14: 3 | AT14: 8 | AU14: 6 | AW14: 1 | AX14: 1 | BA14: 3 | BB14: 2 | BC14: 7 | BD14: 1 | BF14: 3 | BG14: 1 | BH14: 1 | BI14: 3 | BJ14: 1 | BK14: 30 | BL14: 40
A15: Cancelamento e Reemissão de Nota Fiscal | B15: 9 | D15: Total Geral | E15: 1 | F15: 1 | G15: 1 | H15: 1 | I15: 3 | J15: 1 | K15: 1 | L15: 8 | M15: 5 | N15: 4 | O15: 2 | P15: 3 | Q15: 2 | R15: 2 | S15: 2 | T15: 5 | U15: 4 | V15: 2 | W15: 4 | X15: 7 | Y15: 16 | Z15: 6 | AA15: 74 | AB15: 1 | AC15: 6 | AD15: 3 | AE15: 21 | AF15: 7 | AG15: 3 | AH15: 10 | AI15: 14 | AJ15: 5 | AK15: 1 | AL15: 6 | AM15: 1 | AN15: 2 | AO15: 4 | AP15: 5 | AQ15: 3 | AR15: 3 | AS15: 1 | AT15: 96 | AU15: 9 | AV15: 6 | AW15: 4 | AX15: 7 | AY15: 1 | AZ15: 1 | BA15: 5 | BB15: 4 | BC15: 10 | BD15: 3 | BE15: 1 | BF15: 4 | BG15: 2 | BH15: 10 | BI15: 5 | BJ15: 4 | BK15: 76 | BL15: 253
A16: Cobrança e Contestação | B16: 8
A17: Contratos, Comercial e Cadastro | B17: 6
A18: Faturamento e Obrigações Fiscais | B18: 4
A19: Pagamentos, Boletos e Recebimentos | B19: 4
A20: #N/D | B20: 1
A21: Stephany Lima | B21: 57
A22: Atendimento Administrativo e Suporte | B22: 1
A23: Cancelamento e Reemissão de Nota Fiscal | B23: 25
A24: Cobrança e Contestação | B24: 19
A25: Contratos, Comercial e Cadastro | B25: 5
A26: Faturamento e Obrigações Fiscais | B26: 2
A27: Pagamentos, Boletos e Recebimentos | B27: 5
... A35: Total Geral | B35: 148

Sheet D.As
E1: Solicitação | O1: Aprovação 1° nivel (Everton | R1: Aprovação 2° nivel (Tatebe) | U1: Aprovação 3° nivel (Calil)
B2: # | C2: Concluído | D2: Status | E2: Data | F2: Assunto e-mail | G2: Chamado | H2: D.A Comercial | I2: Natureza | J2: Contexto | K2: R$ | L2: Solicitante | M2: Ofensor | N2: Alçada necessária | O2: Data2 | P2: Aprovador | Q2: Obs | R2: Data4 | S2: Aprovador5 | T2: Obs6 | U2: Data7 | V2: Aprovador8 | W2: Obs9
B3: 1 | C3: FALSE | D3: =IF(AND(P3="OK",OR(S3="OK",S3="N/A"),OR(V3="OK",V3="N/A")),"Aprovado",IF(OR(P3="Reprovado",S3="Reprovado",V3="Reprovado"),"Reprovado","Pendente")) -> Aprovado | E3: 46231 | F3: Aprovação - Cancelamento de notas - MOITINHO AUTOMOVEIS LTDA 22.134.988/0001-14 - 20192438 | G3: =RIGHT(Tabela1[[#This Row],[Assunto e-mail]],8) -> 20192438 | H3: OK | I3: Cancelamento de NF | J3: Erro sistemico, o SF enviou ao billing tarifa diferente do contrato | K3: 36586.11 | L3: Fabiana | N3: =IF(K3<10000,"Everton",IF(K3<=50000,"Everton + Tatebe","Everton + Tatebe + Calil")) -> Everton + Tatebe | O3: 46232 | P3: OK | Q3: - | R3: 46259 | S3: OK | T3: =IF(K3<10000,"N/A","-") -> - | U3: =IF(K3<=50000,"N/A","") -> N/A | V3: =IF(K3<=50000,"N/A","") -> N/A | W3: =IF(K3<=50000,"N/A","-") -> N/A
B4: =B3+1 -> 2 | C4: FALSE | D4: =IF(AND(P4="OK",OR(S4="OK",S4="N/A"),OR(V4="OK",V4="N/A")),"Aprovado",IF(OR(P4="Reprovado",S4="Reprovado",V4="Reprovado"),"Reprovado","Pendente")) -> Aprovado | E4: 46232 | F4: Aprovação - Cancelamento de notas - OBJETIVO 1220 COMERCIO DE COSMETICO-30.318.916/0001-55 | 21602868 | G4: =RIGHT(Tabela1[[#This Row],[Assunto e-mail]],8) -> 21602868 | H4: OK | I4: Cancelamento de NF | J4: Estrategia comercial, cancelamento de 2 meses como desconto para o cliente | K4: 16214.4 | L4: Emilly | N4: =IF(K4<10000,"Everton",IF(K4<=50000,"Everton + Tatebe","Everton + Tatebe + Calil")) -> Everton + Tatebe | O4: 46233 | P4: OK | Q4: - | R4: 46244 | S4: OK | T4: =IF(K4<10000,"N/A","-") -> - | U4: =IF(K4<=50000,"N/A","") -> N/A | V4: =IF(K4<=50000,"N/A","") -> N/A | W4: =IF(K4<=50000,"N/A","-") -> N/A
B5: =B4+1 -> 3 | C5: FALSE | D5: =IF(AND(P5="OK",OR(S5="OK",S5="N/A"),OR(V5="OK",V5="N/A")),"Aprovado",IF(OR(P5="Reprovado",S5="Reprovado",V5="Reprovado"),"Reprovado","Pendente")) -> Aprovado | E5: 46232 | F5: Aprovação - Cancelamento de notas - ELO CONSULTORIA E SOLUCOES LTDA-54.709.015/0001-52 | 22101893 | G5: =RIGHT(Tabela1[[#This Row],[Assunto e-mail]],8) -> 22101893 | H5: OK | I5: Cancelamento de NF | J5: Contrato fora do padrão, cobrança de ISS padrão que não consta no contrato | K5: 8163.27 | L5: Emilly | N5: =IF(K5<10000,"Everton",IF(K5<=50000,"Everton + Tatebe","Everton + Tatebe + Calil")) -> Everton | O5: 46233 | P5: OK | Q5: - | R5: =IF(K5<10000,"N/A","") -> N/A | S5: =IF(K5<10000,"N/A","") -> N/A | T5: =IF(K5<10000,"N/A","-") -> N/A | U5: =IF(K5<=50000,"N/A","") -> N/A | V5: =IF(K5<=50000,"N/A","") -> N/A | W5: =IF(K5<=50000,"N/A","-") -> N/A
B6: =B5+1 -> 4 | C6: FALSE | D6: =IF(AND(P6="OK",OR(S6="OK",S6="N/A"),OR(V6="OK",V6="N/A")),"Aprovado",IF(OR(P6="Reprovado",S6="Reprovado",V6="Reprovado"),"Reprovado","Pendente")) -> Aprovado | E6: 46226 | F6: Aprovação - Cancelamento de notas - ELEVE DISTRIBUIDORA DE PRODUTOS NUTRICOSMETICOS LTDA-31.178.848/0001-39 |21338462 | G6: =RIGHT(Tabela1[[#This Row],[Assunto e-mail]],8) -> 21338462 | H6: OK | I6: Cancelamento de NF | J6: Cancelamento não tempestivo pela comercial na tentativa de reverter a decisão do cliente | K6: 178.42 | L6: Emilly | N6: =IF(K6<10000,"Everton",IF(K6<=50000,"Everton + Tatebe","Everton + Tatebe + Calil")) -> Everton | O6: 46233 | P6: OK | Q6: - | R6: =IF(K6<10000,"N/A","") -> N/A | S6: =IF(K6<10000,"N/A","") -> N/A | T6: =IF(K6<10000,"N/A","-") -> N/A | U6: =IF(K6<=50000,"N/A","") -> N/A | V6: =IF(K6<=50000,"N/A","") -> N/A | W6: =IF(K6<=50000,"N/A","-") -> N/A
B7: =B6+1 -> 5 | C7: FALSE | D7: =IF(AND(P7="OK",OR(S7="OK",S7="N/A"),OR(V7="OK",V7="N/A")),"Aprovado",IF(OR(P7="Reprovado",S7="Reprovado",V7="Reprovado"),"Reprovado","Pendente")) -> Aprovado | E7: 46231 | F7: Aprovação - Cancelamento de notas - DIRETIVA IMPORTACAO E DISTRIBUICAO- 52.833.913/0001-92 | 23024837 | G7: =RIGHT(Tabela1[[#This Row],[Assunto e-mail]],8) -> 23024837 | H7: OK | I7: Cancelamento de NF | J7: Erro sistemico, após o cancelamento do cliente houve cobrança do Min. Mensal | K7: 6428.58 | L7: Emilly | N7: =IF(K7<10000,"Everton",IF(K7<=50000,"Everton + Tatebe","Everton + Tatebe + Calil")) -> Everton | O7: 46233 | P7: OK | Q7: - | R7: =IF(K7<10000,"N/A","") -> N/A | S7: =IF(K7<10000,"N/A","") -> N/A | T7: =IF(K7<10000,"N/A","-") -> N/A | U7: =IF(K7<=50000,"N/A","") -> N/A | V7: =IF(K7<=50000,"N/A","") -> N/A | W7: =IF(K7<=50000,"N/A","-") -> N/A
B8: =B7+1 -> 6 | C8: FALSE | D8: =IF(AND(P8="OK",OR(S8="OK",S8="N/A"),OR(V8="OK",V8="N/A")),"Aprovado",IF(OR(P8="Reprovado",S8="Reprovado",V8="Reprovado"),"Reprovado","Pendente")) -> Pendente | E8: 46212 | F8: Aprovar o cancelamento de NFs | Cliente: WISHPAG LTDA - Chamado 18915650 | G8: =RIGHT(Tabela1[[#This Row],[Assunto e-mail]],8) -> 18915650 | H8: OK | I8: Cancelamento de NF | J8: Cancelamento não tempestivo pela comercial | K8: 160574.6 | L8: Vanessa | N8: =IF(K8<10000,"Everton",IF(K8<=50000,"Everton + Tatebe","Everton + Tatebe + Calil")) -> Everton + Tatebe + Calil | O8: 46216 | P8: OK | Q8: - | R8: 46226 | S8: OK | T8: =IF(K8<10000,"N/A","-") -> - | U8: =IF(K8<=50000,"N/A","") | V8: =IF(K8<=50000,"N/A","") | W8: =IF(K8<=50000,"N/A","-") -> -
B9: =B8+1 -> 7 | C9: FALSE | D9: =IF(AND(P9="OK",OR(S9="OK",S9="N/A"),OR(V9="OK",V9="N/A")),"Aprovado",IF(OR(P9="Reprovado",S9="Reprovado",V9="Reprovado"),"Reprovado","Pendente")) -> Aprovado | E9: 46233 | F9: Aprovação - Cancelamento de notas -ALFA AGENCIA DE VIAGENS LTDA - 07.141.168/0001-66 | 19467525 | G9: =RIGHT(Tabela1[[#This Row],[Assunto e-mail]],8) -> 19467525 | H9: N/A | I9: Cancelamento de NF | J9: Solicitação vencida, chamado de congeladomento do contrato após a emissão da NF | K9: 4636.73 | L9: Emilly | N9: =IF(K9<10000,"Everton",IF(K9<=50000,"Everton + Tatebe","Everton + Tatebe + Calil")) -> Everton | O9: 46233 | P9: OK | Q9: - | R9: =IF(K9<10000,"N/A","") -> N/A | S9: =IF(K9<10000,"N/A","") -> N/A | T9: =IF(K9<10000,"N/A","-") -> N/A | U9: =IF(K9<=50000,"N/A","") -> N/A | V9: =IF(K9<=50000,"N/A","") -> N/A | W9: =IF(K9<=50000,"N/A","-") -> N/A
B10: =B9+1 -> 8 | C10: FALSE | D10: =IF(AND(P10="OK",OR(S10="OK",S10="N/A"),OR(V10="OK",V10="N/A")),"Aprovado",IF(OR(P10="Reprovado",S10="Reprovado",V10="Reprovado"),"Reprovado","Pendente")) -> Pendente | E10: 46227 | F10: Aprovação - Cancelamento de notas - NEXTION PAY TECNOLOGIA LTDA 50.726.492/0001-75 - 21573732 | G10: =RIGHT(Tabela1[[#This Row],[Assunto e-mail]],8) -> 21573732 | H10: OK | I10: Cancelamento de NF | J10: Solicitação de cancelamento não efetivada, gerando emissão indevida de NFs para cliente identificado como fraude. | K10: 156876.52 | L10: Fabiana/ Vanessa | N10: =IF(K10<10000,"Everton",IF(K10<=50000,"Everton + Tatebe","Everton + Tatebe + Calil")) -> Everton + Tatebe + Calil | O10: 46241 | P10: OK | Q10: Sob revisão do texto | R10: =IF(K10<10000,"N/A","") | S10: =IF(K10<10000,"N/A","") | T10: =IF(K10<10000,"N/A","-") -> - | U10: =IF(K10<=50000,"N/A","") | V10: =IF(K10<=50000,"N/A","") | W10: =IF(K10<=50000,"N/A","-") -> -
B11: =B10+1 -> 9 | C11: FALSE | D11: =IF(AND(P11="OK",OR(S11="OK",S11="N/A"),OR(V11="OK",V11="N/A")),"Aprovado",IF(OR(P11="Reprovado",S11="Reprovado",V11="Reprovado"),"Reprovado","Pendente")) -> Aprovado | E11: 46227 | F11: Aprovação - Cancelamento de notas - VOAI TECH LTDA-17.891.555/0001-73 | 21029459 | G11: =RIGHT(Tabela1[[#This Row],[Assunto e-mail]],8) -> 21029459 | H11: OK | I11: Cancelamento de NF | J11: Cadastro incorreto, o SF envio para o Billing produtos que não estão em contrato | K11: 1840.8 | L11: Emilly | N11: =IF(K11<10000,"Everton",IF(K11<=50000,"Everton + Tatebe","Everton + Tatebe + Calil")) -> Everton | O11: 46233 | P11: OK | Q11: - | R11: =IF(K11<10000,"N/A","") -> N/A | S11: =IF(K11<10000,"N/A","") -> N/A | T11: =IF(K11<10000,"N/A","-") -> N/A | U11: =IF(K11<=50000,"N/A","") -> N/A | V11: =IF(K11<=50000,"N/A","") -> N/A | W11: =IF(K11<=50000,"N/A","-") -> N/A
B12: =B11+1 -> 10 | C12: FALSE | D12: =IF(AND(P12="OK",OR(S12="OK",S12="N/A"),OR(V12="OK",V12="N/A")),"Aprovado",IF(OR(P12="Reprovado",S12="Reprovado",V12="Reprovado"),"Reprovado","Pendente")) -> Aprovado | E12: 46217 | F12: Aprovação - Cancelamento de notas fiscais - FAROL COMUNICACAO E SERVICOS DE INFORMATICA LTDA 21.011.165/0001-39 - 21124852 | G12: =RIGHT(Tabela1[[#This Row],[Assunto e-mail]],8) -> 21124852 | H12: OK | I12: Cancelamento de NF | J12: Cancelamento não tempestivo pela comercial na tentativa de reverter a decisão do cliente | K12: =3*973.14+174.54 -> 3093.96 | L12: Stephany | N12: =IF(K12<10000,"Everton",IF(K12<=50000,"Everton + Tatebe","Everton + Tatebe + Calil")) -> Everton | O12: 46233 | P12: OK | Q12: - | R12: =IF(K12<10000,"N/A","") -> N/A | S12: =IF(K12<10000,"N/A","") -> N/A | T12: =IF(K12<10000,"N/A","-") -> N/A | U12: =IF(K12<=50000,"N/A","") -> N/A | V12: =IF(K12<=50000,"N/A","") -> N/A | W12: =IF(K12<=50000,"N/A","-") -> N/A
B13: =B12+1 -> 11 | C13: FALSE | D13: =IF(AND(P13="OK",OR(S13="OK",S13="N/A"),OR(V13="OK",V13="N/A")),"Aprovado",IF(OR(P13="Reprovado",S13="Reprovado",V13="Reprovado"),"Reprovado","Pendente")) -> Aprovado | E13: 46162 | F13: Aprovação - Cancelamento de notas - PLANNE SOFTWARE LTDA-28.580.044/0001-57 |20697638 | G13: =RIGHT(Tabela1[[#This Row],[Assunto e-mail]],8) -> 20697638 | H13: OK | I13: Cancelamento de NF | J13: O cliente foi cobrado por um serviço que não chegou a ser implantado nem utilizado devido a falhas na integração e ausência de suporte. | K13: 6020.08 | L13: Emilly | N13: =IF(K13<10000,"Everton",IF(K13<=50000,"Everton + Tatebe","Everton + Tatebe + Calil")) -> Everton | O13: 46241 | P13: OK | R13: =IF(K13<10000,"N/A","") -> N/A | S13: =IF(K13<10000,"N/A","") -> N/A | T13: =IF(K13<10000,"N/A","-") -> N/A | U13: =IF(K13<=50000,"N/A","") -> N/A | V13: =IF(K13<=50000,"N/A","") -> N/A | W13: =IF(K13<=50000,"N/A","-") -> N/A
B14: =B13+1 -> 12 | C14: FALSE | D14: =IF(AND(P14="OK",OR(S14="OK",S14="N/A"),OR(V14="OK",V14="N/A")),"Aprovado",IF(OR(P14="Reprovado",S14="Reprovado",V14="Reprovado"),"Reprovado","Pendente")) -> Pendente | E14: 46232 | F14: Aprovação - Cancelamento de notas - AMERICANAS S.A - EM RECUPERACAO JUD 00.776.574/2019-92 - 23457203 | G14: =RIGHT(Tabela1[[#This Row],[Assunto e-mail]],8) -> 23457203 | H14: OK | I14: Cancelamento de NF | J14: Após a alteração de CNPJ, o cliente ficou impossibilitado de realizar os pagamentos, gerando as NFs em discussão para cancelamento até a conclusão do termo de cessão. | K14: 50579.53 | L14: Vanessa | N14: =IF(K14<10000,"Everton",IF(K14<=50000,"Everton + Tatebe","Everton + Tatebe + Calil")) -> Everton + Tatebe + Calil | O14: 46241 | P14: OK | R14: 46248 | S14: OK | T14: =IF(K14<10000,"N/A","-") -> - | U14: =IF(K14<=50000,"N/A","") | V14: =IF(K14<=50000,"N/A","") | W14: =IF(K14<=50000,"N/A","-") -> -
B15: =B14+1 -> 13 | C15: FALSE | D15: =IF(AND(P15="OK",OR(S15="OK",S15="N/A"),OR(V15="OK",V15="N/A")),"Aprovado",IF(OR(P15="Reprovado",S15="Reprovado",V15="Reprovado"),"Reprovado","Pendente")) -> Aprovado | E15: 46232 | F15: Aprovação - Cancelamento de notas - GOODSTORAGE HOLDING PARTICIPACOES -18.897.459/0001-03 | 25248269 | G15: =RIGHT(Tabela1[[#This Row],[Assunto e-mail]],8) -> 25248269 | H15: OK | I15: Cancelamento de NF | J15: Erro sistêmico | K15: 19897.96 | L15: Emilly | N15: =IF(K15<10000,"Everton",IF(K15<=50000,"Everton + Tatebe","Everton + Tatebe + Calil")) -> Everton + Tatebe | O15: 46241 | P15: OK | R15: 46255 | S15: OK | T15: =IF(K15<10000,"N/A","-") -> - | U15: =IF(K15<=50000,"N/A","") -> N/A | V15: =IF(K15<=50000,"N/A","") -> N/A | W15: =IF(K15<=50000,"N/A","-") -> N/A
B16: =B15+1 -> 14 | C16: FALSE | D16: =IF(AND(P16="OK",OR(S16="OK",S16="N/A"),OR(V16="OK",V16="N/A")),"Aprovado",IF(OR(P16="Reprovado",S16="Reprovado",V16="Reprovado"),"Reprovado","Pendente")) -> Aprovado | E16: 46234 | F16: Aprovação - Cancelamento de notas - GSE COMERCIO DE ROUPAS LTDA-22.675.768/0001-06 | 18822614 | G16: =RIGHT(Tabela1[[#This Row],[Assunto e-mail]],8) -> 18822614 | H16: OK | I16: Cancelamento de NF | J16: Solicitação de cancelamento integral não tratada corretamente, resultando em cobrança indevida após janeiro/2025. | K16: 12425.86 | L16: Emilly | N16: =IF(K16<10000,"Everton",IF(K16<=50000,"Everton + Tatebe","Everton + Tatebe + Calil")) -> Everton + Tatebe | O16: 46241 | P16: OK | R16: 46255 | S16: OK | T16: =IF(K16<10000,"N/A","-") -> - | U16: =IF(K16<=50000,"N/A","") -> N/A | V16: =IF(K16<=50000,"N/A","") -> N/A | W16: =IF(K16<=50000,"N/A","-") -> N/A
B17: =B16+1 -> 15 | C17: FALSE | D17: =IF(AND(P17="OK",OR(S17="OK",S17="N/A"),OR(V17="OK",V17="N/A")),"Aprovado",IF(OR(P17="Reprovado",S17="Reprovado",V17="Reprovado"),"Reprovado","Pendente")) -> Aprovado | E17: 46239 | F17: Aprovação - Cancelamento de notas-LUX INVEST CAPITAL LTDA- 34.383.831/0001-01 | 25264548- 25247817 | G17: =RIGHT(Tabela1[[#This Row],[Assunto e-mail]],8) -> 25247817 | H17: OK | I17: Cancelamento de NF | J17: Duplicidade contratual gerou faturamento indevido ao cliente. O contrato de produtos foi cancelado, mantendo apenas o Split ativo. Solicita-se o cancelamento de 9 NFs emitidas por erro comercial, incluindo a multa contratual. | K17: 45000 | L17: Emilly | N17: =IF(K17<10000,"Everton",IF(K17<=50000,"Everton + Tatebe","Everton + Tatebe + Calil")) -> Everton + Tatebe | O17: 46241 | P17: OK | R17: 46244 | S17: OK | T17: =IF(K17<10000,"N/A","-") -> - | U17: =IF(K17<=50000,"N/A","") -> N/A | V17: =IF(K17<=50000,"N/A","") -> N/A | W17: =IF(K17<=50000,"N/A","-") -> N/A
B18: =B17+1 -> 16 | C18: FALSE | D18: =IF(AND(P18="OK",OR(S18="OK",S18="N/A"),OR(V18="OK",V18="N/A")),"Aprovado",IF(OR(P18="Reprovado",S18="Reprovado",V18="Reprovado"),"Reprovado","Pendente")) -> Aprovado | E18: 46240 | F18: Aprovação - Cancelamento de notas -PHARMADELLE FORMULAS LTDA- 21.570.535/0001-78 | 19809905 | G18: 19809905 | H18: OK | I18: Cancelamento de NF | J18: O cliente solicitou o cancelamento em outubro/2023, entretanto, o processo não foi realizado. | K18: 3244.62 | L18: Emilly | N18: =IF(K18<10000,"Everton",IF(K18<=50000,"Everton + Tatebe","Everton + Tatebe + Calil")) -> Everton | O18: 46241 | P18: OK | R18: =IF(K18<10000,"N/A","") -> N/A | S18: =IF(K18<10000,"N/A","") -> N/A | T18: =IF(K18<10000,"N/A","-") -> N/A | U18: =IF(K18<=50000,"N/A","") -> N/A | V18: =IF(K18<=50000,"N/A","") -> N/A | W18: =IF(K18<=50000,"N/A","-") -> N/A
B19: =B18+1 -> 17 | C19: FALSE | D19: =IF(AND(P19="OK",OR(S19="OK",S19="N/A"),OR(V19="OK",V19="N/A")),"Aprovado",IF(OR(P19="Reprovado",S19="Reprovado",V19="Reprovado"),"Reprovado","Pendente")) -> Pendente | E19: 46241 | F19: Aprovação - Cancelamento de notas -MAGALUPAY INSTITUICAO DE PAGAMENTO- 13.884.775/0001-19 |25319444 | G19: =RIGHT(Tabela1[[#This Row],[Assunto e-mail]],8) -> 25319444 | H19: OK | I19: Cancelamento de NF | J19: Cancelamento solicitado em decorrência da ausência de solicitação tempestiva de cancelamento do produto, impossibilitando o cancelamento da NF dentro do prazo legal. | K19: 48773.21 | L19: Emilly | M19: Comercial | N19: =IF(K19<10000,"Everton",IF(K19<=50000,"Everton + Tatebe","Everton + Tatebe + Calil")) -> Everton + Tatebe | R19: 46248 | S19: OK | T19: =IF(K19<10000,"N/A","-") -> - | U19: =IF(K19<=50000,"N/A","") -> N/A | V19: =IF(K19<=50000,"N/A","") -> N/A | W19: =IF(K19<=50000,"N/A","-") -> N/A
B20: =B19+1 -> 18 | C20: FALSE | D20: =IF(AND(P20="OK",OR(S20="OK",S20="N/A"),OR(V20="OK",V20="N/A")),"Aprovado",IF(OR(P20="Reprovado",S20="Reprovado",V20="Reprovado"),"Reprovado","Pendente")) -> Aprovado | E20: 46239 | F20: Aprovação - Cancelamento de notas - VOLTATTO SUPRIMENTOS LTDA- 59.557.054/0001-03 | 24289294 | G20: =RIGHT(Tabela1[[#This Row],[Assunto e-mail]],8) -> 24289294 | I20: Cancelamento de NF | J20: Identificamos que, em decorrência de um erro sistêmico, a nota foi emitida em duplicidade. | K20: 248.98 | L20: Emilly | M20: Financeiro | N20: =IF(K20<10000,"Everton",IF(K20<=50000,"Everton + Tatebe","Everton + Tatebe + Calil")) -> Everton | O20: 46267 | P20: OK | R20: =IF(K20<10000,"N/A","") -> N/A | S20: =IF(K20<10000,"N/A","") -> N/A | T20: =IF(K20<10000,"N/A","-") -> N/A | U20: =IF(K20<=50000,"N/A","") -> N/A | V20: =IF(K20<=50000,"N/A","") -> N/A | W20: =IF(K20<=50000,"N/A","-") -> N/A
B21: =B20+1 -> 19 | C21: FALSE | D21: =IF(AND(P21="OK",OR(S21="OK",S21="N/A"),OR(V21="OK",V21="N/A")),"Aprovado",IF(OR(P21="Reprovado",S21="Reprovado",V21="Reprovado"),"Reprovado","Pendente")) -> Pendente | E21: 46247 | F21: Aprovação - Cancelamento de notas - GIORDANI TURISMO LTDA | Chamado: 2620110481154 | G21: 24912277 | H21: OK | I21: Cancelamento de NF | J21: A área de Cobrança identificou que a NF 0118088 foi emitida em duplicidade para o cliente GIORDANI TURISMO LTDA. Conforme validação realizada pela equipe responsável, a nota correta é a NF 0118002 | K21: 6266.85 | L21: Fabiana | M21: Financeiro | N21: =IF(K21<10000,"Everton",IF(K21<=50000,"Everton + Tatebe","Everton + Tatebe + Calil")) -> Everton | R21: 46248 | S21: OK | T21: =IF(K21<10000,"N/A","-") -> N/A | U21: =IF(K21<=50000,"N/A","") -> N/A | V21: =IF(K21<=50000,"N/A","") -> N/A | W21: =IF(K21<=50000,"N/A","-") -> N/A
B22: =B21+1 -> 20 | C22: FALSE | D22: =IF(AND(P22="OK",OR(S22="OK",S22="N/A"),OR(V22="OK",V22="N/A")),"Aprovado",IF(OR(P22="Reprovado",S22="Reprovado",V22="Reprovado"),"Reprovado","Pendente")) -> Pendente | E22: 46260 | F22: Cancelamento de NF COMERC FINANCIAL TRADING COMERCIALIZADORA DE ENERGIA LTDA | I22: Cancelamento de NF | J22: O cliente possui dois CNPJs, porém o contrato vigente está vinculado apenas a um deles. Por equívoco, a nota fiscal de setup foi emitida também para o CNPJ sem relação contratual ativa. | K22: 4236.49 | L22: Pamela | M22: Financeiro | N22: =IF(K22<10000,"Everton",IF(K22<=50000,"Everton + Tatebe","Everton + Tatebe + Calil")) -> Everton | R22: =IF(K22<10000,"N/A","") -> N/A | S22: =IF(K22<10000,"N/A","") -> N/A | T22: =IF(K22<10000,"N/A","-") -> N/A | U22: =IF(K22<=50000,"N/A","") -> N/A | V22: =IF(K22<=50000,"N/A","") -> N/A | W22: =IF(K22<=50000,"N/A","-") -> N/A
B23: =B22+1 -> 21 | C23: TRUE | D23: =IF(AND(P23="OK",OR(S23="OK",S23="N/A"),OR(V23="OK",V23="N/A")),"Aprovado",IF(OR(P23="Reprovado",S23="Reprovado",V23="Reprovado"),"Reprovado","Pendente")) -> Aprovado | E23: 46259 | F23: Aprovação - Cancelamento de notas - CENTRO CULTURAL AFRORIO - 11.697.918/0001-58 | 25578004 | G23: =RIGHT(Tabela1[[#This Row],[Assunto e-mail]],8) -> 25578004 | H23: OK | I23: Cancelamento de NF | J23: O contrato foi cancelado e houve aprovação formal da área comercial para o cancelamento integral das cobranças. O cadastro do cliente foi encerrado por decisão interna decorrente de apontamentos de risco identificados impossibilitando a continuidade da relação comercial. | K23: 18428.78 | L23: Amanda | M23: Comercial | N23: =IF(K23<10000,"Everton",IF(K23<=50000,"Everton + Tatebe","Everton + Tatebe + Calil")) -> Everton + Tatebe | O23: 46267 | P23: OK | R23: 46279 | S23: OK | T23: =IF(K23<10000,"N/A","-") -> - | U23: =IF(K23<=50000,"N/A","") -> N/A | V23: =IF(K23<=50000,"N/A","") -> N/A | W23: =IF(K23<=50000,"N/A","-") -> N/A
B24: =B23+1 -> 22 | C24: TRUE | D24: =IF(AND(P24="OK",OR(S24="OK",S24="N/A"),OR(V24="OK",V24="N/A")),"Aprovado",IF(OR(P24="Reprovado",S24="Reprovado",V24="Reprovado"),"Reprovado","Pendente")) -> Aprovado | E24: 46259 | F24: Aprovação - Cancelamento de notas - UNINTER EDUCACIONAL S/A - 02.261.854/0001-57 | 26341250 | G24: =RIGHT(Tabela1[[#This Row],[Assunto e-mail]],8) -> 26341250 | H24: OK | I24: Cancelamento de NF | J24: O cliente formalizou o pedido de cancelamento contratual em maio/2023, porém o processo foi concluído apenas em dezembro/2024. Em decorrência dessa falha operacional, permaneceram sendo geradas cobranças de mensalidade mínima. | K24: 21617.57 | L24: Amanda | M24: Comercial | N24: =IF(K24<10000,"Everton",IF(K24<=50000,"Everton + Tatebe","Everton + Tatebe + Calil")) -> Everton + Tatebe | O24: 46267 | P24: OK | R24: 46279 | S24: OK | T24: =IF(K24<10000,"N/A","-") -> - | U24: =IF(K24<=50000,"N/A","") -> N/A | V24: =IF(K24<=50000,"N/A","") -> N/A | W24: =IF(K24<=50000,"N/A","-") -> N/A
B25: =B24+1 -> 23 | C25: FALSE | D25: =IF(AND(P25="OK",OR(S25="OK",S25="N/A"),OR(V25="OK",V25="N/A")),"Aprovado",IF(OR(P25="Reprovado",S25="Reprovado",V25="Reprovado"),"Reprovado","Pendente")) -> Aprovado | E25: 46259 | F25: Aprovação - EDITORA SANAR S.A - 18.990.682/0001-92 - 18244519 | G25: =RIGHT(Tabela1[[#This Row],[Assunto e-mail]],8) -> 18244519 | H25: OK | I25: Cancelamento de NF | J25: O cliente solicitou o cancelamento do contrato na época, porém a solicitação não foi formalizada pelos gestores responsáveis. Em função dessa ausência de formalização, o contrato permaneceu ativo em nossos sistemas, ocasionando a continuidade da emissão das notas fiscais de forma indevida. | K25: 39695.55 | L25: Stephany | M25: Comercial | N25: =IF(K25<10000,"Everton",IF(K25<=50000,"Everton + Tatebe","Everton + Tatebe + Calil")) -> Everton + Tatebe | O25: 46267 | P25: OK | R25: 46279 | S25: OK | T25: =IF(K25<10000,"N/A","-") -> - | U25: =IF(K25<=50000,"N/A","") -> N/A | V25: =IF(K25<=50000,"N/A","") -> N/A | W25: =IF(K25<=50000,"N/A","-") -> N/A
B26: =B25+1 -> 24 | C26: TRUE | D26: =IF(AND(P26="OK",OR(S26="OK",S26="N/A"),OR(V26="OK",V26="N/A")),"Aprovado",IF(OR(P26="Reprovado",S26="Reprovado",V26="Reprovado"),"Reprovado","Pendente")) -> Aprovado | E26: 46261 | F26: Aprovação - Cancelamento de notas - INFRACOMMERCE SYNAPCOM COMERCI - 27.932.734/0001-65 | 26412747 | G26: =RIGHT(Tabela1[[#This Row],[Assunto e-mail]],8) -> 26412747 | H26: OK | I26: Cancelamento de NF | J26: As notas foram emitidas após a data de cancelamento do contrato (26/06/2023) devido à não conclusão do processo de cancelamento pelo time comercial à época. Dessa forma, houve faturamento indevido após o encerramento contratual. | K26: 44986.46 | L26: Amanda | M26: Comercial | N26: =IF(K26<10000,"Everton",IF(K26<=50000,"Everton + Tatebe","Everton + Tatebe + Calil")) -> Everton + Tatebe | O26: 46267 | P26: OK | R26: 46279 | S26: OK | T26: =IF(K26<10000,"N/A","-") -> - | U26: =IF(K26<=50000,"N/A","") -> N/A | V26: =IF(K26<=50000,"N/A","") -> N/A | W26: =IF(K26<=50000,"N/A","-") -> N/A
B27: =B26+1 -> 25 | C27: FALSE | D27: =IF(AND(P27="OK",OR(S27="OK",S27="N/A"),OR(V27="OK",V27="N/A")),"Aprovado",IF(OR(P27="Reprovado",S27="Reprovado",V27="Reprovado"),"Reprovado","Pendente")) -> Pendente | E27: 46262 | F27: Cancelamento de NFs DIAS FINANCE LTDA | H27: OK | I27: Cancelamento de NF | J27: A Nota Fiscal foi emitida para cobrança de multa contratual em decorrência do cancelamento do contrato do cliente LGS DIAS, realizado em 12/02/2026, quando ainda restavam 11 dias para o término do período contratual de 12 meses. Contudo, conforme alinhamento prévio entre o time Comercial e o cliente, foi acordado que o cancelamento ocorreria sem a aplicação de multa contratual. Dessa forma, a cobrança foi emitida indevidamente, não havendo obrigação de pagamento por parte do cliente. | K27: 91587.67 | L27: Pamela | M27: Comercial | N27: =IF(K27<10000,"Everton",IF(K27<=50000,"Everton + Tatebe","Everton + Tatebe + Calil")) -> Everton + Tatebe + Calil | R27: =IF(K27<10000,"N/A","") | S27: =IF(K27<10000,"N/A","") | T27: =IF(K27<10000,"N/A","-") -> - | U27: =IF(K27<=50000,"N/A","") | V27: =IF(K27<=50000,"N/A","") | W27: =IF(K27<=50000,"N/A","-") -> -
B28: =B27+1 -> 26 | C28: FALSE | D28: =IF(AND(P28="OK",OR(S28="OK",S28="N/A"),OR(V28="OK",V28="N/A")),"Aprovado",IF(OR(P28="Reprovado",S28="Reprovado",V28="Reprovado"),"Reprovado","Pendente")) -> Pendente | E28: 46259 | F28: Aprovação - Cancelamento de notas - N. R. BENNESBY COMERCIO DE UTE - 37.882.316/0001-64 | 26346273 | G28: =RIGHT(Tabela1[[#This Row],[Assunto e-mail]],8) -> 26346273 | H28: OK | I28: Cancelamento de NF | J28: Histórico de problemas operacionais reportados pelo cliente desde o início da relação comercial, incluindo intercorrências relacionadas à integração Shopify, antifraude e gestão de pedidos, que motivaram sucessivas solicitações de cancelamento e suspensão das cobranças. | K28: 121129.73 | L28: Amanda | M28: Operação | N28: =IF(K28<10000,"Everton",IF(K28<=50000,"Everton + Tatebe","Everton + Tatebe + Calil")) -> Everton + Tatebe + Calil | O28: 46267 | P28: OK | R28: 46279 | S28: OK | T28: =IF(K28<10000,"N/A","-") -> - | U28: =IF(K28<=50000,"N/A","") | V28: =IF(K28<=50000,"N/A","") | W28: =IF(K28<=50000,"N/A","-") -> -
B29: =B28+1 -> 27 | C29: FALSE | D29: =IF(AND(P29="OK",OR(S29="OK",S29="N/A"),OR(V29="OK",V29="N/A")),"Aprovado",IF(OR(P29="Reprovado",S29="Reprovado",V29="Reprovado"),"Reprovado","Pendente")) -> Pendente | F29: Aprovação - Cancelamento/baixa de notas ficais - GUEDES & PAIXAO LTDA 16928871003630 - 18604102 | G29: =RIGHT(Tabela1[[#This Row],[Assunto e-mail]],8) -> 18604102 | H29: ok | I29: Cancelamento de NF e Baixa | J29: Solicito, por gentileza, o seu DA, pois houve um atraso na implantação e, em tratativa realizada pelo time Comercial com o cliente, foi acordado o pagamento de 50% do valor devido. O time de Cobrança informou que o cliente efetuou o pagamento das notas fiscais contempladas no acordo. Dessa forma, precisamos realizar a baixa das notas fiscais relacionadas abaixo, que totalizam R$ 40.308,26. | K29: 40308.26 | L29: Stephany | M29: Operação | N29: =IF(K29<10000,"Everton",IF(K29<=50000,"Everton + Tatebe","Everton + Tatebe + Calil")) -> Everton + Tatebe | R29: =IF(K29<10000,"N/A","") | S29: =IF(K29<10000,"N/A","") | T29: =IF(K29<10000,"N/A","-") -> - | U29: =IF(K29<=50000,"N/A","") -> N/A | V29: =IF(K29<=50000,"N/A","") -> N/A | W29: =IF(K29<=50000,"N/A","-") -> N/A
B30: =B29+1 -> 28 | C30: FALSE | D30: =IF(AND(P30="OK",OR(S30="OK",S30="N/A"),OR(V30="OK",V30="N/A")),"Aprovado",IF(OR(P30="Reprovado",S30="Reprovado",V30="Reprovado"),"Reprovado","Pendente")) -> Pendente | F30: Aprovação - Cancelamento - FRUITFY INTERMEDIACOES E PAGAMENTOS 57315333000127 - 24820605 | G30: =RIGHT(Tabela1[[#This Row],[Assunto e-mail]],8) -> 24820605 | H30: ok | I30: Cancelamento de NF | J30: O cliente informou que enfrentou problemas durante a implementação da solução e declarou que não realizaria os pagamentos enquanto a implantação não estivesse concluída e aderente a tudo o que foi prometido e comercializado. Diante da negativa de pagamento e considerando o risco de ajuizamento, a Cielo optou pelo descredenciamento do cliente e pelo cancelamento das notas fiscais mencionadas. | K30: 1969.4 | L30: Stephany | M30: Operação | N30: =IF(K30<10000,"Everton",IF(K30<=50000,"Everton + Tatebe","Everton + Tatebe + Calil")) -> Everton | R30: =IF(K30<10000,"N/A","") -> N/A | S30: =IF(K30<10000,"N/A","") -> N/A | T30: =IF(K30<10000,"N/A","-") -> N/A | U30: =IF(K30<=50000,"N/A","") -> N/A | V30: =IF(K30<=50000,"N/A","") -> N/A | W30: =IF(K30<=50000,"N/A","-") -> N/A
B31: =B30+1 -> 29 | C31: FALSE | D31: =IF(AND(P31="OK",OR(S31="OK",S31="N/A"),OR(V31="OK",V31="N/A")),"Aprovado",IF(OR(P31="Reprovado",S31="Reprovado",V31="Reprovado"),"Reprovado","Pendente")) -> Pendente | F31: Aprovação - Cancelamento de notas fiscais - DENTAL S. SEBASTIAO LTDA - 09.228.091/0001-91 - 27115064 | G31: 27115064 | H31: ok | I31: Cancelamento de NF | J31: Aprovação - Cancelamento de notas fiscais - DENTAL S. SEBASTIAO LTDA - 09.228.091/0001-91 | K31: 5102.04 | L31: Stephany | N31: =IF(K31<10000,"Everton",IF(K31<=50000,"Everton + Tatebe","Everton + Tatebe + Calil")) -> Everton | R31: =IF(K31<10000,"N/A","") -> N/A | S31: =IF(K31<10000,"N/A","") -> N/A | T31: =IF(K31<10000,"N/A","-") -> N/A | U31: =IF(K31<=50000,"N/A","") -> N/A | V31: =IF(K31<=50000,"N/A","") -> N/A | W31: =IF(K31<=50000,"N/A","-") -> N/A
B32: =B31+1 -> 30 | C32: FALSE | D32: =IF(AND(P32="OK",OR(S32="OK",S32="N/A"),OR(V32="OK",V32="N/A")),"Aprovado",IF(OR(P32="Reprovado",S32="Reprovado",V32="Reprovado"),"Reprovado","Pendente")) -> Pendente | F32: Aprovação - Cancelamento de notas - VOLTBRAS ELETROPOSTOS AGENCIAMENTO LTDA - 32.150.686/0001-93 | 25704891 | G32: =RIGHT(Tabela1[[#This Row],[Assunto e-mail]],8) -> 25704891 | H32: OK | I32: Cancelamento de NF | J32: A integração da solução não foi concluída por questões técnicas, impossibilitando sua efetiva utilização pelo cliente. Além disso, após análise contratual, não foi identificada cláusula específica que estabeleça a obrigatoriedade do pagamento do SETUP nessa situação, motivo pelo qual o cliente formalizou contestação da cobrança por meio de notificação extrajudicial. | K32: 22974.01 | L32: Amanda | M32: Operação | N32: =IF(K32<10000,"Everton",IF(K32<=50000,"Everton + Tatebe","Everton + Tatebe + Calil")) -> Everton + Tatebe | R32: =IF(K32<10000,"N/A","") | S32: =IF(K32<10000,"N/A","") | T32: =IF(K32<10000,"N/A","-") -> - | U32: =IF(K32<=50000,"N/A","") -> N/A | V32: =IF(K32<=50000,"N/A","") -> N/A | W32: =IF(K32<=50000,"N/A","-") -> N/A
B33: =B32+1 -> 31 | C33: FALSE | D33: =IF(AND(P33="OK",OR(S33="OK",S33="N/A"),OR(V33="OK",V33="N/A")),"Aprovado",IF(OR(P33="Reprovado",S33="Reprovado",V33="Reprovado"),"Reprovado","Pendente")) -> Pendente | F33: Aprovação - Cancelamento de notas - JJGC. IND. E COM. MATERIAS DENTARIOS S/A - 00.489.050/0001-84 e 00.489.050/0002-65 | 26895066 | G33: =RIGHT(Tabela1[[#This Row],[Assunto e-mail]],8) -> 26895066 | H33: OK | I33: Cancelamento de NF | J33: O cliente formalizou a solicitação de cancelamento antes da primeira emissão de nota fiscal, para ambos os CNPJ's. Na época a gerente responsável (Isabella Lestingi), chegou a abrir no SF o cancelamento do contrato, mas não foi encaminhado para o financeiro. | K33: 63688.79 | L33: Amanda | M33: Comercial | N33: =IF(K33<10000,"Everton",IF(K33<=50000,"Everton + Tatebe","Everton + Tatebe + Calil")) -> Everton + Tatebe + Calil | R33: =IF(K32<10000,"N/A","") | S33: =IF(K32<10000,"N/A","") | T33: =IF(K33<10000,"N/A","-") -> - | U33: =IF(K33<=50000,"N/A","") | V33: =IF(K33<=50000,"N/A","") | W33: =IF(K33<=50000,"N/A","-") -> -
B34: =B33+1 -> 32 | C34: TRUE | D34: Aprovado | F34: Valores em aberto - Azzas 2154 | G34: 26988914 | H34: OK | I34: Cancelamento de NF | J34: A cliente informou que o pagamento individual das 78 notas gera um esforço operacional elevado, pois cada nota precisa estar vinculada a um boleto específico. Por esse motivo, solicitou a consolidação dos valores em 5 novos documentos fiscais e respectivos boletos. | K34: 389359.12 | L34: Vanessa | M34: Cobrança | N34: =IF(K34<10000,"Everton",IF(K34<=50000,"Everton + Tatebe","Everton + Tatebe + Calil")) -> Everton + Tatebe + Calil | T34: =IF(K34<10000,"N/A","-") -> - | U34: 46281 | V34: OK | W34: =IF(K34<=50000,"N/A","-") -> -
B35: =B34+1 -> 33 | C35: FALSE | D35: =IF(AND(P35="OK",OR(S35="OK",S35="N/A"),OR(V35="OK",V35="N/A")),"Aprovado",IF(OR(P35="Reprovado",S35="Reprovado",V35="Reprovado"),"Reprovado","Pendente")) -> Pendente | E35: 46286 | G35: 27241800 | I35: Cancelamento de NF | J35: Emissão em duplicidade | K35: 202.04 | L35: Amanda | M35: Financeiro | N35: =IF(K35<10000,"Everton",IF(K35<=50000,"Everton + Tatebe","Everton + Tatebe + Calil")) -> Everton | R35: =IF(K34<10000,"N/A","") | S35: =IF(K34<10000,"N/A","") | T35: =IF(K35<10000,"N/A","-") -> N/A | U35: =IF(K35<=50000,"N/A","") -> N/A | V35: =IF(K35<=50000,"N/A","") -> N/A | W35: =IF(K35<=50000,"N/A","-") -> N/A

Sheet Panorama
B1: Qtde. Total chamados Status | I1: Qtde. Total chamados por categoria | S1: Mês/Ano | T1: jul/2026
I2: Status | J2: PENDENTE | S2: Data de abertura | T2: (Tudo)
B4: #VALUE! | J4: Rótulos de Coluna | N4: PENDENTE | O4: FINALIZADO | P4: EM ANDAMENTO | Q4: A INICIAR | S4: Rótulos de Linha | T4: Contagem de Número do Chamado
J5: 2025 | K5: 2026 | L5: - | N5: =GETPIVOTDATA("Número do Chamado",$B$4,"Status","PENDENTE") -> #REF! | O5: =-GETPIVOTDATA("Número do Chamado",$B$4,"Status","FINALIZADO") -> #REF! | P5: =GETPIVOTDATA("Número do Chamado",$B$4,"Status","EM ANDAMENTO") -> #REF! | Q5: =SUM(N5:P5) -> #REF! | S5: Emilly Maria | T5: 20
S6: Fabiana Lisboa | T6: 12
S7: Pamela de Sá | T7: 24
S8: Stephany Lima | T8: 37
I9: Contagem de Número de protocolo | J9: 11 | K9: 84 | L9: 95 | S9: Vanessa Araujo | T9: 4
S10: Total Geral | T10: 97
B17: Qtde. Chamados por categoria x responsável
B18: Status | C18: PENDENTE
B19: Data de abertura | C19: (Vários itens)
B21: Rótulos de Linha | C21: Contagem Chamado
B22: Emilly Maria | C22: 13
B23: Fabiana Lisboa | C23: 10
B24: Pamela de Sá | C24: 23
B25: Stephany Lima | C25: 32
B26: Vanessa Araujo | C26: 6
B27: Total Geral | C27: 84
D45: Amanda verificar

Sheet Compilado chamados
B1: Atualizado em: | C1: 46290
L2: PENDENTE
L3: FINALIZADO
A4: Obs | B4: RESPONSÁVEL | C4: Classificação | D4: Número do Chamado | E4: Chamado Pai (clone) | F4: Número de protocolo | G4: Razão social | H4: CNPJ | I4: Causa raiz | J4: Observação/Ação | K4: Ofensor | L4: Status | M4: Prioridade | N4: Assunto | O4: Data de abertura | P4: Data da última modificação do chamado | Q4: Mês/Ano | R4: Proprietário do Chamado | S4: Email da Web | T4: Nome Fantasia | U4: Descrição | V4: Descrição detalhada | W4: Ref. | X4: Dt.Encerramento | Y4: Situação | Z4: Dias em Aberto | AA4: Aux_Ranking | AB4: Origem
B5: Stephany Lima | C5: =VLOOKUP(I:I,'Referencias '!H:I,2,0) -> Cobrança e Contestação | D5: 12555846 | E5: 0 | F5: 2512611298969 | G5: =T5 -> SUPERMERCADOS BOA LJ01 | I5: Ajuste de cobrança / faturamento | L5: FINALIZADO | M5: Médio | N5: Análise e Ajuste Condições | Boa Supermercado e Superpão | 1018 | 213299 | O5: 45783 | P5: 46003 | Q5: =TEXT(O5,"mmm/aaaa") -> mai/2025 | R5: Vanessa dos Santos Araujo | S5: support@braspag.zendesk.com | T5: SUPERMERCADOS BOA LJ01 | U5: ATENÇÃO: ESTE E-MAIL É DE UM REMETENTE EXTERNO À ORGANIZAÇÃO. Não clique em links ou abra anexos de remetentes desconhecidos ou suspeitos, ou sem validar com o remetente que o conteúdo é seguro. EM CASO DE DÚVIDAS, reporte este e-mail à equipe de Segurança da Informação, por meio do botão “DENUNCIAR PHISHING” em seu Outlook. No celular, você encontrará o botão clicando nos (...) no canto superior direito da mensagem, ao lado do nome do remetente. ##- Não escreva abaixo desta linha -## Você está registrado como CC nesta solicitação de suporte (213299). Responda este email para adicionar um comentário à solicitação. [https://braspag.zendesk.com/images/2016/default-avatar-80.png] Vanessa dos Santos Araujo (Cielo e-commerce) 6 de mai. de 2025, 11:16 BRT Observação privada Gabriela gabrielao@cielo.com.br * Empresa: Braspag * CNPJ: Gabriela * Causa raiz financeiro: Gabriela * Responsável pela demanda: Vanessa dos Santos Araujo [https://braspag.zendesk.com/images/201 | V5: Sem descrição | W5: =_xlfn.CONCAT(D5:E5) -> 125558460 | X5: 46245 | Y5: =IF(X5="","Aberto","Encerrado") -> Encerrado | Z5: =IF(OR(L5="PENDENTE",L5="EM ANDAMENTO",L5="PENDENTE APROVAÇÃO CANCELAMENTO NF"),TODAY()-O5,X5-O5) -> 462 | AA5: =IF(Y5="Aberto",Z5+ROW()/100000,"") | AB5: =IF(ISNUMBER(FIND("@cielo.com.br",S5)),"Interno","Externo") -> Externo
B6: Stephany Lima | C6: =VLOOKUP(I:I,'Referencias '!H:I,2,0) -> Cobrança e Contestação | D6: 13696702 | E6: 0 | F6: 2517719314576 | G6: =T6 -> www soares com br | I6: Ajuste de cobrança / faturamento | L6: FINALIZADO | M6: Médio | N6: 1018 Financeiro | Desejo falar com o setor financeiro | Fernanda Camarneira | fernanda.scamarneira@cielo.com.br | O6: 45834 | P6: 45947 | Q6: =TEXT(O6,"mmm/aaaa") -> jun/2025 | R6: Vanessa dos Santos Araujo | S6: fernanda.scamarneira@cielo.com.br | T6: www soares com br | U6: Olá, segue form enviado pela página de Ticket Braspag:<p><strong>Qual seu nome?:</strong> Fernanda Camarneira</p><p><strong>Endereço de e-mail:</strong> fernanda.scamarneira@cielo.com.br</p><p><strong>Telefone:</strong> (11) 94519-4834</p><p><strong>Assunto:</strong> Fast Solution - Reajuste Analista Advanced</p><p><strong>Sobre qual produto ou área deseja falar?:</strong> Financeiro</p><p><strong>Merchant ID/Estabelecimento Comercial (EC)*:</strong> 03.738.295/0001-96</p><p><strong>CNPJ:</strong> 03.738.295/0001-96</p><p><strong>Como podemos te ajudar?:</strong> Desejo falar com o setor financeiro</p><p><strong>Descrição do problema:</strong> o cliente FAST SOLUTION - 03.738.295/0001-96 realizou um upgrade de plano de antifraude Hierarquia para Advanced em 08/01/2025. Mas como já tinha um contrato com outra data de aniversário, já teve o reajuste aplicado agora em maio/2025 no analista advanced. Nos outros produtos está certo, precisamos aplicar. Mas no analista advanced precisamos r | V6: =IFERROR(_xlfn.TEXTBEFORE(_xlfn.TEXTAFTER(U6,"Descrição do problema:</strong"),"</p>"),_xlfn.TEXTAFTER(U6,"Descrição do problema:</strong")) -> > o cliente FAST SOLUTION - 03.738.295/0001-96 realizou um upgrade de plano de antifraude Hierarquia para Advanced em 08/01/2025. Mas como já tinha um contrato com outra data de aniversário, já teve o reajuste aplicado agora em maio/2025 no analista advanced. Nos outros produtos está certo, precisamos aplicar. Mas no analista advanced precisamos r | W6: =_xlfn.CONCAT(D6:E6) -> 136967020 | X6: 46245 | Y6: =IF(X6="","Aberto","Encerrado") -> Encerrado | Z6: =IF(OR(L6="PENDENTE",L6="EM ANDAMENTO",L6="PENDENTE APROVAÇÃO CANCELAMENTO NF"),TODAY()-O6,X6-O6) -> 411 | AA6: =IF(Y6="Aberto",Z6+ROW()/100000,"") | AB6: =IF(ISNUMBER(FIND("@cielo.com.br",S6)),"Interno","Externo") -> Interno
B7: Stephany Lima | C7: =VLOOKUP(I:I,'Referencias '!H:I,2,0) -> Cobrança e Contestação | D7: 13768449 | E7: 0 | F7: 2518211378652 | G7: =T7 -> CIELO SAINSTITUICAO DE PAGAMENTO | I7: Ajuste de cobrança / faturamento | L7: FINALIZADO | M7: Médio | N7: 1018 Financeiro | Desejo falar com o setor financeiro | Danilo | danilo_nunes@carrefour.com | O7: 45839 | P7: 45945 | Q7: =TEXT(O7,"mmm/aaaa") -> jul/2025 | R7: Vanessa dos Santos Araujo | S7: danilo_nunes@carrefour.com | T7: CIELO SAINSTITUICAO DE PAGAMENTO | U7: Olá, segue form enviado pela página de Ticket Braspag:<p><strong>Qual seu nome?:</strong> Danilo</p><p><strong>Endereço de e-mail:</strong> danilo_nunes@carrefour.com</p><p><strong>CNPJ:</strong> 45.543.915/0001-81</p><p><strong>Telefone:</strong> (11) 96363-2779</p><p><strong>Assunto:</strong> Carrefour | Faturamento Braspag Junho/2025</p><p><strong>Merchant ID/Estabelecimento Comercial (EC)*:</strong> 1bbe7159-6591-48b9-b101-639e81a33465</p><p><strong>Sobre qual produto ou área deseja falar?:</strong> Financeiro</p><p><strong>Como podemos te ajudar?:</strong> Desejo falar com o setor financeiro</p><p><strong>Data e hora do erro:</strong> 01-07-2025 11:22</p><p><strong>Descrição do problema:</strong> Olá, Para este faturamento de junho notificamos a necessidade da aplicação de um desconto referente ao retroativo do mês de abril R$37,55 Chamado de Abril : Antigo: 216094 Atual: 2512611299293 Faturamento Braspag | Abril 2024 | 1018 | ticket.id Por favor seguir com cancelamento da N | V7: =IFERROR(_xlfn.TEXTBEFORE(_xlfn.TEXTAFTER(U7,"Descrição do problema:</strong"),"</p>"),_xlfn.TEXTAFTER(U7,"Descrição do problema:</strong")) -> > Olá, Para este faturamento de junho notificamos a necessidade da aplicação de um desconto referente ao retroativo do mês de abril R$37,55 Chamado de Abril : Antigo: 216094 Atual: 2512611299293 Faturamento Braspag | Abril 2024 | 1018 | ticket.id Por favor seguir com cancelamento da N | W7: =_xlfn.CONCAT(D7:E7) -> 137684490 | X7: 46245 | Y7: =IF(X7="","Aberto","Encerrado") -> Encerrado | Z7: =IF(OR(L7="PENDENTE",L7="EM ANDAMENTO",L7="PENDENTE APROVAÇÃO CANCELAMENTO NF"),TODAY()-O7,X7-O7) -> 406 | AA7: =IF(Y7="Aberto",Z7+ROW()/100000,"") | AB7: =IF(ISNUMBER(FIND("@cielo.com.br",S7)),"Interno","Externo") -> Externo
B8: Vanessa Araujo | C8: =VLOOKUP(I:I,'Referencias '!H:I,2,0) -> Contratos, Comercial e Cadastro | D8: 13810507 | E8: 0 | F8: 2518315414788 | G8: =T8 -> CIELO SAINSTITUICAO DE PAGAMENTO | I8: Cancelamento de contrato | L8: FINALIZADO | M8: Médio | N8: 1003 Cancelamento de Contrato: Contábil Hub | O8: 45840 | P8: 46198 | Q8: =TEXT(O8,"mmm/aaaa") -> jul/2025 | R8: Emilly Maria Sousa Almeida | S8: joiceo@cielo.com.br | T8: CIELO SAINSTITUICAO DE PAGAMENTO | U8: -json-{"CancelamentoDeContratoId":"a0UNp00000YAtioMAD"} - CNPJ da Conta: 30.170.362/0001-91 - Razão Social: CB AFONSO SERVICOS ADMINISTRATIVOS LTDA - Transações Mensais: 200 - Data do Contrato: 17/11/2020 - Executivo: Caroline Matias da Costa - Motivo: Encerramento das Atividades - Justificativa: Encerramento das atividades. - Tipo: Total - Serviços: Cartão Protegido,Pagador - Observações: - Conta SF Id: 0014o00001k7wONAAY | V8: =TRIM(_xlfn.TEXTAFTER(U8,"-json-",-1)) -> {"CancelamentoDeContratoId":"a0UNp00000YAtioMAD"} - CNPJ da Conta: 30.170.362/0001-91 - Razão Social: CB AFONSO SERVICOS ADMINISTRATIVOS LTDA - Transações Mensais: 200 - Data do Contrato: 17/11/2020 - Executivo: Caroline Matias da Costa - Motivo: Encerramento das Atividades - Justificativa: Encerramento das atividades. - Tipo: Total - Serviços: Cartão Protegido,Pagador - Observações: - Conta SF Id: 0014o00001k7wONAAY | W8: =_xlfn.CONCAT(D8:E8) -> 138105070 | X8: 46227 | Y8: =IF(X8="","Aberto","Encerrado") -> Encerrado | Z8: =IF(OR(L8="PENDENTE",L8="EM ANDAMENTO",L8="PENDENTE APROVAÇÃO CANCELAMENTO NF"),TODAY()-O8,X8-O8) -> 387 | AA8: =IF(Y8="Aberto",Z8+ROW()/100000,"") | AB8: =IF(ISNUMBER(FIND("@cielo.com.br",S8)),"Interno","Externo") -> Interno
B9: Stephany Lima | C9: =VLOOKUP(I:I,'Referencias '!H:I,2,0) -> Cobrança e Contestação | D9: 15816740 | E9: 0 | F9: 2526910101742 | G9: =VLOOKUP(H:H,'Referencias '!B:C,2,0) -> HOSTGATOR BRASIL LTDA. | H9: =TRIM(_xlfn.TEXTBEFORE(_xlfn.TEXTAFTER(U9,"CNPJ/CPF:</strong>"),"</p>")) -> 15.754.475/0001-40 | I9: Dúvidas sobre cobrança | L9: FINALIZADO | M9: Médio | N9: 1011 Velocity Check | Estou em produção e tenho uma dúvida | Monica Murer | monica.murer@newfold.com | O9: 45926 | P9: 46028 | Q9: =TEXT(O9,"mmm/aaaa") -> set/2025 | R9: STEPHANY LIMA DE LISBOA | S9: monica.murer@newfold.com | T9: HOSTGATOR HOSP SITES | U9: Olá, segue formulário enviado para Cielo E-commerce:<p><strong>Qual seu nome?:</strong> Monica Murer</p><p><strong>Endereço de e-mail:</strong> monica.murer@newfold.com</p><p><strong>CNPJ/CPF:</strong> 15.754.475/0001-40</p><p><strong>Telefone:</strong> (48) 9943-0204</p><p><strong>Assunto:</strong> Velocity Check - Divergência nos valores faturados x Contrato.</p><p><strong>Merchant ID/Estabelecimento Comercial (EC):</strong> 1055024074</p><p><strong>Sobre qual produto ou área deseja falar?:</strong> Velocity Check</p><p><strong>Descrição do problema:</strong> Estou com uma dúvida sobre a cobrança do serviço de &quot;velocity check&quot; da Stelo, em nosso contrato, o valor desse serviço deveria ser fixo mensal, com reajuste apenas em novembro, usando a taxa do IPCA. No entanto, desde março, estamos notando valores diferentes e discrepantes nas cobranças. Segue abaixo valores reconhecidos na despesa de acordo com as NFs. Jan/Fev - R$466 / Mar - R$506 / Abr - R$763 / Mai - R$829 / Jun | V9: =IFERROR(_xlfn.TEXTBEFORE(_xlfn.TEXTAFTER(U9,"Descrição do problema:</strong"),"</p>"),_xlfn.TEXTAFTER(U9,"Descrição do problema:</strong")) -> > Estou com uma dúvida sobre a cobrança do serviço de &quot;velocity check&quot; da Stelo, em nosso contrato, o valor desse serviço deveria ser fixo mensal, com reajuste apenas em novembro, usando a taxa do IPCA. No entanto, desde março, estamos notando valores diferentes e discrepantes nas cobranças. Segue abaixo valores reconhecidos na despesa de acordo com as NFs. Jan/Fev - R$466 / Mar - R$506 / Abr - R$763 / Mai - R$829 / Jun | W9: =_xlfn.CONCAT(D9:E9) -> 158167400 | X9: 46245 | Y9: =IF(X9="","Aberto","Encerrado") -> Encerrado | Z9: =IF(OR(L9="PENDENTE",L9="EM ANDAMENTO",L9="PENDENTE APROVAÇÃO CANCELAMENTO NF"),TODAY()-O9,X9-O9) -> 319 | AA9: =IF(Y9="Aberto",Z9+ROW()/100000,"") | AB9: =IF(ISNUMBER(FIND("@cielo.com.br",S9)),"Interno","Externo") -> Externo
B10: Stephany Lima | C10: =VLOOKUP(I:I,'Referencias '!H:I,2,0) -> Cancelamento e Reemissão de Nota Fiscal | D10: 16424808 | E10: 0 | F10: 2529414584699 | G10: =VLOOKUP(H:H,'Referencias '!B:C,2,0) -> OBRAS SOCIAIS DA ARQUIDIOCESE DE APARECIDA | H10: =TRIM(_xlfn.TEXTBEFORE(_xlfn.TEXTAFTER(U10,"CNPJ/CPF:</strong>"),"</p>")) -> 45.201.019/0001-34 | I10: Cancelamento de NF | L10: FINALIZADO | M10: Médio | N10: 1018 Financeiro | Desejo falar com o setor financeiro | Pâmela | pamela.cristina@santuarionacional.com | O10: 45951 | P10: 46202 | Q10: =TEXT(O10,"mmm/aaaa") -> out/2025 | R10: Vanessa dos Santos Araujo | S10: pamela.cristina@santuarionacional.com | T10: SANTUARIO CV1 | U10: Olá, segue formulário enviado para Cielo E-commerce:<p><strong>Qual seu nome?:</strong> Pâmela</p><p><strong>Endereço de e-mail:</strong> pamela.cristina@santuarionacional.com</p><p><strong>CNPJ/CPF:</strong> 45.201.019/0001-34</p><p><strong>Telefone:</strong> (12) 3104-1820</p><p><strong>Assunto:</strong> Boletos</p><p><strong>Merchant ID/Estabelecimento Comercial (EC):</strong> OBRAS SOCIAIS DA ARQUIDIOCESE DE AP</p><p><strong>Sobre qual produto ou área deseja falar?:</strong> Financeiro</p><p><strong>Como podemos te ajudar?:</strong> Desejo falar com o setor financeiro</p><p><strong>Descrição do problema:</strong> Estamos recebendo boletos no CNPJ novo que ainda não contemplamos a assinatura do contrato, faturas vindo de forma equivocada no valor de R$ 425,86 em nome de SANTUARIO NACIONAL DE NOSSA SENHORA, sendo que o pagamento já está sendo feito em OBRAS SOCIAIS DA ARQUIDIOCESE DE AP. Gostaríamos de saber o porque de estarmos recebendo este boleto de cobrança?</p><p><strong>GA Cli | V10: =IFERROR(_xlfn.TEXTBEFORE(_xlfn.TEXTAFTER(U10,"Descrição do problema:</strong"),"</p>"),_xlfn.TEXTAFTER(U10,"Descrição do problema:</strong")) -> > Estamos recebendo boletos no CNPJ novo que ainda não contemplamos a assinatura do contrato, faturas vindo de forma equivocada no valor de R$ 425,86 em nome de SANTUARIO NACIONAL DE NOSSA SENHORA, sendo que o pagamento já está sendo feito em OBRAS SOCIAIS DA ARQUIDIOCESE DE AP. Gostaríamos de saber o porque de estarmos recebendo este boleto de cobrança? | W10: =_xlfn.CONCAT(D10:E10) -> 164248080 | X10: 46246 | Y10: =IF(X10="","Aberto","Encerrado") -> Encerrado | Z10: =IF(OR(L10="PENDENTE",L10="EM ANDAMENTO",L10="PENDENTE APROVAÇÃO CANCELAMENTO NF"),TODAY()-O10,X10-O10) -> 295 | AA10: =IF(Y10="Aberto",Z10+ROW()/100000,"") | AB10: =IF(ISNUMBER(FIND("@cielo.com.br",S10)),"Interno","Externo") -> Externo
B11: Stephany Lima | C11: =VLOOKUP(I:I,'Referencias '!H:I,2,0) -> Cobrança e Contestação | D11: 17076598 | E11: 0 | F11: 2531710061695 | G11: =T11 -> COVABRA SUPERMERCADOS LTDA | H11: =TRIM(_xlfn.TEXTBEFORE(_xlfn.TEXTAFTER(U11,"CNPJ/CPF:</strong>"),"</p>")) -> 61.233.151/0016-60 | I11: Cobrança retroativa | L11: FINALIZADO | M11: Médio | N11: 1018 Financeiro | Desejo falar com o setor financeiro | Caroline Mendes | carolineal@cielo.com.br | O11: 45974 | P11: 46002 | Q11: =TEXT(O11,"mmm/aaaa") -> nov/2025 | R11: STEPHANY LIMA DE LISBOA | S11: carolineal@cielo.com.br | T11: COVABRA SUPERMERCADOS LTDA | U11: Olá, segue formulário enviado para Cielo E-commerce:<p><strong>Qual seu nome?:</strong> Caroline Mendes</p><p><strong>Endereço de e-mail:</strong> carolineal@cielo.com.br</p><p><strong>CNPJ/CPF:</strong> 61.233.151/0016-60</p><p><strong>Telefone:</strong> (11) 94503-1458</p><p><strong>Assunto:</strong> Ajuste de cobrança - Velocity Check</p><p><strong>Merchant ID/Estabelecimento Comercial (EC):</strong> 61.233.151/0016-60</p><p><strong>Descrição do problema:</strong> Bom dia, time! Tudo bem? Identifiquei um erro na cobrança do Velocity Check do cliente Covabra. Atualmente, o contrato prevê cobrança padrão por tarifa e mínimo mensal de 500 transações. Porém, o cliente está sendo cobrado apenas pelo mínimo mensal, mesmo realizando bem mais que as 500 transações — em média, cerca de 3.000 transações por mês. Precisamos corrigir o formato da cobrança. Pelo que verifiquei, essa inconsistência ocorre desde 2023. Conseguem me ajudar com essa correção? Qualquer dúvida, fico à disposição. Abraç | V11: =IFERROR(_xlfn.TEXTBEFORE(_xlfn.TEXTAFTER(U11,"Descrição do problema:</strong"),"</p>"),_xlfn.TEXTAFTER(U11,"Descrição do problema:</strong")) -> > Bom dia, time! Tudo bem? Identifiquei um erro na cobrança do Velocity Check do cliente Covabra. Atualmente, o contrato prevê cobrança padrão por tarifa e mínimo mensal de 500 transações. Porém, o cliente está sendo cobrado apenas pelo mínimo mensal, mesmo realizando bem mais que as 500 transações — em média, cerca de 3.000 transações por mês. Precisamos corrigir o formato da cobrança. Pelo que verifiquei, essa inconsistência ocorre desde 2023. Conseguem me ajudar com essa correção? Qualquer dúvida, fico à disposição. Abraç | W11: =_xlfn.CONCAT(D11:E11) -> 170765980 | X11: 46246 | Y11: =IF(X11="","Aberto","Encerrado") -> Encerrado | Z11: =IF(OR(L11="PENDENTE",L11="EM ANDAMENTO",L11="PENDENTE APROVAÇÃO CANCELAMENTO NF"),TODAY()-O11,X11-O11) -> 272 | AA11: =IF(Y11="Aberto",Z11+ROW()/100000,"") | AB11: =IF(ISNUMBER(FIND("@cielo.com.br",S11)),"Interno","Externo") -> Interno
B12: Vanessa Araujo | C12: =VLOOKUP(I:I,'Referencias '!H:I,2,0) -> Pagamentos, Boletos e Recebimentos | D12: 17118848 | E12: 0 | F12: 2531812093794 | G12: =VLOOKUP(H:H,'Referencias '!B:C,2,0) -> MAFE ACESSORIOS SEMIJOIAS LTDA | H12: =TRIM(_xlfn.TEXTBEFORE(_xlfn.TEXTAFTER(U12,"CNPJ/CPF:</strong>"),"</p>")) -> 38.356.562/0001-45 | I12: Reenvio de boleto / NF | L12: FINALIZADO | M12: Médio | N12: 1018 Financeiro | Desejo falar com o setor financeiro | Giulia | giuliac@cielo.com.br | O12: 45975 | P12: 46072 | Q12: =TEXT(O12,"mmm/aaaa") -> nov/2025 | R12: STEPHANY LIMA DE LISBOA | S12: giuliac@cielo.com.br | T12: MAFE ACESSORIOS | U12: Olá, segue formulário enviado para Cielo E-commerce:<p><strong>CNPJ/CPF:</strong> 38.356.562/0001-45</p><p><strong>Qual seu nome?:</strong> Giulia</p><p><strong>Endereço de e-mail:</strong> giuliac@cielo.com.br</p><p><strong>Telefone:</strong> (11) 99104-1320</p><p><strong>Assunto:</strong> Cobrança Indevida - Erro de Billing</p><p><strong>Merchant ID/Estabelecimento Comercial (EC):</strong> 38.356.562/0001-45</p><p><strong>Descrição do problema:</strong> Essa cliente tinha a oportunidade aberta no Salesforce e o contrato estava la, mas precisavamos aguardar a resolução de algumas questoes do cliente antes de fechar a oportunidade. Novamente, igual a um outro caso que ocorreu, o financeiro/billing fez a cobrança sem a oportunidade estar fechada. Preciso que realizem o cancelamento de todos os boletos emitidos e que interrompam as cobranças futuras! Obrigada!</p><p><strong>ID da transação:</strong> </p><p><strong>Código do erro:</strong> </p><p><strong>Sobre qual produto ou área desej | V12: =IFERROR(_xlfn.TEXTBEFORE(_xlfn.TEXTAFTER(U12,"Descrição do problema:</strong"),"</p>"),_xlfn.TEXTAFTER(U12,"Descrição do problema:</strong")) -> > Essa cliente tinha a oportunidade aberta no Salesforce e o contrato estava la, mas precisavamos aguardar a resolução de algumas questoes do cliente antes de fechar a oportunidade. Novamente, igual a um outro caso que ocorreu, o financeiro/billing fez a cobrança sem a oportunidade estar fechada. Preciso que realizem o cancelamento de todos os boletos emitidos e que interrompam as cobranças futuras! Obrigada! | W12: =_xlfn.CONCAT(D12:E12) -> 171188480 | X12: 46231 | Y12: =IF(X12="","Aberto","Encerrado") -> Encerrado | Z12: =IF(OR(L12="PENDENTE",L12="EM ANDAMENTO",L12="PENDENTE APROVAÇÃO CANCELAMENTO NF"),TODAY()-O12,X12-O12) -> 256 | AA12: =IF(Y12="Aberto",Z12+ROW()/100000,"") | AB12: =IF(ISNUMBER(FIND("@cielo.com.br",S12)),"Interno","Externo") -> Interno
B13: Emilly Maria | C13: =VLOOKUP(I:I,'Referencias '!H:I,2,0) -> Contratos, Comercial e Cadastro | D13: 17218498 | E13: 0 | F13: 2532215161936 | G13: =T13 -> STYLO FARMA CURITIBA | I13: Cancelamento de contrato | L13: FINALIZADO | M13: Médio | N13: Cancelamento Braspag | O13: 45979 | P13: 46199 | Q13: =TEXT(O13,"mmm/aaaa") -> nov/2025 | R13: Emilly Maria Sousa Almeida | S13: denderadrugstore@gmail.com | T13: STYLO FARMA CURITIBA | U13: ATENÇÃO: ESTE E-MAIL É DE UM REMETENTE EXTERNO À ORGANIZAÇÃO. Não clique em links ou abra anexos de remetentes desconhecidos ou suspeitos, ou sem validar com o remetente que o conteúdo é seguro. EM CASO DE DÚVIDAS, reporte este e-mail à equipe de Segurança da Informação, por meio do botão “DENUNCIAR PHISHING” em seu Outlook. No celular, você encontrará o botão clicando nos (...) no canto superior direito da mensagem, ao lado do nome do remetente. Bom dia, Até o momento não recebi qualquer retorno dos chamados abertos para resolver nossos problemas com as notas emitidas incorretas e estamos sendo notificados da cobrança dessas notas que desde quando emitidas foram solicitadas as substituições. Atenciosamente, Dendera | V13: Bom dia, Até o momento não recebi qualquer retorno dos chamados abertos para resolver nossos problemas com as notas emitidas incorretas e estamos sendo notificados da cobrança dessas notas que desde quando emitidas foram solicitadas as substituições. | W13: =_xlfn.CONCAT(D13:E13) -> 172184980 | X13: 46234 | Y13: =IF(X13="","Aberto","Encerrado") -> Encerrado | Z13: =IF(OR(L13="PENDENTE",L13="EM ANDAMENTO",L13="PENDENTE APROVAÇÃO CANCELAMENTO NF"),TODAY()-O13,X13-O13) -> 255 | AA13: =IF(Y13="Aberto",Z13+ROW()/100000,"") | AB13: =IF(ISNUMBER(FIND("@cielo.com.br",S13)),"Interno","Externo") -> Externo
B14: Stephany Lima | C14: =VLOOKUP(I:I,'Referencias '!H:I,2,0) -> Cancelamento e Reemissão de Nota Fiscal | D14: 17351325 | E14: 0 | F14: 2532815256004 | G14: =VLOOKUP(H:H,'Referencias '!B:C,2,0) -> PMZ DISTRIBUIDORA S.A | H14: =TRIM(_xlfn.TEXTBEFORE(_xlfn.TEXTAFTER(U14,"CNPJ/CPF:</strong>"),"</p>")) -> 22.763.502/0017-74 | I14: Cancelamento de NF | L14: FINALIZADO | M14: Médio | N14: 1018 Financeiro | Desejo falar com o setor financeiro | Clarissa Rissi | clarissa.rissi@cielo.com.br | O14: 45985 | P14: 46030 | Q14: =TEXT(O14,"mmm/aaaa") -> nov/2025 | R14: STEPHANY LIMA DE LISBOA | S14: clarissa.rissi@cielo.com.br | T14: PEMAZA | U14: Olá, segue formulário enviado para Cielo E-commerce:<p><strong>Qual seu nome?:</strong> Clarissa Rissi</p><p><strong>Endereço de e-mail:</strong> clarissa.rissi@cielo.com.br</p><p><strong>CNPJ/CPF:</strong> 22.763.502/0017-74</p><p><strong>Telefone:</strong> (11) 97261-4151</p><p><strong>Assunto:</strong> Cancelamento de Notas</p><p><strong>Merchant ID/Estabelecimento Comercial (EC):</strong> 22.763.502/0017-74</p><p><strong>Descrição do problema:</strong> Boa tarde, pessoa. Conforme análise do contrato original e do Termo Aditivo firmado com a PMZ Distribuidora (anexo), identificamos que houve emissão de notas durante o período de congelamento (01/06/2025 a 31/08/2025), no qual estava prevista a isenção da cobrança dos serviços Plano Advanced, Antifraude, Cartão Protegido, Gateway e Velocity. Já temos o DA do Pelizon para canclemanto das notas: 91732, 92588, 92669, 92944, 93419,94521,94588,94765, 95540. (em anexo histórico de troca de emails sobre o caso e DA).</p><p><strong>ID da t | V14: =IFERROR(_xlfn.TEXTBEFORE(_xlfn.TEXTAFTER(U14,"Descrição do problema:</strong"),"</p>"),_xlfn.TEXTAFTER(U14,"Descrição do problema:</strong")) -> > Boa tarde, pessoa. Conforme análise do contrato original e do Termo Aditivo firmado com a PMZ Distribuidora (anexo), identificamos que houve emissão de notas durante o período de congelamento (01/06/2025 a 31/08/2025), no qual estava prevista a isenção da cobrança dos serviços Plano Advanced, Antifraude, Cartão Protegido, Gateway e Velocity. Já temos o DA do Pelizon para canclemanto das notas: 91732, 92588, 92669, 92944, 93419,94521,94588,94765, 95540. (em anexo histórico de troca de emails sobre o caso e DA). | W14: =_xlfn.CONCAT(D14:E14) -> 173513250 | X14: 46246 | Y14: =IF(X14="","Aberto","Encerrado") -> Encerrado | Z14: =IF(OR(L14="PENDENTE",L14="EM ANDAMENTO",L14="PENDENTE APROVAÇÃO CANCELAMENTO NF"),TODAY()-O14,X14-O14) -> 261 | AA14: =IF(Y14="Aberto",Z14+ROW()/100000,"") | AB14: =IF(ISNUMBER(FIND("@cielo.com.br",S14)),"Interno","Externo") -> Interno
B15: Stephany Lima | C15: =VLOOKUP(I:I,'Referencias '!H:I,2,0) -> Cobrança e Contestação | D15: 17584342 | E15: 0 | F15: 2533610419559 | G15: =VLOOKUP(H:H,'Referencias '!B:C,2,0) -> MOMENTUM EMPREENDIMENTOS IMOBILIARIOS LTDA | H15: =TRIM(_xlfn.TEXTBEFORE(_xlfn.TEXTAFTER(U15,"CNPJ/CPF:</strong>"),"</p>")) -> 47.686.555/0001-00 | I15: Contestação de cobrança | L15: FINALIZADO | M15: Médio | N15: 1018 Financeiro | Desejo falar com o setor financeiro | GIOVANNA | giovannabellotto@momentum.com.br | O15: 45993 | P15: 46000 | Q15: =TEXT(O15,"mmm/aaaa") -> dez/2025 | R15: STEPHANY LIMA DE LISBOA | S15: giovannabellotto@momentum.com.br | T15: MOMENTUM EMPREEND IMOB | U15: Olá, segue formulário enviado para Cielo E-commerce:<p><strong>Qual seu nome?:</strong> GIOVANNA</p><p><strong>Endereço de e-mail:</strong> giovannabellotto@momentum.com.br</p><p><strong>CNPJ/CPF:</strong> 47.686.555/0001-00</p><p><strong>Telefone:</strong> (11) 5039-8533</p><p><strong>Assunto:</strong> Divergência de Reajuste – Solicitação de Correção dos Valores Aplicados</p><p><strong>Merchant ID/Estabelecimento Comercial (EC):</strong> MOMENTUM EMPREEENDIMENTOS IMOBILIARIOS L</p><p><strong>Descrição do problema:</strong> Prezados, Durante a conferência das faturas recentes, identifiquei divergências no reajuste aplicado, tanto no valor mensal quanto nas tarifas por transação, que não estão de acordo com o contrato vigente. Conforme estabelecido contratualmente, o reajuste anual deve seguir exclusivamente a variação positiva do IGP-M/FGV. Para o período correspondente de 11/2024 a 10/2025, o índice acumulado é de 0,91635%, conforme cálculo oficial da Calculadora do Cidadão – Banco C | V15: =IFERROR(_xlfn.TEXTBEFORE(_xlfn.TEXTAFTER(U15,"Descrição do problema:</strong"),"</p>"),_xlfn.TEXTAFTER(U15,"Descrição do problema:</strong")) -> > Prezados, Durante a conferência das faturas recentes, identifiquei divergências no reajuste aplicado, tanto no valor mensal quanto nas tarifas por transação, que não estão de acordo com o contrato vigente. Conforme estabelecido contratualmente, o reajuste anual deve seguir exclusivamente a variação positiva do IGP-M/FGV. Para o período correspondente de 11/2024 a 10/2025, o índice acumulado é de 0,91635%, conforme cálculo oficial da Calculadora do Cidadão – Banco C | W15: =_xlfn.CONCAT(D15:E15) -> 175843420 | X15: 46246 | Y15: =IF(X15="","Aberto","Encerrado") -> Encerrado | Z15: =IF(OR(L15="PENDENTE",L15="EM ANDAMENTO",L15="PENDENTE APROVAÇÃO CANCELAMENTO NF"),TODAY()-O15,X15-O15) -> 253 | AA15: =IF(Y15="Aberto",Z15+ROW()/100000,"") | AB15: =IF(ISNUMBER(FIND("@cielo.com.br",S15)),"Interno","Externo") -> Externo
B16: Stephany Lima | C16: =VLOOKUP(I:I,'Referencias '!H:I,2,0) -> Contratos, Comercial e Cadastro | D16: 17677815 | E16: 0 | F16: 2533814485145 | G16: =VLOOKUP(H:H,'Referencias '!B:C,2,0) -> WHITE MARTINS GASES INDUSTRIAIS LTDA | H16: =TRIM(_xlfn.TEXTBEFORE(_xlfn.TEXTAFTER(U16,"CNPJ/CPF:</strong>"),"</p>")) -> 35.820.448/0001-36 | I16: Renegociação contrato | L16: FINALIZADO | M16: Médio | N16: 1018 Financeiro | Desejo falar com o setor financeiro | Caroline Mendes | carolineal@cielo.com.br | O16: 45995 | P16: 46055 | Q16: =TEXT(O16,"mmm/aaaa") -> dez/2025 | R16: STEPHANY LIMA DE LISBOA | S16: carolineal@cielo.com.br | T16: WHITE MARTINS GASES INDUSTRIAIS LTDA | U16: Olá, segue formulário enviado para Cielo E-commerce:<p><strong>Qual seu nome?:</strong> Caroline Mendes</p><p><strong>Endereço de e-mail:</strong> carolineal@cielo.com.br</p><p><strong>CNPJ/CPF:</strong> 35.820.448/0001-36</p><p><strong>Telefone:</strong> (11) 94503-1458</p><p><strong>Assunto:</strong> Atualização/renegociação de preço - analista advanced</p><p><strong>Merchant ID/Estabelecimento Comercial (EC):</strong> 35.820.448/0001-36</p><p><strong>Descrição do problema:</strong> Boa tarde, time! Tudo bem? Realizamos uma renegociação exclusivamente do serviço de Analista Advanced para este cliente, com o objetivo de mantê-los ativos e utilizando o produto. O contrato já foi assinado por ambas as partes e estou anexando o aditivo para que possamos seguir com as cobranças considerando o valor atualizado. Valor original em contrato: R$ 4.500,00 Valor negociado: R$ 4.202,04/mês Em anexo, segue o aditivo contratual. Qualquer dúvida, estou totalmente à disposição. Abraços.</p><p><stro | V16: =IFERROR(_xlfn.TEXTBEFORE(_xlfn.TEXTAFTER(U16,"Descrição do problema:</strong"),"</p>"),_xlfn.TEXTAFTER(U16,"Descrição do problema:</strong")) -> > Boa tarde, time! Tudo bem? Realizamos uma renegociação exclusivamente do serviço de Analista Advanced para este cliente, com o objetivo de mantê-los ativos e utilizando o produto. O contrato já foi assinado por ambas as partes e estou anexando o aditivo para que possamos seguir com as cobranças considerando o valor atualizado. Valor original em contrato: R$ 4.500,00 Valor negociado: R$ 4.202,04/mês Em anexo, segue o aditivo contratual. Qualquer dúvida, estou totalmente à disposição. Abraços. | W16: =_xlfn.CONCAT(D16:E16) -> 176778150 | X16: 46246 | Y16: =IF(X16="","Aberto","Encerrado") -> Encerrado | Z16: =IF(OR(L16="PENDENTE",L16="EM ANDAMENTO",L16="PENDENTE APROVAÇÃO CANCELAMENTO NF"),TODAY()-O16,X16-O16) -> 251 | AA16: =IF(Y16="Aberto",Z16+ROW()/100000,"") | AB16: =IF(ISNUMBER(FIND("@cielo.com.br",S16)),"Interno","Externo") -> Interno
B17: Vanessa Araujo | C17: =VLOOKUP(I:I,'Referencias '!H:I,2,0) -> Faturamento e Obrigações Fiscais | D17: 17839281 | E17: 0 | F17: 2534413598590 | G17: =VLOOKUP(H:H,'Referencias '!B:C,2,0) -> PROPARTS COMERCIO DE ARTIGOS ESPORTIVOS E TECNOLOGIA LTDA | H17: =TRIM(_xlfn.TEXTBEFORE(_xlfn.TEXTAFTER(U17,"CNPJ/CPF:</strong>"),"</p>")) -> 68.365.501/0001-05 | I17: Verificação Faturamento | L17: FINALIZADO | M17: Médio | N17: 1018 Financeiro | Desejo falar com o setor financeiro | Larissa Venancio | larissave@cielo.com.br | O17: 46001 | P17: 46003 | Q17: =TEXT(O17,"mmm/aaaa") -> dez/2025 | R17: Larissa QUIRINO CANUTO | S17: larissave@cielo.com.br | T17: Garmin Loja Moema 01 POS2 Fisic | U17: Olá, segue formulário enviado para Cielo E-commerce:<p><strong>Qual seu nome?:</strong> Larissa Venancio</p><p><strong>Endereço de e-mail:</strong> larissave@cielo.com.br</p><p><strong>CNPJ/CPF:</strong> 68.365.501/0001-05</p><p><strong>Telefone:</strong> (11) 97622-8821</p><p><strong>Assunto:</strong> Cliente não está sendo faturado pelo produto 3ds</p><p><strong>Merchant ID/Estabelecimento Comercial (EC):</strong> 68.365.501/0001-05</p><p><strong>Sobre qual produto ou área deseja falar?:</strong> Financeiro</p><p><strong>Como podemos te ajudar?:</strong> Desejo falar com o setor financeiro</p><p><strong>Descrição do problema:</strong> Time, tudo bem? cliente possui contratado o produto 3DS desde Agosto/2024, mas, aparentemente nunca foi cobrado - não localizei nenhuma NF e tambem nao localizei no billing. Segue contrato assinado anexo. Podem checar, por favor? Caso não tenha sido cobrado realmente, podem fazer o levantamento de quantos meses retroativos precisariamos cobrar do cl | V17: =IFERROR(_xlfn.TEXTBEFORE(_xlfn.TEXTAFTER(U17,"Descrição do problema:</strong"),"</p>"),_xlfn.TEXTAFTER(U17,"Descrição do problema:</strong")) -> > Time, tudo bem? cliente possui contratado o produto 3DS desde Agosto/2024, mas, aparentemente nunca foi cobrado - não localizei nenhuma NF e tambem nao localizei no billing. Segue contrato assinado anexo. Podem checar, por favor? Caso não tenha sido cobrado realmente, podem fazer o levantamento de quantos meses retroativos precisariamos cobrar do cl | W17: =_xlfn.CONCAT(D17:E17) -> 178392810 | X17: 46283 | Y17: =IF(X17="","Aberto","Encerrado") -> Encerrado | Z17: =IF(OR(L17="PENDENTE",L17="EM ANDAMENTO",L17="PENDENTE APROVAÇÃO CANCELAMENTO NF"),TODAY()-O17,X17-O17) -> 282 | AA17: =IF(Y17="Aberto",Z17+ROW()/100000,"") | AB17: =IF(ISNUMBER(FIND("@cielo.com.br",S17)),"Interno","Externo") -> Interno
B18: Vanessa Araujo | C18: =VLOOKUP(I:I,'Referencias '!H:I,2,0) -> Cancelamento e Reemissão de Nota Fiscal | D18: 18039556 | E18: 0 | F18: 2535111741853 | G18: =T18 -> PASSARELA CALCADOS VIRTUAL | H18: =TRIM(_xlfn.TEXTBEFORE(_xlfn.TEXTAFTER(U18,"CNPJ/CPF:</strong>"),"</p>")) -> 45.512.555/0024-47 | I18: Cancelamento de NF | L18: FINALIZADO | M18: Médio | N18: 1018 Financeiro | Desejo falar com o setor financeiro | PASSARELA MODAS LTDA EM RECUPERACAO | ariane.pasilva@cielo.com.br | O18: 46008 | P18: 46042 | Q18: =TEXT(O18,"mmm/aaaa") -> dez/2025 | R18: STEPHANY LIMA DE LISBOA | S18: ariane.pasilva@cielo.com.br | T18: PASSARELA CALCADOS VIRTUAL | U18: Olá, segue formulário enviado para Cielo E-commerce:<p><strong>Qual seu nome?:</strong> PASSARELA MODAS LTDA EM RECUPERACAO</p><p><strong>Endereço de e-mail:</strong> ariane.pasilva@cielo.com.br</p><p><strong>CNPJ/CPF:</strong> 45.512.555/0024-47</p><p><strong>Telefone:</strong> (11) 97707-1602</p><p><strong>Assunto:</strong> Notas indevida</p><p><strong>Merchant ID/Estabelecimento Comercial (EC):</strong> 45512555002447</p><p><strong>Descrição do problema:</strong> notas emitidas indevidamente, após o cancelamento do contrato em junho/2024 - Chamado de cancelamento no Salesforce: Ticket #195541 Demanda precisa ser tratada pelo N2 - Financeiro</p><p><strong>ID da transação:</strong> </p><p><strong>Código do erro:</strong> </p><p><strong>Sobre qual produto ou área deseja falar?:</strong> Financeiro</p><p><strong>Como podemos te ajudar?:</strong> Desejo falar com o setor financeiro</p><p><strong>GA Client ID:</strong> 1401063149.1757524286</p><p><strong>Lead Hash ID:</strong> 2a07344672c | V18: =IFERROR(_xlfn.TEXTBEFORE(_xlfn.TEXTAFTER(U18,"Descrição do problema:</strong"),"</p>"),_xlfn.TEXTAFTER(U18,"Descrição do problema:</strong")) -> > notas emitidas indevidamente, após o cancelamento do contrato em junho/2024 - Chamado de cancelamento no Salesforce: Ticket #195541 Demanda precisa ser tratada pelo N2 - Financeiro | W18: =_xlfn.CONCAT(D18:E18) -> 180395560 | X18: 46260 | Y18: =IF(X18="","Aberto","Encerrado") -> Encerrado | Z18: =IF(OR(L18="PENDENTE",L18="EM ANDAMENTO",L18="PENDENTE APROVAÇÃO CANCELAMENTO NF"),TODAY()-O18,X18-O18) -> 252 | AA18: =IF(Y18="Aberto",Z18+ROW()/100000,"") | AB18: =IF(ISNUMBER(FIND("@cielo.com.br",S18)),"Interno","Externo") -> Interno
A19: Aberto antigos | B19: Amanda Silva | C19: =VLOOKUP(I:I,'Referencias '!H:I,2,0) -> Cobrança e Contestação | D19: 18108887 | E19: 0 | F19: 2535310790641 | G19: =VLOOKUP(H:H,'Referencias '!B:C,2,0) -> TAM LINHAS AEREAS S/A. | H19: =TRIM(_xlfn.TEXTBEFORE(_xlfn.TEXTAFTER(U19,"CNPJ/CPF:</strong>"),"</p>")) -> 02.012.862/0001-60 | I19: Dúvidas sobre cobrança | L19: FINALIZADO | M19: Alta | N19: 1018 Financeiro | Desejo falar com o setor financeiro | Mariane Oliveira dos Santos | mariane.santos@cielo.com.br | O19: 46010 | P19: 46286 | Q19: =TEXT(O19,"mmm/aaaa") -> dez/2025 | R19: Larissa QUIRINO CANUTO | S19: mariane.santos@cielo.com.br | T19: LATAM ALLEGRO XPSP | U19: Olá, segue formulário enviado para Cielo E-commerce:<p><strong>Qual seu nome?:</strong> Mariane Oliveira dos Santos</p><p><strong>Endereço de e-mail:</strong> mariane.santos@cielo.com.br</p><p><strong>CNPJ/CPF:</strong> 02.012.862/0001-60</p><p><strong>Telefone:</strong> (11) 98407-1789</p><p><strong>Assunto:</strong> Reajuste anual</p><p><strong>Sobre qual produto ou área deseja falar?:</strong> Financeiro</p><p><strong>Como podemos te ajudar?:</strong> Desejo falar com o setor financeiro</p><p><strong>Descrição do problema:</strong> Bom dia, pessoal! Tudo bem? Eu estava analisando o último contrato assinado entre Braspag e Latam e existe uma cláusula dizendo que o reajuste IPCA deve ser aplicado em 20 de dezembro. Porém, olhando no billing verifiquei que o reajuste foi aplicado em agosto. Vamos precisar fazer o levantamento dos valores que cobramos a mais deste de cliente de agosto até dezembro e minha sugestão seria aplicar desconto das próximas faturas. Faz sentido seguirmos dessa | V19: =IFERROR(_xlfn.TEXTBEFORE(_xlfn.TEXTAFTER(U19,"Descrição do problema:</strong"),"</p>"),_xlfn.TEXTAFTER(U19,"Descrição do problema:</strong")) -> > Bom dia, pessoal! Tudo bem? Eu estava analisando o último contrato assinado entre Braspag e Latam e existe uma cláusula dizendo que o reajuste IPCA deve ser aplicado em 20 de dezembro. Porém, olhando no billing verifiquei que o reajuste foi aplicado em agosto. Vamos precisar fazer o levantamento dos valores que cobramos a mais deste de cliente de agosto até dezembro e minha sugestão seria aplicar desconto das próximas faturas. Faz sentido seguirmos dessa | W19: =_xlfn.CONCAT(D19:E19) -> 181088870 | X19: 46287 | Y19: =IF(X19="","Aberto","Encerrado") -> Encerrado | Z19: =IF(OR(L19="PENDENTE",L19="EM ANDAMENTO",L19="PENDENTE APROVAÇÃO CANCELAMENTO NF"),TODAY()-O19,X19-O19) -> 277 | AA19: =IF(Y19="Aberto",Z19+ROW()/100000,"") | AB19: =IF(ISNUMBER(FIND("@cielo.com.br",S19)),"Interno","Externo") -> Interno
A20: Aberto antigos | B20: Stephany Lima | C20: =VLOOKUP(I:I,'Referencias '!H:I,2,0) -> Cobrança e Contestação | D20: 18167620 | E20: 0 | F20: 2535616833624 | G20: =T20 -> LIMFI COMERCIO DE MODA FEMININA | H20: =TRIM(_xlfn.TEXTBEFORE(_xlfn.TEXTAFTER(U20,"CNPJ/CPF:</strong>"),"</p>")) -> 08.518.361/0001-36 | I20: Contestação de cobrança | J20: Resolvido | L20: FINALIZADO | M20: Alta | N20: 1018 Financeiro | Desejo falar com o setor financeiro | Aria | ariane.pasilva@cielo.com.br | O20: 46013 | P20: 46058 | Q20: =TEXT(O20,"mmm/aaaa") -> dez/2025 | R20: Larissa QUIRINO CANUTO | S20: ariane.pasilva@cielo.com.br | T20: LIMFI COMERCIO DE MODA FEMININA | U20: Olá, segue formulário enviado para Cielo E-commerce:<p><strong>Qual seu nome?:</strong> Aria</p><p><strong>Endereço de e-mail:</strong> ariane.pasilva@cielo.com.br</p><p><strong>CNPJ/CPF:</strong> 08.518.361/0001-36</p><p><strong>Telefone:</strong> (11) 97707-1602</p><p><strong>Assunto:</strong> Baixa de NF</p><p><strong>Merchant ID/Estabelecimento Comercial (EC):</strong> 08518361000136</p><p><strong>Descrição do problema:</strong> Por favor, transfira esse chamado para o N2, financeiro. Foram emitido notas indevidas para o cliente. Houve cancelamento de antifraude + analista em 02/10/2024 e emitimos notas após o cancelamento.</p><p><strong>ID da transação:</strong> </p><p><strong>Código do erro:</strong> </p><p><strong>Sobre qual produto ou área deseja falar?:</strong> Financeiro</p><p><strong>Como podemos te ajudar?:</strong> Desejo falar com o setor financeiro</p><p><strong>GA Client ID:</strong> 1401063149.1757524286</p><p><strong>Lead Hash ID:</strong> 2a07344672c93c9ca782cc07cf | V20: =IFERROR(_xlfn.TEXTBEFORE(_xlfn.TEXTAFTER(U20,"Descrição do problema:</strong"),"</p>"),_xlfn.TEXTAFTER(U20,"Descrição do problema:</strong")) -> > Por favor, transfira esse chamado para o N2, financeiro. Foram emitido notas indevidas para o cliente. Houve cancelamento de antifraude + analista em 02/10/2024 e emitimos notas após o cancelamento. | W20: =_xlfn.CONCAT(D20:E20) -> 181676200 | X20: 46288 | Y20: =IF(X20="","Aberto","Encerrado") -> Encerrado | Z20: =IF(OR(L20="PENDENTE",L20="EM ANDAMENTO",L20="PENDENTE APROVAÇÃO CANCELAMENTO NF"),TODAY()-O20,X20-O20) -> 275 | AA20: =IF(Y20="Aberto",Z20+ROW()/100000,"") | AB20: =IF(ISNUMBER(FIND("@cielo.com.br",S20)),"Interno","Externo") -> Interno
B21: Vanessa Araujo | C21: =VLOOKUP(I:I,'Referencias '!H:I,2,0) -> Pagamentos, Boletos e Recebimentos | D21: 18201926 | E21: 0 | F21: 2535717858088 | G21: =VLOOKUP(H:H,'Referencias '!B:C,2,0) -> REBORN TECNOLOGIA E SERVICOS LTDA | H21: =TRIM(_xlfn.TEXTBEFORE(_xlfn.TEXTAFTER(U21,"CNPJ/CPF:</strong>"),"</p>")) -> 59.627.567/0001-35 | I21: Prorrogação / Reenvio de boleto | L21: FINALIZADO | M21: Médio | N21: 1018 Financeiro | Desejo falar com o setor financeiro | Giulia | giuliac@cielo.com.br | O21: 46014 | P21: 46062 | Q21: =TEXT(O21,"mmm/aaaa") -> dez/2025 | R21: ECOMMERCE BP SUPORTE FINANCEIRO N2 | S21: giuliac@cielo.com.br | T21: REBORN | U21: Olá, segue formulário enviado para Cielo E-commerce:<p><strong>Qual seu nome?:</strong> Giulia</p><p><strong>Endereço de e-mail:</strong> giuliac@cielo.com.br</p><p><strong>CNPJ/CPF:</strong> 59.627.567/0001-35</p><p><strong>Telefone:</strong> (11) 99104-1320</p><p><strong>Assunto:</strong> Reemissao de boleto sem multa</p><p><strong>Merchant ID/Estabelecimento Comercial (EC):</strong> 59.627.567/0001-35</p><p><strong>Descrição do problema:</strong> Boa tarde! Pessoal, o cliente Reborn (CNPJ: 59.627.567/0001-35) pediu a reemissao do boleto de setup sem juros e multa. Poderiam enviar? O motivo do atraso no pagamento foi por que aconteceram alguns erros do nosso lado, atraso para gerar as chaves e taxa de antecipação, e por isso o cliente aguardou para fazer o pagamento enquanto resolvíamos. Assim que reemitirem o boleto ele ja vai pagar! Obrigada!</p><p><strong>ID da transação:</strong> </p><p><strong>Código do erro:</strong> </p><p><strong>Sobre qual produto ou área deseja falar?:</ | V21: =IFERROR(_xlfn.TEXTBEFORE(_xlfn.TEXTAFTER(U21,"Descrição do problema:</strong"),"</p>"),_xlfn.TEXTAFTER(U21,"Descrição do problema:</strong")) -> > Boa tarde! Pessoal, o cliente Reborn (CNPJ: 59.627.567/0001-35) pediu a reemissao do boleto de setup sem juros e multa. Poderiam enviar? O motivo do atraso no pagamento foi por que aconteceram alguns erros do nosso lado, atraso para gerar as chaves e taxa de antecipação, e por isso o cliente aguardou para fazer o pagamento enquanto resolvíamos. Assim que reemitirem o boleto ele ja vai pagar! Obrigada! | W21: =_xlfn.CONCAT(D21:E21) -> 182019260 | X21: 46244 | Y21: =IF(X21="","Aberto","Encerrado") -> Encerrado | Z21: =IF(OR(L21="PENDENTE",L21="EM ANDAMENTO",L21="PENDENTE APROVAÇÃO CANCELAMENTO NF"),TODAY()-O21,X21-O21) -> 230 | AA21: =IF(Y21="Aberto",Z21+ROW()/100000,"") | AB21: =IF(ISNUMBER(FIND("@cielo.com.br",S21)),"Interno","Externo") -> Interno
A22: Aberto antigos | B22: Emilly Maria | C22: =VLOOKUP(I:I,'Referencias '!H:I,2,0) -> Contratos, Comercial e Cadastro | D22: 18271042 | E22: 0 | F22: 2536318908852 | G22: =VLOOKUP(H:H,'Referencias '!B:C,2,0) -> 4 BIO MEDICAMENTOS S.A. | H22: =TRIM(_xlfn.TEXTBEFORE(_xlfn.TEXTAFTER(U22,"CNPJ/CPF:</strong>"),"</p>")) -> 07.015.691/0001-46 | I22: Atualização Condições Comerciais | L22: FINALIZADO | M22: Alta | N22: 1018 Financeiro | Desejo falar com o setor financeiro | Mariane Oliveira dos Santos | mariane.santos@cielo.com.br | O22: 46020 | P22: 46062 | Q22: =TEXT(O22,"mmm/aaaa") -> dez/2025 | R22: Larissa QUIRINO CANUTO | S22: mariane.santos@cielo.com.br | T22: 4 BIO MEDICAMENTOS SA | U22: Olá, segue formulário enviado para Cielo E-commerce:<p><strong>Qual seu nome?:</strong> Mariane Oliveira dos Santos</p><p><strong>Endereço de e-mail:</strong> mariane.santos@cielo.com.br</p><p><strong>CNPJ/CPF:</strong> 07.015.691/0001-46</p><p><strong>Telefone:</strong> (11) 98407-1789</p><p><strong>Assunto:</strong> Atualização das Condições Comerciais</p><p><strong>Merchant ID/Estabelecimento Comercial (EC):</strong> 07.015.691/0001-46</p><p><strong>Descrição do problema:</strong> Boa tarde, pessoal! Tudo bem? Poderiam atualizar as condições comerciais do cliente 4Bio, segue em anexo o contrato assinado.</p><p><strong>ID da transação:</strong> </p><p><strong>Código do erro:</strong> </p><p><strong>Sobre qual produto ou área deseja falar?:</strong> Financeiro</p><p><strong>Como podemos te ajudar?:</strong> Desejo falar com o setor financeiro</p><p><strong>GA Client ID:</strong> 2073864016.1764846153</p><p><strong>Lead Hash ID:</strong> c539f6b58efe9518ed2e3f1f181196c6d44dcdad1ded01c | V22: =IFERROR(_xlfn.TEXTBEFORE(_xlfn.TEXTAFTER(U22,"Descrição do problema:</strong"),"</p>"),_xlfn.TEXTAFTER(U22,"Descrição do problema:</strong")) -> > Boa tarde, pessoal! Tudo bem? Poderiam atualizar as condições comerciais do cliente 4Bio, segue em anexo o contrato assinado. | W22: =_xlfn.CONCAT(D22:E22) -> 182710420 | X22: 46287 | Y22: =IF(X22="","Aberto","Encerrado") -> Encerrado | Z22: =IF(OR(L22="PENDENTE",L22="EM ANDAMENTO",L22="PENDENTE APROVAÇÃO CANCELAMENTO NF"),TODAY()-O22,X22-O22) -> 267 | AA22: =IF(Y22="Aberto",Z22+ROW()/100000,"") | AB22: =IF(ISNUMBER(FIND("@cielo.com.br",S22)),"Interno","Externo") -> Interno
A23: Aberto antigos | B23: Stephany Lima | C23: =VLOOKUP(I:I,'Referencias '!H:I,2,0) -> Cancelamento e Reemissão de Nota Fiscal | D23: 18252534 | E23: 0 | F23: 2536311895901 | G23: =VLOOKUP(H:H,'Referencias '!B:C,2,0) -> AFINZ INSTITUICAO DE PAGAMENTO S.A. | H23: =TRIM(_xlfn.TEXTBEFORE(_xlfn.TEXTAFTER(U23,"CNPJ/CPF:</strong>"),"</p>")) -> 60.114.865/0001-00 | I23: Cancelamento de NF | J23: Aguardando o Gerente comercial ajustar com o time de salesforce o cadastro do cliente no sap | L23: EM ANDAMENTO | M23: Alta | N23: 1018 Financeiro | Desejo falar com o setor financeiro | Joice Rosa | joice.dsilva@cielo.com.br | O23: 46020 | P23: 23/09/2026 | Q23: =TEXT(O23,"mmm/aaaa") -> dez/2025 | R23: STEPHANY LIMA DE LISBOA | S23: joice.dsilva@cielo.com.br | T23: PAGOLIVRE | U23: Olá, segue formulário enviado para Cielo E-commerce:<p><strong>Qual seu nome?:</strong> Joice Rosa</p><p><strong>Endereço de e-mail:</strong> joice.dsilva@cielo.com.br</p><p><strong>CNPJ/CPF:</strong> 60.114.865/0001-00</p><p><strong>Telefone:</strong> (11) 99526-4876</p><p><strong>Assunto:</strong> Cessão contratual</p><p><strong>Merchant ID/Estabelecimento Comercial (EC):</strong> não tem</p><p><strong>Descrição do problema:</strong> Bom dia, Time! Estão bem? Chamado aberto para informar cessão contratual para alteração do CNPJ e Razão Social. Antigo: Razão Social: PAGOLIVRE TECNOLOGIA S.A. CNPJ: 21.262.661/0001-65 Novo: Razão Social: AFINZ INSTITUICAO DE PAGAMENTO S.A. CNPJ- 60.114.865/0001-00</p><p><strong>ID da transação:</strong> </p><p><strong>Código do erro:</strong> </p><p><strong>Sobre qual produto ou área deseja falar?:</strong> Financeiro</p><p><strong>Como podemos te ajudar?:</strong> Desejo falar com o setor financeiro</p><p><strong>GA Client ID:</strong> 707146309 | V23: =IFERROR(_xlfn.TEXTBEFORE(_xlfn.TEXTAFTER(U23,"Descrição do problema:</strong"),"</p>"),_xlfn.TEXTAFTER(U23,"Descrição do problema:</strong")) -> > Bom dia, Time! Estão bem? Chamado aberto para informar cessão contratual para alteração do CNPJ e Razão Social. Antigo: Razão Social: PAGOLIVRE TECNOLOGIA S.A. CNPJ: 21.262.661/0001-65 Novo: Razão Social: AFINZ INSTITUICAO DE PAGAMENTO S.A. CNPJ- 60.114.865/0001-00 | W23: =_xlfn.CONCAT(D23:E23) -> 182525340 | Y23: =IF(X23="","Aberto","Encerrado") -> Aberto | Z23: =IF(OR(L23="PENDENTE",L23="EM ANDAMENTO",L23="PENDENTE APROVAÇÃO CANCELAMENTO NF"),TODAY()-O23,X23-O23) -> 270 | AA23: =IF(Y23="Aberto",Z23+ROW()/100000,"") -> 270.00023 | AB23: =IF(ISNUMBER(FIND("@cielo.com.br",S23)),"Interno","Externo") -> Interno
B24: Vanessa Araujo | C24: =VLOOKUP(I:I,'Referencias '!H:I,2,0) -> Cancelamento e Reemissão de Nota Fiscal | D24: 18250972 | E24: 0 | F24: 0 | G24: =T24 -> PRODUTO SH | H24: =TRIM(_xlfn.TEXTBEFORE(_xlfn.TEXTAFTER(U24,"CNPJ/CPF:</strong>"),"</p>")) -> 19.112.842/0002-44 | I24: Cancelamento de NF / reemissão | L24: FINALIZADO | M24: Médio | N24: 1018 Financeiro | Desejo falar com o setor financeiro | INFRACOMMERCE TATIX COMERCIO E PARTICIPACOES LTDA | ariane.pasilva@cielo.com.br | O24: 46020 | P24: 46030 | Q24: =TEXT(O24,"mmm/aaaa") -> dez/2025 | R24: STEPHANY LIMA DE LISBOA | S24: ariane.pasilva@cielo.com.br | T24: PRODUTO SH | U24: Olá, segue formulário enviado para Cielo E-commerce:<p><strong>Qual seu nome?:</strong> INFRACOMMERCE TATIX COMERCIO E PARTICIPACOES LTDA</p><p><strong>Endereço de e-mail:</strong> ariane.pasilva@cielo.com.br</p><p><strong>CNPJ/CPF:</strong> 19.112.842/0002-44</p><p><strong>Telefone:</strong> (11) 97707-1602</p><p><strong>Assunto:</strong> Substituição CNPJ NFS</p><p><strong>Merchant ID/Estabelecimento Comercial (EC):</strong> 19.112.842/0002-44</p><p><strong>Descrição do problema:</strong> Transferir chamado para o financeiro. Bloqueio temporário de serviços.</p><p><strong>ID da transação:</strong> </p><p><strong>Código do erro:</strong> </p><p><strong>Sobre qual produto ou área deseja falar?:</strong> Financeiro</p><p><strong>Como podemos te ajudar?:</strong> Desejo falar com o setor financeiro</p><p><strong>GA Client ID:</strong> 1401063149.1757524286</p><p><strong>Lead Hash ID:</strong> 2a07344672c93c9ca782cc07cf9dc37d0cd4c270e817a83b9f87f9b32f0130a9</p><p><strong>Lead Form ID:</s | V24: =IFERROR(_xlfn.TEXTBEFORE(_xlfn.TEXTAFTER(U24,"Descrição do problema:</strong"),"</p>"),_xlfn.TEXTAFTER(U24,"Descrição do problema:</strong")) -> > Transferir chamado para o financeiro. Bloqueio temporário de serviços. | W24: =_xlfn.CONCAT(D24:E24) -> 182509720 | X24: 46214 | Y24: =IF(X24="","Aberto","Encerrado") -> Encerrado | Z24: =IF(OR(L24="PENDENTE",L24="EM ANDAMENTO",L24="PENDENTE APROVAÇÃO CANCELAMENTO NF"),TODAY()-O24,X24-O24) -> 194 | AA24: =IF(Y24="Aberto",Z24+ROW()/100000,"") | AB24: =IF(ISNUMBER(FIND("@cielo.com.br",S24)),"Interno","Externo") -> Interno
A25: Aberto antigos | B25: Amanda Silva | C25: =VLOOKUP(I:I,'Referencias '!H:I,2,0) -> Cancelamento e Reemissão de Nota Fiscal | D25: 18250214 | E25: 0 | F25: 2536310894312 | G25: =T25 | H25: =TRIM(_xlfn.TEXTBEFORE(_xlfn.TEXTAFTER(U25,"CNPJ/CPF:</strong>"),"</p>")) -> 19.112.842/0002-44 | I25: Cancelamento de NF | L25: FINALIZADO | M25: Alta | N25: 1018 Financeiro | Desejo falar com o setor financeiro | INFRACOMMERCE TATIX COMERCIO E PARTICIPACOES LTDA | ariane.pasilva@cielo.com.br | O25: 46020 | P25: 46020 | Q25: =TEXT(O25,"mmm/aaaa") -> dez/2025 | R25: ECOMMERCE BP SUPORTE FINANCEIRO N2 | S25: ariane.pasilva@cielo.com.br | U25: Olá, segue formulário enviado para Cielo E-commerce:<p><strong>Qual seu nome?:</strong> INFRACOMMERCE TATIX COMERCIO E PARTICIPACOES LTDA</p><p><strong>Endereço de e-mail:</strong> ariane.pasilva@cielo.com.br</p><p><strong>CNPJ/CPF:</strong> 19.112.842/0002-44</p><p><strong>Telefone:</strong> (11) 97707-1602</p><p><strong>Assunto:</strong> Substituição CNPJ NFS</p><p><strong>Merchant ID/Estabelecimento Comercial (EC):</strong> 19.112.842/0002-44</p><p><strong>Descrição do problema:</strong> Transferir chamado para N2. Substituição de NF antiga.</p><p><strong>ID da transação:</strong> </p><p><strong>Código do erro:</strong> </p><p><strong>Sobre qual produto ou área deseja falar?:</strong> Financeiro</p><p><strong>Como podemos te ajudar?:</strong> Desejo falar com o setor financeiro</p><p><strong>GA Client ID:</strong> 1401063149.1757524286</p><p><strong>Lead Hash ID:</strong> 2a07344672c93c9ca782cc07cf9dc37d0cd4c270e817a83b9f87f9b32f0130a9</p><p><strong>Lead Form ID:</strong> 2a0734467 | V25: =IFERROR(_xlfn.TEXTBEFORE(_xlfn.TEXTAFTER(U25,"Descrição do problema:</strong"),"</p>"),_xlfn.TEXTAFTER(U25,"Descrição do problema:</strong")) -> > Transferir chamado para N2. Substituição de NF antiga. | W25: =_xlfn.CONCAT(D25:E25) -> 182502140 | X25: 46289 | Y25: =IF(X25="","Aberto","Encerrado") -> Encerrado | Z25: =IF(OR(L25="PENDENTE",L25="EM ANDAMENTO",L25="PENDENTE APROVAÇÃO CANCELAMENTO NF"),TODAY()-O25,X25-O25) -> 269 | AA25: =IF(Y25="Aberto",Z25+ROW()/100000,"") | AB25: =IF(ISNUMBER(FIND("@cielo.com.br",S25)),"Interno","Externo") -> Interno
A26: Aberto antigos | B26: Stephany Lima | C26: =VLOOKUP(I:I,'Referencias '!H:I,2,0) -> Cancelamento e Reemissão de Nota Fiscal | D26: 18245555 | E26: 0 | F26: 2536309891162 | G26: =VLOOKUP(H:H,'Referencias '!B:C,2,0) -> PARDO SERVICOS IMOBILIARIOS E ADMINISTRACAO HOTELEIRA S/A | H26: =TRIM(_xlfn.TEXTBEFORE(_xlfn.TEXTAFTER(U26,"CNPJ/CPF:</strong>"),"</p>")) -> 30.050.246/0001-39 | I26: Cancelamento de NF | J26: Aguardando a verificação do Everton ou da Vanessa se já enviamos o DA para o Calil | L26: EM ANDAMENTO | M26: Alta | N26: 1018 Financeiro | Desejo falar com o setor financeiro | Ariane de Paula Silva | ariane.pasilva@cielo.com.br | O26: 46020 | P26: 23/09/2026 | Q26: =TEXT(O26,"mmm/aaaa") -> dez/2025 | R26: STEPHANY LIMA DE LISBOA | S26: ariane.pasilva@cielo.com.br | U26: Olá, segue formulário enviado para Cielo E-commerce:<p><strong>Endereço de e-mail:</strong> ariane.pasilva@cielo.com.br</p><p><strong>Qual seu nome?:</strong> Ariane de Paula Silva</p><p><strong>CNPJ/CPF:</strong> 30.050.246/0001-39</p><p><strong>Telefone:</strong> (11) 97707-1602</p><p><strong>Assunto:</strong> Cancelar FS</p><p><strong>Merchant ID/Estabelecimento Comercial (EC):</strong> 30050246000139</p><p><strong>Descrição do problema:</strong> Transferir esse chamado para N2. Cancelamento de NFS. DAS em anexo.</p><p><strong>ID da transação:</strong> </p><p><strong>Código do erro:</strong> </p><p><strong>Sobre qual produto ou área deseja falar?:</strong> Financeiro</p><p><strong>Como podemos te ajudar?:</strong> Desejo falar com o setor financeiro</p><p><strong>GA Client ID:</strong> 1401063149.1757524286</p><p><strong>Lead Hash ID:</strong> 2a07344672c93c9ca782cc07cf9dc37d0cd4c270e817a83b9f87f9b32f0130a9</p><p><strong>Lead Form ID:</strong> 2a07344672c93c9ca782cc07cf9dc37d0cd4c2 | V26: =IFERROR(_xlfn.TEXTBEFORE(_xlfn.TEXTAFTER(U26,"Descrição do problema:</strong"),"</p>"),_xlfn.TEXTAFTER(U26,"Descrição do problema:</strong")) -> > Transferir esse chamado para N2. Cancelamento de NFS. DAS em anexo. | W26: =_xlfn.CONCAT(D26:E26) -> 182455550 | Y26: =IF(X26="","Aberto","Encerrado") -> Aberto | Z26: =IF(OR(L26="PENDENTE",L26="EM ANDAMENTO",L26="PENDENTE APROVAÇÃO CANCELAMENTO NF"),TODAY()-O26,X26-O26) -> 270 | AA26: =IF(Y26="Aberto",Z26+ROW()/100000,"") -> 270.00026 | AB26: =IF(ISNUMBER(FIND("@cielo.com.br",S26)),"Interno","Externo") -> Interno
A27: Aberto antigos | B27: Emilly Maria | C27: =VLOOKUP(I:I,'Referencias '!H:I,2,0) -> Cancelamento e Reemissão de Nota Fiscal | D27: 18245159 | E27: 0 | F27: 2536308890842 | G27: =T27 | H27: =TRIM(_xlfn.TEXTBEFORE(_xlfn.TEXTAFTER(U27,"CNPJ/CPF:</strong>"),"</p>")) -> 09.509.776/0001-06 | I27: Cancelamento de NF | L27: FINALIZADO | M27: Alta | N27: 1018 Financeiro | Desejo falar com o setor financeiro | Ariane de Paula Silva | ariane.pasilva@cielo.com.br | O27: 46020 | P27: 46020 | Q27: =TEXT(O27,"mmm/aaaa") -> dez/2025 | R27: ECOMMERCE BP SUPORTE FINANCEIRO N2 | S27: ariane.pasilva@cielo.com.br | U27: Olá, segue formulário enviado para Cielo E-commerce:<p><strong>Qual seu nome?:</strong> Ariane de Paula Silva</p><p><strong>Endereço de e-mail:</strong> ariane.pasilva@cielo.com.br</p><p><strong>CNPJ/CPF:</strong> 09.509.776/0001-06</p><p><strong>Telefone:</strong> (11) 97707-1602</p><p><strong>Assunto:</strong> Cancelar FS</p><p><strong>Merchant ID/Estabelecimento Comercial (EC):</strong> 09509776000106</p><p><strong>Descrição do problema:</strong> Transferir chamado para N2, time financeiro. Cancelamento de NF. DAS em anexo.</p><p><strong>ID da transação:</strong> </p><p><strong>Código do erro:</strong> </p><p><strong>Sobre qual produto ou área deseja falar?:</strong> Financeiro</p><p><strong>Como podemos te ajudar?:</strong> Desejo falar com o setor financeiro</p><p><strong>GA Client ID:</strong> 1401063149.1757524286</p><p><strong>Lead Hash ID:</strong> 2a07344672c93c9ca782cc07cf9dc37d0cd4c270e817a83b9f87f9b32f0130a9</p><p><strong>Lead Form ID:</strong> 2a07344672c93c9ca782cc07cf9 | V27: =IFERROR(_xlfn.TEXTBEFORE(_xlfn.TEXTAFTER(U27,"Descrição do problema:</strong"),"</p>"),_xlfn.TEXTAFTER(U27,"Descrição do problema:</strong")) -> > Transferir chamado para N2, time financeiro. Cancelamento de NF. DAS em anexo. | W27: =_xlfn.CONCAT(D27:E27) -> 182451590 | X27: 46287 | Y27: =IF(X27="","Aberto","Encerrado") -> Encerrado | Z27: =IF(OR(L27="PENDENTE",L27="EM ANDAMENTO",L27="PENDENTE APROVAÇÃO CANCELAMENTO NF"),TODAY()-O27,X27-O27) -> 267 | AA27: =IF(Y27="Aberto",Z27+ROW()/100000,"") | AB27: =IF(ISNUMBER(FIND("@cielo.com.br",S27)),"Interno","Externo") -> Interno
A28: Aberto antigos | B28: Pamela de Sá | C28: =VLOOKUP(I:I,'Referencias '!H:I,2,0) -> Cancelamento e Reemissão de Nota Fiscal | D28: 18244519 | E28: 0 | F28: 2536308890373 | G28: =T28 -> EDITORA SANAR | H28: =TRIM(_xlfn.TEXTBEFORE(_xlfn.TEXTAFTER(U28,"CNPJ/CPF:</strong>"),"</p>")) -> 18.990.682/0001-92 | I28: Cancelamento de NF | L28: FINALIZADO | M28: Alta | N28: 1018 Financeiro | Desejo falar com o setor financeiro | Ariane de Paula Silva | ariane.pasilva@cielo.com.br | O28: 46020 | P28: 19/05/2026 | Q28: =TEXT(O28,"mmm/aaaa") -> dez/2025 | R28: STEPHANY LIMA DE LISBOA | S28: ariane.pasilva@cielo.com.br | T28: EDITORA SANAR | U28: Olá, segue formulário enviado para Cielo E-commerce:<p><strong>Qual seu nome?:</strong> Ariane de Paula Silva</p><p><strong>Endereço de e-mail:</strong> ariane.pasilva@cielo.com.br</p><p><strong>CNPJ/CPF:</strong> 18.990.682/0001-92</p><p><strong>Telefone:</strong> (11) 97707-1602</p><p><strong>Assunto:</strong> Cancelar FS</p><p><strong>Merchant ID/Estabelecimento Comercial (EC):</strong> 18990682000192</p><p><strong>Sobre qual produto ou área deseja falar?:</strong> Financeiro</p><p><strong>Como podemos te ajudar?:</strong> Desejo falar com o setor financeiro</p><p><strong>Descrição do problema:</strong> Por favor, transferir esse chamado para N2, time financeiro. Solicitação: Cancelar a prejuízo PDD, todas as NFS em aberto para cliente EDITORA SANAR S.A.</p><p><strong>GA Client ID:</strong> 1401063149.1757524286</p><p><strong>Lead Hash ID:</strong> 2a07344672c93c9ca782cc07cf9dc37d0cd4c270e817a83b9f87f9b32f0130a9</p><p><strong>Lead Form ID:</strong> 2a07344672c93c9ca782cc07cf9dc37d | V28: =IFERROR(_xlfn.TEXTBEFORE(_xlfn.TEXTAFTER(U28,"Descrição do problema:</strong"),"</p>"),_xlfn.TEXTAFTER(U28,"Descrição do problema:</strong")) -> > Por favor, transferir esse chamado para N2, time financeiro. Solicitação: Cancelar a prejuízo PDD, todas as NFS em aberto para cliente EDITORA SANAR S.A. | W28: =_xlfn.CONCAT(D28:E28) -> 182445190 | X28: 46290 | Y28: =IF(X28="","Aberto","Encerrado") -> Encerrado | Z28: =IF(OR(L28="PENDENTE",L28="EM ANDAMENTO",L28="PENDENTE APROVAÇÃO CANCELAMENTO NF"),TODAY()-O28,X28-O28) -> 270 | AA28: =IF(Y28="Aberto",Z28+ROW()/100000,"") | AB28: =IF(ISNUMBER(FIND("@cielo.com.br",S28)),"Interno","Externo") -> Interno
A29: Aberto antigos | B29: Amanda Silva | C29: =VLOOKUP(I:I,'Referencias '!H:I,2,0) -> Cancelamento e Reemissão de Nota Fiscal | D29: 18273616 | E29: 0 | F29: 2536408910812 | G29: =VLOOKUP(H:H,'Referencias '!B:C,2,0) -> COVABRA SUPERMERCADOS LTDA | H29: =TRIM(_xlfn.TEXTBEFORE(_xlfn.TEXTAFTER(U29,"CNPJ/CPF:</strong>"),"</p>")) -> 61.233.151/0005-08 | I29: Cancelamento de NF | L29: FINALIZADO | M29: Alta | N29: 1018 Financeiro | Desejo falar com o setor financeiro | COVABRA SUPERMERCADOS LTDA | ariane.pasilva@cielo.com.br | O29: 46021 | P29: 46164 | Q29: =TEXT(O29,"mmm/aaaa") -> dez/2025 | R29: STEPHANY LIMA DE LISBOA | S29: ariane.pasilva@cielo.com.br | U29: Olá, segue formulário enviado para Cielo E-commerce:<p><strong>Qual seu nome?:</strong> COVABRA SUPERMERCADOS LTDA</p><p><strong>Endereço de e-mail:</strong> ariane.pasilva@cielo.com.br</p><p><strong>CNPJ/CPF:</strong> 61.233.151/0005-08</p><p><strong>Telefone:</strong> (11) 97707-1602</p><p><strong>Assunto:</strong> Baixar NF</p><p><strong>Merchant ID/Estabelecimento Comercial (EC):</strong> 61.233.151/0005-08</p><p><strong>Descrição do problema:</strong> Transferir chamado para N2. Caso onde precisam baixar a NF conforme todo o histórico tratado com a cliente em novembro/2025. irei anexar as evidências.</p><p><strong>ID da transação:</strong> </p><p><strong>Código do erro:</strong> </p><p><strong>Sobre qual produto ou área deseja falar?:</strong> Financeiro</p><p><strong>Como podemos te ajudar?:</strong> Desejo falar com o setor financeiro</p><p><strong>GA Client ID:</strong> 1401063149.1757524286</p><p><strong>Lead Hash ID:</strong> 2a07344672c93c9ca782cc07cf9dc37d0cd4c270e817a83b9f | V29: =IFERROR(_xlfn.TEXTBEFORE(_xlfn.TEXTAFTER(U29,"Descrição do problema:</strong"),"</p>"),_xlfn.TEXTAFTER(U29,"Descrição do problema:</strong")) -> > Transferir chamado para N2. Caso onde precisam baixar a NF conforme todo o histórico tratado com a cliente em novembro/2025. irei anexar as evidências. | W29: =_xlfn.CONCAT(D29:E29) -> 182736160 | X29: 46288 | Y29: =IF(X29="","Aberto","Encerrado") -> Encerrado | Z29: =IF(OR(L29="PENDENTE",L29="EM ANDAMENTO",L29="PENDENTE APROVAÇÃO CANCELAMENTO NF"),TODAY()-O29,X29-O29) -> 267 | AA29: =IF(Y29="Aberto",Z29+ROW()/100000,"") | AB29: =IF(ISNUMBER(FIND("@cielo.com.br",S29)),"Interno","Externo") -> Interno
B30: Stephany Lima | C30: =VLOOKUP(I:I,'Referencias '!H:I,2,0) -> Cancelamento e Reemissão de Nota Fiscal | D30: 18345627 | E30: 0 | F30: 0 | G30: =T30 -> SOLEAH | H30: =TRIM(_xlfn.TEXTBEFORE(_xlfn.TEXTAFTER(U30,"CNPJ/CPF:</strong>"),"</p>")) -> 18.539.846/0001-60 | I30: Cancelamento de NF / reemissão | L30: FINALIZADO | M30: Médio | N30: 1018 Financeiro | Desejo falar com o setor financeiro | M.P. IDALGO INDUSTRIA E COMERCIO DE ACESSORIOS DE MODA LTDA | ariane.pasilva@cielo.com.br | O30: 46027 | P30: 46052 | Q30: =TEXT(O30,"mmm/aaaa") -> jan/2026 | R30: Larissa QUIRINO CANUTO | S30: ariane.pasilva@cielo.com.br | T30: SOLEAH | U30: Olá, segue formulário enviado para Cielo E-commerce:<p><strong>Qual seu nome?:</strong> M.P. IDALGO INDUSTRIA E COMERCIO DE ACESSORIOS DE MODA LTDA</p><p><strong>Endereço de e-mail:</strong> ariane.pasilva@cielo.com.br</p><p><strong>CNPJ/CPF:</strong> 18.539.846/0001-60</p><p><strong>Telefone:</strong> (11) 97707-1602</p><p><strong>Assunto:</strong> Cancelar NFS</p><p><strong>Merchant ID/Estabelecimento Comercial (EC):</strong> 18.539.846/0001-60</p><p><strong>Descrição do problema:</strong> Por favor transferir esse chamado para N2 - tratar por financeiro time Everton Cancelamento de nota. cliente: M.P. IDALGO INDUSTRIA E COMERCIO DE ACESSORIOS DE MODA LTDA Cancelar 80 NFS: 68330 68598 68601 68607 70045 70219 70473 70582 71725 71981 72103 72689 73347 73590 73831 74261 75016 75413 75428 75582 76534 76983 76993 77018 78395 78647 78651 78661 79987 80909 80917 80942 81530 81932 82008 82329 83352 83518 84025 84031 84931 85370 85451 86106 86411 87284 87401 87636 88236 89119 89200 89365 8 | V30: =IFERROR(_xlfn.TEXTBEFORE(_xlfn.TEXTAFTER(U30,"Descrição do problema:</strong"),"</p>"),_xlfn.TEXTAFTER(U30,"Descrição do problema:</strong")) -> > Por favor transferir esse chamado para N2 - tratar por financeiro time Everton Cancelamento de nota. cliente: M.P. IDALGO INDUSTRIA E COMERCIO DE ACESSORIOS DE MODA LTDA Cancelar 80 NFS: 68330 68598 68601 68607 70045 70219 70473 70582 71725 71981 72103 72689 73347 73590 73831 74261 75016 75413 75428 75582 76534 76983 76993 77018 78395 78647 78651 78661 79987 80909 80917 80942 81530 81932 82008 82329 83352 83518 84025 84031 84931 85370 85451 86106 86411 87284 87401 87636 88236 89119 89200 89365 8 | W30: =_xlfn.CONCAT(D30:E30) -> 183456270 | X30: 46224 | Y30: =IF(X30="","Aberto","Encerrado") -> Encerrado | Z30: =IF(OR(L30="PENDENTE",L30="EM ANDAMENTO",L30="PENDENTE APROVAÇÃO CANCELAMENTO NF"),TODAY()-O30,X30-O30) -> 197 | AA30: =IF(Y30="Aberto",Z30+ROW()/100000,"") | AB30: =IF(ISNUMBER(FIND("@cielo.com.br",S30)),"Interno","Externo") -> Interno
B31: Pamela de Sá | C31: =VLOOKUP(I:I,'Referencias '!H:I,2,0) -> Atendimento Administrativo e Suporte | D31: 18438855 | E31: 0 | F31: 2600717028611 | G31: =VLOOKUP(H:H,'Referencias '!B:C,2,0) -> GLOBO COMUNICACAO E PARTICIPACOES S/A | H31: =TRIM(_xlfn.TEXTBEFORE(_xlfn.TEXTAFTER(U31,"CNPJ/CPF:</strong>"),"</p>")) -> 27.865.757/0069-92 | I31: Sem solicitação encerrar | L31: FINALIZADO | M31: Médio | N31: 1018 Financeiro | Desejo falar com o setor financeiro | Fernanda Santana Camarneira | fernanda.scamarneira@cielo.com.br | O31: 46029 | P31: 46044 | Q31: =TEXT(O31,"mmm/aaaa") -> jan/2026 | R31: Larissa QUIRINO CANUTO | S31: fernanda.scamarneira@cielo.com.br | T31: GLOBO | U31: Olá, segue formulário enviado para Cielo E-commerce:<p><strong>Endereço de e-mail:</strong> fernanda.scamarneira@cielo.com.br</p><p><strong>Qual seu nome?:</strong> Fernanda Santana Camarneira</p><p><strong>CNPJ/CPF:</strong> 27.865.757/0069-92</p><p><strong>Telefone:</strong> (11) 94519-4834</p><p><strong>Assunto:</strong> Contrato Globo: Ajustes e Cancelamento de nota</p><p><strong>Merchant ID/Estabelecimento Comercial (EC):</strong> 27.865.757/0069-92</p><p><strong>Sobre qual produto ou área deseja falar?:</strong> Financeiro</p><p><strong>Como podemos te ajudar?:</strong> Desejo falar com o setor financeiro</p><p><strong>Descrição do problema:</strong> Assinamos o contrato de renovação da globo, o CNPJ que eles utilizam com a gente é o CNPJ 27.865.757/0069-92. No contrato menciona o CNPJ 27.865.757/0001-02 e suas filiais, por esse motivo o contrato contempla as filiais também. As condições comerciais que precisam ser ajustadas é apenas do CNPJ 27.865.757/0069-92 da Globoplay. | V31: =IFERROR(_xlfn.TEXTBEFORE(_xlfn.TEXTAFTER(U31,"Descrição do problema:</strong"),"</p>"),_xlfn.TEXTAFTER(U31,"Descrição do problema:</strong")) -> > Assinamos o contrato de renovação da globo, o CNPJ que eles utilizam com a gente é o CNPJ 27.865.757/0069-92. No contrato menciona o CNPJ 27.865.757/0001-02 e suas filiais, por esse motivo o contrato contempla as filiais também. As condições comerciais que precisam ser ajustadas é apenas do CNPJ 27.865.757/0069-92 da Globoplay. | W31: =_xlfn.CONCAT(D31:E31) -> 184388550 | X31: 46242 | Y31: =IF(X31="","Aberto","Encerrado") -> Encerrado | Z31: =IF(OR(L31="PENDENTE",L31="EM ANDAMENTO",L31="PENDENTE APROVAÇÃO CANCELAMENTO NF"),TODAY()-O31,X31-O31) -> 213 | AA31: =IF(Y31="Aberto",Z31+ROW()/100000,"") | AB31: =IF(ISNUMBER(FIND("@cielo.com.br",S31)),"Interno","Externo") -> Interno
B32: Emilly Maria | C32: =VLOOKUP(I:I,'Referencias '!H:I,2,0) -> Atendimento Administrativo e Suporte | D32: 18470317 | E32: 0 | F32: 2600815050333 | G32: =VLOOKUP(H:H,'Referencias '!B:C,2,0) -> KALUNGA SA | H32: =TRIM(_xlfn.TEXTBEFORE(_xlfn.TEXTAFTER(U32,"CNPJ/CPF:</strong>"),"</p>")) -> 43.283.811/0001-50 | I32: Sem solicitação encerrar | L32: FINALIZADO | M32: Médio | N32: 1018 Financeiro | Desejo falar com o setor financeiro | KALUNGA SA | ariane.pasilva@cielo.com.br | O32: 46030 | P32: 46094 | Q32: =TEXT(O32,"mmm/aaaa") -> jan/2026 | R32: Vanessa dos Santos Araujo | S32: ariane.pasilva@cielo.com.br | T32: KALUNGACOM | U32: Olá, segue formulário enviado para Cielo E-commerce:<p><strong>Qual seu nome?:</strong> KALUNGA SA</p><p><strong>Endereço de e-mail:</strong> ariane.pasilva@cielo.com.br</p><p><strong>CNPJ/CPF:</strong> 43.283.811/0001-50</p><p><strong>Telefone:</strong> (11) 97707-1602</p><p><strong>Assunto:</strong> Cancelar NF</p><p><strong>Merchant ID/Estabelecimento Comercial (EC):</strong> 43283811000150</p><p><strong>Descrição do problema:</strong> Por favor, transferir esse chamado para o financeiro N2. Prezados, boa tarde. Preciso que a NF 103288, seja cancelada. Motivo:Tivemos um impacto na implantação devido ao freezing da Black Friday - tanto pela Braspag quanto pela ClearSale - o que impossibilitou a finalização do processo nesse período. Diferentemente de outras integrações, realizamos a migração do MID Kalunga da ClearSale diretamente para a Braspag. Diante disso, acredito que a ClearSale tenha iniciado as cobranças somente após a efetiva migração, que ocorreu no dia 03/12: DAS SUPEX c | V32: =IFERROR(_xlfn.TEXTBEFORE(_xlfn.TEXTAFTER(U32,"Descrição do problema:</strong"),"</p>"),_xlfn.TEXTAFTER(U32,"Descrição do problema:</strong")) -> > Por favor, transferir esse chamado para o financeiro N2. Prezados, boa tarde. Preciso que a NF 103288, seja cancelada. Motivo:Tivemos um impacto na implantação devido ao freezing da Black Friday - tanto pela Braspag quanto pela ClearSale - o que impossibilitou a finalização do processo nesse período. Diferentemente de outras integrações, realizamos a migração do MID Kalunga da ClearSale diretamente para a Braspag. Diante disso, acredito que a ClearSale tenha iniciado as cobranças somente após a efetiva migração, que ocorreu no dia 03/12: DAS SUPEX c | W32: =_xlfn.CONCAT(D32:E32) -> 184703170 | X32: 46240 | Y32: =IF(X32="","Aberto","Encerrado") -> Encerrado | Z32: =IF(OR(L32="PENDENTE",L32="EM ANDAMENTO",L32="PENDENTE APROVAÇÃO CANCELAMENTO NF"),TODAY()-O32,X32-O32) -> 210 | AA32: =IF(Y32="Aberto",Z32+ROW()/100000,"") | AB32: =IF(ISNUMBER(FIND("@cielo.com.br",S32)),"Interno","Externo") -> Interno
B33: Emilly Maria | C33: =VLOOKUP(I:I,'Referencias '!H:I,2,0) -> Atendimento Administrativo e Suporte | D33: 18507331 | E33: 0 | F33: 2600916075566 | G33: =VLOOKUP(H:H,'Referencias '!B:C,2,0) -> COVABRA SUPERMERCADOS LTDA | H33: =TRIM(_xlfn.TEXTBEFORE(_xlfn.TEXTAFTER(U33,"CNPJ/CPF:</strong>"),"</p>")) -> 61.233.151/0005-08 | I33: Outros | L33: FINALIZADO | M33: Médio | N33: 1018 Financeiro | Desejo falar com o setor financeiro | Caroline Mendes | carolineal@cielo.com.br | O33: 46031 | P33: 46035 | Q33: =TEXT(O33,"mmm/aaaa") -> jan/2026 | R33: Larissa QUIRINO CANUTO | S33: carolineal@cielo.com.br | T33: COVABRA SUPERMERCADOS LTDA | U33: Olá, segue formulário enviado para Cielo E-commerce:<p><strong>Qual seu nome?:</strong> Caroline Mendes</p><p><strong>Endereço de e-mail:</strong> carolineal@cielo.com.br</p><p><strong>CNPJ/CPF:</strong> 61.233.151/0005-08</p><p><strong>Telefone:</strong> (11) 94503-1458</p><p><strong>Assunto:</strong> Taxas divergente + Cobrança Incorreta</p><p><strong>Merchant ID/Estabelecimento Comercial (EC):</strong> 61.233.151/0005-08</p><p><strong>Descrição do problema:</strong> Oi pessoal, tudo bem? Preciso de uma ajuda, o cliente Covabra me questionou o porque a cobrança deles está sendo de 91,39 no produto velocity, sendo que no contrato assinado em 2025 o valor era de 85,00. Além disso, observei que que o formato da cobrança está desajustado. Quando as transações ultrapassam o mínimo, o valor cobrado passa a ser calculado pelos centavos multiplicados pelo custo. No mês de dezembro, vocês tiveram 3.245 transações no Velocity, acima do mínimo de 500. Ou seja, o custo por transação seria de | V33: =IFERROR(_xlfn.TEXTBEFORE(_xlfn.TEXTAFTER(U33,"Descrição do problema:</strong"),"</p>"),_xlfn.TEXTAFTER(U33,"Descrição do problema:</strong")) -> > Oi pessoal, tudo bem? Preciso de uma ajuda, o cliente Covabra me questionou o porque a cobrança deles está sendo de 91,39 no produto velocity, sendo que no contrato assinado em 2025 o valor era de 85,00. Além disso, observei que que o formato da cobrança está desajustado. Quando as transações ultrapassam o mínimo, o valor cobrado passa a ser calculado pelos centavos multiplicados pelo custo. No mês de dezembro, vocês tiveram 3.245 transações no Velocity, acima do mínimo de 500. Ou seja, o custo por transação seria de | W33: =_xlfn.CONCAT(D33:E33) -> 185073310 | X33: 46240 | Y33: =IF(X33="","Aberto","Encerrado") -> Encerrado | Z33: =IF(OR(L33="PENDENTE",L33="EM ANDAMENTO",L33="PENDENTE APROVAÇÃO CANCELAMENTO NF"),TODAY()-O33,X33-O33) -> 209 | AA33: =IF(Y33="Aberto",Z33+ROW()/100000,"") | AB33: =IF(ISNUMBER(FIND("@cielo.com.br",S33)),"Interno","Externo") -> Interno
B34: Stephany Lima | C34: =VLOOKUP(I:I,'Referencias '!H:I,2,0) -> Cancelamento e Reemissão de Nota Fiscal | D34: 18493953 | E34: 0 | F34: 2600911066390 | G34: =T34 -> BLOMME LTDA | H34: =TRIM(_xlfn.TEXTBEFORE(_xlfn.TEXTAFTER(U34,"CNPJ/CPF:</strong>"),"</p>")) -> 50.998.581/0001-70 | I34: Cancelamento de NF | K34: Comercial | L34: FINALIZADO | M34: Médio | N34: 1018 Financeiro | Desejo falar com o setor financeiro | BLOMME LTDA | ariane.pasilva@cielo.com.br | O34: 46031 | P34: 46031 | Q34: =TEXT(O34,"mmm/aaaa") -> jan/2026 | R34: STEPHANY LIMA DE LISBOA | S34: ariane.pasilva@cielo.com.br | T34: BLOMME LTDA | U34: Olá, segue formulário enviado para Cielo E-commerce:<p><strong>Qual seu nome?:</strong> BLOMME LTDA</p><p><strong>Endereço de e-mail:</strong> ariane.pasilva@cielo.com.br</p><p><strong>CNPJ/CPF:</strong> 50.998.581/0001-70</p><p><strong>Telefone:</strong> (11) 97707-1602</p><p><strong>Assunto:</strong> Cancelar NFS</p><p><strong>Merchant ID/Estabelecimento Comercial (EC):</strong> 50.998.581/0001-70</p><p><strong>Descrição do problema:</strong> Transferir esse chamado para o financeiro N2, time Everton.</p><p><strong>ID da transação:</strong> </p><p><strong>Código do erro:</strong> </p><p><strong>Sobre qual produto ou área deseja falar?:</strong> Financeiro</p><p><strong>Como podemos te ajudar?:</strong> Desejo falar com o setor financeiro</p><p><strong>GA Client ID:</strong> 1401063149.1757524286</p><p><strong>Lead Hash ID:</strong> 2a07344672c93c9ca782cc07cf9dc37d0cd4c270e817a83b9f87f9b32f0130a9</p><p><strong>Lead Form ID:</strong> 2a07344672c93c9ca782cc07cf9dc37d0cd4c270e817a83b9f87 | V34: =IFERROR(_xlfn.TEXTBEFORE(_xlfn.TEXTAFTER(U34,"Descrição do problema:</strong"),"</p>"),_xlfn.TEXTAFTER(U34,"Descrição do problema:</strong")) -> > Transferir esse chamado para o financeiro N2, time Everton. | W34: =_xlfn.CONCAT(D34:E34) -> 184939530 | X34: =P34 -> 46031 | Y34: =IF(X34="","Aberto","Encerrado") -> Encerrado | Z34: =IF(OR(L34="PENDENTE",L34="EM ANDAMENTO",L34="PENDENTE APROVAÇÃO CANCELAMENTO NF"),TODAY()-O34,X34-O34) -> 0 | AA34: =IF(Y34="Aberto",Z34+ROW()/100000,"") | AB34: =IF(ISNUMBER(FIND("@cielo.com.br",S34)),"Interno","Externo") -> Interno
B35: Stephany Lima | C35: =VLOOKUP(I:I,'Referencias '!H:I,2,0) -> Cobrança e Contestação | D35: 18597237 | E35: 0 | F35: 2601317140800 | G35: =VLOOKUP(H:H,'Referencias '!B:C,2,0) -> SAVEGNAGO-SUPERMERCADOS LTDA | H35: =TRIM(_xlfn.TEXTBEFORE(_xlfn.TEXTAFTER(U35,"CNPJ/CPF:</strong>"),"</p>")) -> 71.322.150/0001-60 | I35: Contestação de cobrança | L35: FINALIZADO | M35: Médio | N35: 1018 Financeiro | Desejo falar com o setor financeiro | Lenon Oliveira | lenon.oliveira@savegnago.com.br | O35: 46035 | P35: 46059 | Q35: =TEXT(O35,"mmm/aaaa") -> jan/2026 | R35: Larissa QUIRINO CANUTO | S35: lenon.oliveira@savegnago.com.br | T35: SAVEGNAGO Lj 1 Matriz Sertaozinho | U35: Olá, segue formulário enviado para Cielo E-commerce:<p><strong>Qual seu nome?:</strong> Lenon Oliveira</p><p><strong>Endereço de e-mail:</strong> lenon.oliveira@savegnago.com.br</p><p><strong>CNPJ/CPF:</strong> 71.322.150/0001-60</p><p><strong>Telefone:</strong> (16) 99720-1151</p><p><strong>Assunto:</strong> NF INDEVIDA</p><p><strong>Merchant ID/Estabelecimento Comercial (EC):</strong> 71.322.150/0001-60</p><p><strong>Descrição do problema:</strong> Boa tarde! Pessoal encontrei uma divergência quanto a uma nota fiscal do Antifraude, NF 80105 Trata-se de uma nota de 2024, quando ainda não existia nenhum contrato com Antifraude, Preciso de um documento indicando que tal cobrança é indevida, pois está lançada no meu sistema.</p><p><strong>ID da transação:</strong> </p><p><strong>Código do erro:</strong> </p><p><strong>Sobre qual produto ou área deseja falar?:</strong> Financeiro</p><p><strong>Como podemos te ajudar?:</strong> Desejo falar com o setor financeiro</p><p><strong>GA Clien | V35: =IFERROR(_xlfn.TEXTBEFORE(_xlfn.TEXTAFTER(U35,"Descrição do problema:</strong"),"</p>"),_xlfn.TEXTAFTER(U35,"Descrição do problema:</strong")) -> > Boa tarde! Pessoal encontrei uma divergência quanto a uma nota fiscal do Antifraude, NF 80105 Trata-se de uma nota de 2024, quando ainda não existia nenhum contrato com Antifraude, Preciso de um documento indicando que tal cobrança é indevida, pois está lançada no meu sistema. | W35: =_xlfn.CONCAT(D35:E35) -> 185972370 | X35: 46239 | Y35: =IF(X35="","Aberto","Encerrado") -> Encerrado | Z35: =IF(OR(L35="PENDENTE",L35="EM ANDAMENTO",L35="PENDENTE APROVAÇÃO CANCELAMENTO NF"),TODAY()-O35,X35-O35) -> 204 | AA35: =IF(Y35="Aberto",Z35+ROW()/100000,"") | AB35: =IF(ISNUMBER(FIND("@cielo.com.br",S35)),"Interno","Externo") -> Externo
B36: Stephany Lima | C36: =VLOOKUP(I:I,'Referencias '!H:I,2,0) -> Contratos, Comercial e Cadastro | D36: 18623547 | E36: 0 | F36: 2601414159330 | G36: =VLOOKUP(H:H,'Referencias '!B:C,2,0) -> ESCOLAWEB LTDA | H36: =TRIM(_xlfn.TEXTBEFORE(_xlfn.TEXTAFTER(U36,"CNPJ/CPF:</strong>"),"</p>")) -> 11.615.383/0001-29 | I36: Congelamento de contrato | L36: FINALIZADO | M36: Médio | N36: 1018 Financeiro | Desejo falar com o setor financeiro | Isabella | isabella.lestingi@cielo.com.br | O36: 46036 | P36: 46042 | Q36: =TEXT(O36,"mmm/aaaa") -> jan/2026 | R36: STEPHANY LIMA DE LISBOA | S36: isabella.lestingi@cielo.com.br | T36: ESCOLAWEB | U36: Olá, segue formulário enviado para Cielo E-commerce:<p><strong>Qual seu nome?:</strong> Isabella</p><p><strong>Endereço de e-mail:</strong> isabella.lestingi@cielo.com.br</p><p><strong>CNPJ/CPF:</strong> 11.615.383/0001-29</p><p><strong>Telefone:</strong> (11) 99516-9999</p><p><strong>Assunto:</strong> CONGELAMENTO CONTRATO GATEWAY</p><p><strong>Merchant ID/Estabelecimento Comercial (EC):</strong> 11.615.383/0001-29</p><p><strong>Descrição do problema:</strong> Caros, peço a gentileza de congelar o contrato de GATEWAY da cliente escola web (11.615.383/0001-29) até o dia 1 de abril de 2026, conforme contrato de congelamento. Ja estou solicitando o DA para cancelamento das notas emitidas em dezembro e janeiro.</p><p><strong>ID da transação:</strong> </p><p><strong>Código do erro:</strong> </p><p><strong>Sobre qual produto ou área deseja falar?:</strong> Financeiro</p><p><strong>Como podemos te ajudar?:</strong> Desejo falar com o setor financeiro</p><p><strong>GA Client ID:</strong> 5 | V36: =IFERROR(_xlfn.TEXTBEFORE(_xlfn.TEXTAFTER(U36,"Descrição do problema:</strong"),"</p>"),_xlfn.TEXTAFTER(U36,"Descrição do problema:</strong")) -> > Caros, peço a gentileza de congelar o contrato de GATEWAY da cliente escola web (11.615.383/0001-29) até o dia 1 de abril de 2026, conforme contrato de congelamento. Ja estou solicitando o DA para cancelamento das notas emitidas em dezembro e janeiro. | W36: =_xlfn.CONCAT(D36:E36) -> 186235470 | X36: 46234 | Y36: =IF(X36="","Aberto","Encerrado") -> Encerrado | Z36: =IF(OR(L36="PENDENTE",L36="EM ANDAMENTO",L36="PENDENTE APROVAÇÃO CANCELAMENTO NF"),TODAY()-O36,X36-O36) -> 198 | AA36: =IF(Y36="Aberto",Z36+ROW()/100000,"") | AB36: =IF(ISNUMBER(FIND("@cielo.com.br",S36)),"Interno","Externo") -> Interno
B37: Stephany Lima | C37: =VLOOKUP(I:I,'Referencias '!H:I,2,0) -> Cancelamento e Reemissão de Nota Fiscal | D37: 18604102 | E37: 0 | F37: 2601409145692 | G37: =VLOOKUP(H:H,'Referencias '!B:C,2,0) -> GUEDES & PAIXAO LTDA | H37: =TRIM(_xlfn.TEXTBEFORE(_xlfn.TEXTAFTER(U37,"CNPJ/CPF:</strong>"),"</p>")) -> 16.928.871/0036-30 | I37: Cancelamento de Nota Fiscal | J37: Aguardando DA | L37: FINALIZADO | M37: Alta | N37: 1018 Financeiro | Desejo falar com o setor financeiro | Raphael Palmeira | raphael.palmeira@cielo.com.br | O37: 46036 | P37: 46162 | Q37: =TEXT(O37,"mmm/aaaa") -> jan/2026 | R37: STEPHANY LIMA DE LISBOA | S37: raphael.palmeira@cielo.com.br | T37: DROGARIA MINAS BRASIL | U37: Olá, segue formulário enviado para Cielo E-commerce:<p><strong>Qual seu nome?:</strong> Raphael Palmeira</p><p><strong>Endereço de e-mail:</strong> raphael.palmeira@cielo.com.br</p><p><strong>CNPJ/CPF:</strong> 16.928.871/0036-30</p><p><strong>Telefone:</strong> (11) 98774-0847</p><p><strong>Assunto:</strong> financeiro</p><p><strong>Merchant ID/Estabelecimento Comercial (EC):</strong> DROGARIA MINAS BRASIL</p><p><strong>Descrição do problema:</strong> Bom dia time! Temos o de acordo do supex Pelizon para o cancelamento parcial das NFs do cliente Drogaria Minas Brasil. Serão canceladas: 9 notas do gateway, de março a novembro. 4 notas do antifraude avançado de agosto a novembro. No anexo está o de acordo com todos os email trocados. Fico a disposição.</p><p><strong>ID da transação:</strong> </p><p><strong>Código do erro:</strong> </p><p><strong>Sobre qual produto ou área deseja falar?:</strong> Financeiro</p><p><strong>Como podemos te ajudar?:</strong> Desejo falar com o setor f | V37: =IFERROR(_xlfn.TEXTBEFORE(_xlfn.TEXTAFTER(U37,"Descrição do problema:</strong"),"</p>"),_xlfn.TEXTAFTER(U37,"Descrição do problema:</strong")) -> > Bom dia time! Temos o de acordo do supex Pelizon para o cancelamento parcial das NFs do cliente Drogaria Minas Brasil. Serão canceladas: 9 notas do gateway, de março a novembro. 4 notas do antifraude avançado de agosto a novembro. No anexo está o de acordo com todos os email trocados. Fico a disposição. | W37: =_xlfn.CONCAT(D37:E37) -> 186041020 | X37: 46287 | Y37: =IF(X37="","Aberto","Encerrado") -> Encerrado | Z37: =IF(OR(L37="PENDENTE",L37="EM ANDAMENTO",L37="PENDENTE APROVAÇÃO CANCELAMENTO NF"),TODAY()-O37,X37-O37) -> 251 | AA37: =IF(Y37="Aberto",Z37+ROW()/100000,"") | AB37: =IF(ISNUMBER(FIND("@cielo.com.br",S37)),"Interno","Externo") -> Interno
B38: Pamela de Sá | C38: =VLOOKUP(I:I,'Referencias '!H:I,2,0) -> Contratos, Comercial e Cadastro | D38: 18762416 | E38: 0 | F38: 2601918257712 | G38: =VLOOKUP(H:H,'Referencias '!B:C,2,0) -> ZAPPING DO BRASIL LTDA | H38: =TRIM(_xlfn.TEXTBEFORE(_xlfn.TEXTAFTER(U38,"CNPJ/CPF:</strong>"),"</p>")) -> 34.308.177/0001-71 | I38: Pendente Retorno Comercial | L38: FINALIZADO | M38: Médio | N38: 1018 Financeiro | Desejo falar com o setor financeiro | Clarissa Rissi | clarissa.rissi@cielo.com.br | O38: 46041 | P38: 46062 | Q38: =TEXT(O38,"mmm/aaaa") -> jan/2026 | R38: Larissa QUIRINO CANUTO | S38: clarissa.rissi@cielo.com.br | T38: ZAPPING | U38: Olá, segue formulário enviado para Cielo E-commerce:<p><strong>Qual seu nome?:</strong> Clarissa Rissi</p><p><strong>Endereço de e-mail:</strong> clarissa.rissi@cielo.com.br</p><p><strong>CNPJ/CPF:</strong> 34.308.177/0001-71</p><p><strong>Telefone:</strong> (11) 97261-4151</p><p><strong>Assunto:</strong> Renegociação de Taxas</p><p><strong>Merchant ID/Estabelecimento Comercial (EC):</strong> 34.308.177/0001-71</p><p><strong>Descrição do problema:</strong> Prezados, boa tarde, tudo bem? Fizemos a renegociação dos valores de antifraude do clientes, assim como a adição do emailage, crio esse chamado para reforçar as novas condições no termo em anexo, pois precisamos que elas reflitam no billing. Obrigada.</p><p><strong>ID da transação:</strong> </p><p><strong>Código do erro:</strong> </p><p><strong>Sobre qual produto ou área deseja falar?:</strong> Financeiro</p><p><strong>Como podemos te ajudar?:</strong> Desejo falar com o setor financeiro</p><p><strong>GA Client ID:</strong> 4774163 | V38: =IFERROR(_xlfn.TEXTBEFORE(_xlfn.TEXTAFTER(U38,"Descrição do problema:</strong"),"</p>"),_xlfn.TEXTAFTER(U38,"Descrição do problema:</strong")) -> > Prezados, boa tarde, tudo bem? Fizemos a renegociação dos valores de antifraude do clientes, assim como a adição do emailage, crio esse chamado para reforçar as novas condições no termo em anexo, pois precisamos que elas reflitam no billing. Obrigada. | W38: =_xlfn.CONCAT(D38:E38) -> 187624160 | X38: 46242 | Y38: =IF(X38="","Aberto","Encerrado") -> Encerrado | Z38: =IF(OR(L38="PENDENTE",L38="EM ANDAMENTO",L38="PENDENTE APROVAÇÃO CANCELAMENTO NF"),TODAY()-O38,X38-O38) -> 201 | AA38: =IF(Y38="Aberto",Z38+ROW()/100000,"") | AB38: =IF(ISNUMBER(FIND("@cielo.com.br",S38)),"Interno","Externo") -> Interno
B39: Emilly Maria | C39: =VLOOKUP(I:I,'Referencias '!H:I,2,0) -> Contratos, Comercial e Cadastro | D39: 18751902 | E39: 0 | F39: 2601915250536 | G39: =T39 -> EMPORIO CHAP | I39: Pendente Retorno Comercial | L39: FINALIZADO | M39: Médio | N39: 1002 Portais E-commerce | Estou com um problema em produção e preciso de ajuda | Raquel Bencini | raquel.bencini@mbrf.com | O39: 46041 | P39: 46050 | Q39: =TEXT(O39,"mmm/aaaa") -> jan/2026 | R39: ECOMMERCE BP SUPORTE FINANCEIRO N2 | S39: raquel.bencini@mbrf.com | T39: EMPORIO CHAP | U39: Olá, segue formulário enviado para Cielo E-commerce:<p><strong>Qual seu nome?:</strong> Raquel Bencini</p><p><strong>Endereço de e-mail:</strong> raquel.bencini@mbrf.com</p><p><strong>Telefone:</strong> (11) 97690-0931</p><p><strong>Assunto:</strong> EXTRAÇÃO RELATÓRIO PROTOCOLO 3DS</p><p><strong>Merchant ID/Estabelecimento Comercial (EC):</strong> 9580CDA7-A196-49EE-A018-A7C3DC2F76BB</p><p><strong>Sobre qual produto ou área deseja falar?:</strong> Portais E-commerce</p><p><strong>Descrição do problema:</strong> EXTRAÇÃO RELATÓRIO PERÍDO 26/11/2025 À 25/12/2025 PARA CONFERENCIA DE COBRANÇA</p><p><strong>Data e hora do erro:</strong> 19-01-2026 15:17</p><p><strong>Como podemos te ajudar?:</strong> Estou com um problema em produção e preciso de ajuda</p><p><strong>GA Client ID:</strong> 1915800139.1768846022</p><p><strong>Lead Hash ID:</strong> 62710623a45d6c43690eee781a516329891495e9770548d7d03e9187351fd741</p><p><strong>Lead Form ID:</strong> 62710623a45d6c43690eee781a516329891495e9770 | V39: =IFERROR(_xlfn.TEXTBEFORE(_xlfn.TEXTAFTER(U39,"Descrição do problema:</strong"),"</p>"),_xlfn.TEXTAFTER(U39,"Descrição do problema:</strong")) -> > EXTRAÇÃO RELATÓRIO PERÍDO 26/11/2025 À 25/12/2025 PARA CONFERENCIA DE COBRANÇA | W39: =_xlfn.CONCAT(D39:E39) -> 187519020 | X39: 46245 | Y39: =IF(X39="","Aberto","Encerrado") -> Encerrado | Z39: =IF(OR(L39="PENDENTE",L39="EM ANDAMENTO",L39="PENDENTE APROVAÇÃO CANCELAMENTO NF"),TODAY()-O39,X39-O39) -> 204 | AA39: =IF(Y39="Aberto",Z39+ROW()/100000,"") | AB39: =IF(ISNUMBER(FIND("@cielo.com.br",S39)),"Interno","Externo") -> Externo
B40: Emilly Maria | C40: =VLOOKUP(I:I,'Referencias '!H:I,2,0) -> Cancelamento e Reemissão de Nota Fiscal | D40: 18831004 | E40: 0 | F40: 2602114306856 | G40: =T40 -> REDE RECORD DE TELEVISAO EOU RECORD TV | H40: =TRIM(_xlfn.TEXTBEFORE(_xlfn.TEXTAFTER(U40,"CNPJ/CPF:</strong>"),"</p>")) -> 60.628.369/0001-75 | I40: Cancelamento de NF / reemissão | L40: EM ANDAMENTO | M40: Médio | N40: 1018 Financeiro | Desejo falar com o setor financeiro | vinicius ferraz | vferraz@recordtv.com.br | O40: 46043 | P40: 46044 | Q40: =TEXT(O40,"mmm/aaaa") -> jan/2026 | R40: ECOMMERCE BP SUPORTE FINANCEIRO N2 | S40: vferraz@recordtv.com.br | T40: REDE RECORD DE TELEVISAO EOU RECORD TV | U40: Olá, segue formulário enviado para Cielo E-commerce:<p><strong>Qual seu nome?:</strong> vinicius ferraz</p><p><strong>Endereço de e-mail:</strong> vferraz@recordtv.com.br</p><p><strong>CNPJ/CPF:</strong> 60.628.369/0001-75</p><p><strong>Telefone:</strong> (11) 3300-3602</p><p><strong>Assunto:</strong> Correção de Nf com valor diferente do contrato</p><p><strong>Merchant ID/Estabelecimento Comercial (EC):</strong> débito</p><p><strong>Sobre qual produto ou área deseja falar?:</strong> Financeiro</p><p><strong>Como podemos te ajudar?:</strong> Desejo falar com o setor financeiro</p><p><strong>Descrição do problema:</strong> Boa tarde! Caros por favor, as NF’s 103973 e 103863 estão com as tarifas incorretas segundo o contrato, por isso solicito o recalculo, cancelamento das nf’s e re-emissão no valor correto. 103973 Tarifa contrato R$ 0,0100 Tarifa NF R$ 0,1044 103863 Tarifa contrato R$ 1.750,00 Tarifa NF R$ 1.827,18 Fico no aguardo</p><p><strong>Data e hor | V40: =IFERROR(_xlfn.TEXTBEFORE(_xlfn.TEXTAFTER(U40,"Descrição do problema:</strong"),"</p>"),_xlfn.TEXTAFTER(U40,"Descrição do problema:</strong")) -> > Boa tarde! Caros por favor, as NF’s 103973 e 103863 estão com as tarifas incorretas segundo o contrato, por isso solicito o recalculo, cancelamento das nf’s e re-emissão no valor correto. 103973 Tarifa contrato R$ 0,0100 Tarifa NF R$ 0,1044 103863 Tarifa contrato R$ 1.750,00 Tarifa NF R$ 1.827,18 Fico no aguardo | W40: =_xlfn.CONCAT(D40:E40) -> 188310040 | Y40: =IF(X40="","Aberto","Encerrado") -> Aberto | Z40: =IF(OR(L40="PENDENTE",L40="EM ANDAMENTO",L40="PENDENTE APROVAÇÃO CANCELAMENTO NF"),TODAY()-O40,X40-O40) -> 247 | AA40: =IF(Y40="Aberto",Z40+ROW()/100000,"") -> 247.0004 | AB40: =IF(ISNUMBER(FIND("@cielo.com.br",S40)),"Interno","Externo") -> Externo
B41: Stephany Lima | C41: =VLOOKUP(I:I,'Referencias '!H:I,2,0) -> Cancelamento e Reemissão de Nota Fiscal | D41: 18823102 | E41: 0 | F41: 2602112300919 | G41: =VLOOKUP(H:H,'Referencias '!B:C,2,0) -> COMERCIAL E IMPORTADORA DE PNEUS LTDA | H41: =TRIM(_xlfn.TEXTBEFORE(_xlfn.TEXTAFTER(U41,"CNPJ/CPF:</strong>"),"</p>")) -> 61.234.985/0001-04 | I41: Cancelamento de NF | L41: FINALIZADO | M41: Médio | N41: 1018 Financeiro | Desejo falar com o setor financeiro | COMERCIAL E IMPORTADORA DE PNEUS LTDA | ariane.pasilva@cielo.com.br | O41: 46043 | P41: 46073 | Q41: =TEXT(O41,"mmm/aaaa") -> jan/2026 | R41: STEPHANY LIMA DE LISBOA | S41: ariane.pasilva@cielo.com.br | U41: Olá, segue formulário enviado para Cielo E-commerce:<p><strong>Qual seu nome?:</strong> COMERCIAL E IMPORTADORA DE PNEUS LTDA</p><p><strong>Endereço de e-mail:</strong> ariane.pasilva@cielo.com.br</p><p><strong>CNPJ/CPF:</strong> 61.234.985/0001-04</p><p><strong>Telefone:</strong> (11) 97707-1602</p><p><strong>Assunto:</strong> Emissão de NF</p><p><strong>Merchant ID/Estabelecimento Comercial (EC):</strong> 61.234.985/0001-04</p><p><strong>Descrição do problema:</strong> Pessoal, em anexo segue pedido do cliente para emissão da NF. ''Seguem os pedidos em anexo para a emissão da NF''</p><p><strong>ID da transação:</strong> </p><p><strong>Código do erro:</strong> </p><p><strong>Sobre qual produto ou área deseja falar?:</strong> Financeiro</p><p><strong>Como podemos te ajudar?:</strong> Desejo falar com o setor financeiro</p><p><strong>GA Client ID:</strong> 1401063149.1757524286</p><p><strong>Lead Hash ID:</strong> 2a07344672c93c9ca782cc07cf9dc37d0cd4c270e817a83b9f87f9b32f0130a9</p><p>< | V41: =IFERROR(_xlfn.TEXTBEFORE(_xlfn.TEXTAFTER(U41,"Descrição do problema:</strong"),"</p>"),_xlfn.TEXTAFTER(U41,"Descrição do problema:</strong")) -> > Pessoal, em anexo segue pedido do cliente para emissão da NF. ''Seguem os pedidos em anexo para a emissão da NF'' | W41: =_xlfn.CONCAT(D41:E41) -> 188231020 | X41: 46267 | Y41: =IF(X41="","Aberto","Encerrado") -> Encerrado | Z41: =IF(OR(L41="PENDENTE",L41="EM ANDAMENTO",L41="PENDENTE APROVAÇÃO CANCELAMENTO NF"),TODAY()-O41,X41-O41) -> 224 | AA41: =IF(Y41="Aberto",Z41+ROW()/100000,"") | AB41: =IF(ISNUMBER(FIND("@cielo.com.br",S41)),"Interno","Externo") -> Interno
B42: Emilly Maria | C42: =VLOOKUP(I:I,'Referencias '!H:I,2,0) -> Cancelamento e Reemissão de Nota Fiscal | D42: 18822614 | E42: 0 | F42: 2602112300585 | G42: =T42 | H42: =TRIM(_xlfn.TEXTBEFORE(_xlfn.TEXTAFTER(U42,"CNPJ/CPF:</strong>"),"</p>")) -> 22.675.768/0001-06 | I42: Cancelamento de NF / reemissão | L42: FINALIZADO | M42: Médio | N42: 1018 Financeiro | Desejo falar com o setor financeiro | GSE COMERCIO DE ROUPAS LTDA | ariane.pasilva@cielo.com.br | O42: 46043 | P42: 46043 | Q42: =TEXT(O42,"mmm/aaaa") -> jan/2026 | R42: ECOMMERCE BP SUPORTE FINANCEIRO N2 | S42: ariane.pasilva@cielo.com.br | U42: Olá, segue formulário enviado para Cielo E-commerce:<p><strong>Qual seu nome?:</strong> GSE COMERCIO DE ROUPAS LTDA</p><p><strong>Endereço de e-mail:</strong> ariane.pasilva@cielo.com.br</p><p><strong>CNPJ/CPF:</strong> 22.675.768/0001-06</p><p><strong>Telefone:</strong> (11) 97707-1602</p><p><strong>Assunto:</strong> Cancelamento de NF</p><p><strong>Merchant ID/Estabelecimento Comercial (EC):</strong> 22.675.768/0001-06</p><p><strong>Descrição do problema:</strong> Por favor, cancelar todas as NFS desse cliente. Já temos os DAS da comercial</p><p><strong>ID da transação:</strong> </p><p><strong>Código do erro:</strong> </p><p><strong>Sobre qual produto ou área deseja falar?:</strong> Financeiro</p><p><strong>Como podemos te ajudar?:</strong> Desejo falar com o setor financeiro</p><p><strong>GA Client ID:</strong> 1401063149.1757524286</p><p><strong>Lead Hash ID:</strong> 2a07344672c93c9ca782cc07cf9dc37d0cd4c270e817a83b9f87f9b32f0130a9</p><p><strong>Lead Form ID:</strong> 2a07344672c93 | V42: =IFERROR(_xlfn.TEXTBEFORE(_xlfn.TEXTAFTER(U42,"Descrição do problema:</strong"),"</p>"),_xlfn.TEXTAFTER(U42,"Descrição do problema:</strong")) -> > Por favor, cancelar todas as NFS desse cliente. Já temos os DAS da comercial | W42: =_xlfn.CONCAT(D42:E42) -> 188226140 | X42: 46245 | Y42: =IF(X42="","Aberto","Encerrado") -> Encerrado | Z42: =IF(OR(L42="PENDENTE",L42="EM ANDAMENTO",L42="PENDENTE APROVAÇÃO CANCELAMENTO NF"),TODAY()-O42,X42-O42) -> 202 | AA42: =IF(Y42="Aberto",Z42+ROW()/100000,"") | AB42: =IF(ISNUMBER(FIND("@cielo.com.br",S42)),"Interno","Externo") -> Interno
B43: Pamela de Sá | C43: =VLOOKUP(I:I,'Referencias '!H:I,2,0) -> Atendimento Administrativo e Suporte | D43: 18890788 | E43: 0 | F43: 2602222348735 | G43: =T43 | I43: Sem solicitação encerrar | L43: FINALIZADO | M43: Médio | N43: 1018 Financeiro | Desejo falar com o setor financeiro | Daiani | daiani.sopran@herval.com.br | O43: 46044 | P43: 46114 | Q43: =TEXT(O43,"mmm/aaaa") -> jan/2026 | R43: Larissa QUIRINO CANUTO | S43: daiani.sopran@herval.com.br | U43: Olá, segue formulário enviado para Cielo E-commerce:<p><strong>Qual seu nome?:</strong> Daiani</p><p><strong>Endereço de e-mail:</strong> daiani.sopran@herval.com.br</p><p><strong>Telefone:</strong> (51) 3564-8300</p><p><strong>Assunto:</strong> Fatura</p><p><strong>Sobre qual produto ou área deseja falar?:</strong> Financeiro</p><p><strong>Como podemos te ajudar?:</strong> Desejo falar com o setor financeiro</p><p><strong>Descrição do problema:</strong> Boa tarde! Pode verificar se foi emitida a fatura referente ao antifraude agora em Janeiro? Geralmente recebo ela até o dia 15de cada mês, porém ainda não recebi, se não receber ela até amanhã 23/01 de manhã preciso que seja emitida apenas dia 02/02 pois o nosso período fiscal fecha sexta 23/01.</p><p><strong>Merchant ID/Estabelecimento Comercial (EC):</strong> BA3363F9-C5A7-41B5-95A8-1DA5075C9244</p><p><strong>GA Client ID:</strong> 759501410.1767871799</p><p><strong>Lead Hash ID:</strong> 0a29a074e6016919eab459b6ebc2d5e3cb21d33883 | V43: =IFERROR(_xlfn.TEXTBEFORE(_xlfn.TEXTAFTER(U43,"Descrição do problema:</strong"),"</p>"),_xlfn.TEXTAFTER(U43,"Descrição do problema:</strong")) -> > Boa tarde! Pode verificar se foi emitida a fatura referente ao antifraude agora em Janeiro? Geralmente recebo ela até o dia 15de cada mês, porém ainda não recebi, se não receber ela até amanhã 23/01 de manhã preciso que seja emitida apenas dia 02/02 pois o nosso período fiscal fecha sexta 23/01. | W43: =_xlfn.CONCAT(D43:E43) -> 188907880 | X43: 46242 | Y43: =IF(X43="","Aberto","Encerrado") -> Encerrado | Z43: =IF(OR(L43="PENDENTE",L43="EM ANDAMENTO",L43="PENDENTE APROVAÇÃO CANCELAMENTO NF"),TODAY()-O43,X43-O43) -> 198 | AA43: =IF(Y43="Aberto",Z43+ROW()/100000,"") | AB43: =IF(ISNUMBER(FIND("@cielo.com.br",S43)),"Interno","Externo") -> Externo
B44: Stephany Lima | C44: =VLOOKUP(I:I,'Referencias '!H:I,2,0) -> Cancelamento e Reemissão de Nota Fiscal | D44: 18863113 | E44: 0 | F44: 2602211329882 | G44: =VLOOKUP(H:H,'Referencias '!B:C,2,0) -> NEWLAND VEICULOS LTDA | H44: =TRIM(_xlfn.TEXTBEFORE(_xlfn.TEXTAFTER(U44,"CNPJ/CPF:</strong>"),"</p>")) -> 41.597.303/0001-10 | I44: Cancelamento de NF | L44: FINALIZADO | M44: Médio | N44: 1018 Financeiro | Desejo falar com o setor financeiro | Emiliana Lima | emiliana.lima@newland.com.br | O44: 46044 | P44: 46107 | Q44: =TEXT(O44,"mmm/aaaa") -> jan/2026 | R44: STEPHANY LIMA DE LISBOA | S44: emiliana.lima@newland.com.br | T44: NEWLAND VEICULOS LTDA | U44: Olá, segue formulário enviado para Cielo E-commerce:<p><strong>Qual seu nome?:</strong> Emiliana Lima</p><p><strong>Endereço de e-mail:</strong> emiliana.lima@newland.com.br</p><p><strong>CNPJ/CPF:</strong> 41.597.303/0001-10</p><p><strong>Telefone:</strong> (88) 99919-4684</p><p><strong>Assunto:</strong> Pendências de pagamento</p><p><strong>Merchant ID/Estabelecimento Comercial (EC):</strong> 41.597.303/0001-10</p><p><strong>Sobre qual produto ou área deseja falar?:</strong> Financeiro</p><p><strong>Como podemos te ajudar?:</strong> Desejo falar com o setor financeiro</p><p><strong>Descrição do problema:</strong> Bom dia, Estamos com pendências de pagamento em 2 notas, toda nota de serviço é para ser emitido até dia 24 de cada mês. Poderia verificar o envio de novas notas anterior a essa data para que possamos realizar o pagamento ?</p><p><strong>GA Client ID:</strong> 1770719146.1764096498</p><p><strong>Lead Hash ID:</strong> a12acb766b07dd0418426b0c904c5aef6efcc114ee7fb5e1e74fe7c | V44: =IFERROR(_xlfn.TEXTBEFORE(_xlfn.TEXTAFTER(U44,"Descrição do problema:</strong"),"</p>"),_xlfn.TEXTAFTER(U44,"Descrição do problema:</strong")) -> > Bom dia, Estamos com pendências de pagamento em 2 notas, toda nota de serviço é para ser emitido até dia 24 de cada mês. Poderia verificar o envio de novas notas anterior a essa data para que possamos realizar o pagamento ? | W44: =_xlfn.CONCAT(D44:E44) -> 188631130 | X44: 46241 | Y44: =IF(X44="","Aberto","Encerrado") -> Encerrado | Z44: =IF(OR(L44="PENDENTE",L44="EM ANDAMENTO",L44="PENDENTE APROVAÇÃO CANCELAMENTO NF"),TODAY()-O44,X44-O44) -> 197 | AA44: =IF(Y44="Aberto",Z44+ROW()/100000,"") | AB44: =IF(ISNUMBER(FIND("@cielo.com.br",S44)),"Interno","Externo") -> Externo
B45: Stephany Lima | C45: =VLOOKUP(I:I,'Referencias '!H:I,2,0) -> Cancelamento e Reemissão de Nota Fiscal | D45: 18915650 | E45: 0 | F45: 2602314366053 | G45: =T45 | H45: =TRIM(_xlfn.TEXTBEFORE(_xlfn.TEXTAFTER(U45,"CNPJ/CPF:</strong>"),"</p>")) -> 55.213.538/0001-76 | I45: Cancelamento de NF / reemissão | L45: FINALIZADO | M45: Alta | N45: 1018 Financeiro | Desejo falar com o setor financeiro | WISHPAG LTDA | ariane.pasilva@cielo.com.br | O45: 46045 | P45: 46157 | Q45: =TEXT(O45,"mmm/aaaa") -> jan/2026 | R45: STEPHANY LIMA DE LISBOA | S45: ariane.pasilva@cielo.com.br | U45: Olá, segue formulário enviado para Cielo E-commerce:<p><strong>Qual seu nome?:</strong> WISHPAG LTDA</p><p><strong>Endereço de e-mail:</strong> ariane.pasilva@cielo.com.br</p><p><strong>CNPJ/CPF:</strong> 55.213.538/0001-76</p><p><strong>Telefone:</strong> (11) 97707-1602</p><p><strong>Assunto:</strong> cancelamento de nf</p><p><strong>Merchant ID/Estabelecimento Comercial (EC):</strong> 55213538000176</p><p><strong>Descrição do problema:</strong> Prezados, boa tarde. Tudo bem? Em anexo, segue DA para cancelaento de todas as NFS emitidas para esse cliente.</p><p><strong>ID da transação:</strong> </p><p><strong>Código do erro:</strong> </p><p><strong>Sobre qual produto ou área deseja falar?:</strong> Financeiro</p><p><strong>Como podemos te ajudar?:</strong> Desejo falar com o setor financeiro</p><p><strong>GA Client ID:</strong> 1401063149.1757524286</p><p><strong>Lead Hash ID:</strong> 2a07344672c93c9ca782cc07cf9dc37d0cd4c270e817a83b9f87f9b32f0130a9</p><p><strong>Lead Form ID:</stron | V45: =IFERROR(_xlfn.TEXTBEFORE(_xlfn.TEXTAFTER(U45,"Descrição do problema:</strong"),"</p>"),_xlfn.TEXTAFTER(U45,"Descrição do problema:</strong")) -> > Prezados, boa tarde. Tudo bem? Em anexo, segue DA para cancelaento de todas as NFS emitidas para esse cliente. | W45: =_xlfn.CONCAT(D45:E45) -> 189156500 | X45: 46254 | Y45: =IF(X45="","Aberto","Encerrado") -> Encerrado | Z45: =IF(OR(L45="PENDENTE",L45="EM ANDAMENTO",L45="PENDENTE APROVAÇÃO CANCELAMENTO NF"),TODAY()-O45,X45-O45) -> 209 | AA45: =IF(Y45="Aberto",Z45+ROW()/100000,"") | AB45: =IF(ISNUMBER(FIND("@cielo.com.br",S45)),"Interno","Externo") -> Interno
B46: Emilly Maria | C46: =VLOOKUP(I:I,'Referencias '!H:I,2,0) -> Cancelamento e Reemissão de Nota Fiscal | D46: 18899169 | E46: 0 | F46: 2602310354728 | G46: =VLOOKUP(H:H,'Referencias '!B:C,2,0) -> CINEMARK BRASIL S.A. | H46: =TRIM(_xlfn.TEXTBEFORE(_xlfn.TEXTAFTER(U46,"CNPJ/CPF:</strong>"),"</p>")) -> 00.779.721/0001-41 | I46: Cancelamento de NF / reemissão | L46: FINALIZADO | M46: Médio | N46: 1018 Financeiro | Desejo falar com o setor financeiro | CINEMARK BRASIL S.A. | ariane.pasilva@cielo.com.br | O46: 46045 | P46: 46045 | Q46: =TEXT(O46,"mmm/aaaa") -> jan/2026 | R46: ECOMMERCE BP SUPORTE FINANCEIRO N2 | S46: ariane.pasilva@cielo.com.br | U46: Olá, segue formulário enviado para Cielo E-commerce:<p><strong>Qual seu nome?:</strong> CINEMARK BRASIL S.A.</p><p><strong>Endereço de e-mail:</strong> ariane.pasilva@cielo.com.br</p><p><strong>CNPJ/CPF:</strong> 00.779.721/0001-41</p><p><strong>Telefone:</strong> (11) 97707-1602</p><p><strong>Assunto:</strong> Substituição de NF</p><p><strong>Merchant ID/Estabelecimento Comercial (EC):</strong> 00.779.721/0001-41</p><p><strong>Descrição do problema:</strong> Segue em anexo, POS para substituição das NFS do cinemark</p><p><strong>ID da transação:</strong> </p><p><strong>Código do erro:</strong> </p><p><strong>Sobre qual produto ou área deseja falar?:</strong> Financeiro</p><p><strong>Como podemos te ajudar?:</strong> Desejo falar com o setor financeiro</p><p><strong>GA Client ID:</strong> 1401063149.1757524286</p><p><strong>Lead Hash ID:</strong> 2a07344672c93c9ca782cc07cf9dc37d0cd4c270e817a83b9f87f9b32f0130a9</p><p><strong>Lead Form ID:</strong> 2a07344672c93c9ca782cc07cf9dc37d0cd4c27 | V46: =IFERROR(_xlfn.TEXTBEFORE(_xlfn.TEXTAFTER(U46,"Descrição do problema:</strong"),"</p>"),_xlfn.TEXTAFTER(U46,"Descrição do problema:</strong")) -> > Segue em anexo, POS para substituição das NFS do cinemark | W46: =_xlfn.CONCAT(D46:E46) -> 188991690 | X46: 46240 | Y46: =IF(X46="","Aberto","Encerrado") -> Encerrado | Z46: =IF(OR(L46="PENDENTE",L46="EM ANDAMENTO",L46="PENDENTE APROVAÇÃO CANCELAMENTO NF"),TODAY()-O46,X46-O46) -> 195 | AA46: =IF(Y46="Aberto",Z46+ROW()/100000,"") | AB46: =IF(ISNUMBER(FIND("@cielo.com.br",S46)),"Interno","Externo") -> Interno
B47: Emilly Maria | C47: =VLOOKUP(I:I,'Referencias '!H:I,2,0) -> Cancelamento e Reemissão de Nota Fiscal | D47: 18973729 | E47: 0 | F47: 2602617408016 | G47: =VLOOKUP(H:H,'Referencias '!B:C,2,0) -> BERTOLINI S/A | H47: =TRIM(_xlfn.TEXTBEFORE(_xlfn.TEXTAFTER(U47,"CNPJ/CPF:</strong>"),"</p>")) -> 87.556.650/0015-00 | I47: Cancelamento de NF / reemissão | L47: FINALIZADO | M47: Médio | N47: 1018 Financeiro | Desejo falar com o setor financeiro | BERTOLINI S/A | bordini@cielo.com.br | O47: 46048 | P47: 46108 | Q47: =TEXT(O47,"mmm/aaaa") -> jan/2026 | R47: ECOMMERCE BP SUPORTE FINANCEIRO N2 | S47: bordini@cielo.com.br | T47: BERTOLINI SA | U47: Olá, segue formulário enviado para Cielo E-commerce:<p><strong>CNPJ/CPF:</strong> 87.556.650/0015-00</p><p><strong>Merchant ID/Estabelecimento Comercial (EC):</strong> 87.556.650/0015-00</p><p><strong>Qual seu nome?:</strong> BERTOLINI S/A</p><p><strong>Endereço de e-mail:</strong> bordini@cielo.com.br</p><p><strong>Telefone:</strong> (54) 2102-4913</p><p><strong>Assunto:</strong> Cancelar boleto no CNPJ errado</p><p><strong>Descrição do problema:</strong> Time tudo bem? Fizemos a cessão contratual desse cliente porém recebi esse email dele hoje: Boa tarde, Jessica, tudo bem? Novamente a NF 105031 foi emitida para o CNPJ da matriz. Precisamos que cancelem essa NF e emitam para o CNPJ da Bertolini Móveis: 87.556.560/0015-00. Ficamos no aguardo da correção.</p><p><strong>ID da transação:</strong> </p><p><strong>Código do erro:</strong> </p><p><strong>Sobre qual produto ou área deseja falar?:</strong> Financeiro</p><p><strong>Como podemos te ajudar?:</strong> Desejo falar com o setor f | V47: =IFERROR(_xlfn.TEXTBEFORE(_xlfn.TEXTAFTER(U47,"Descrição do problema:</strong"),"</p>"),_xlfn.TEXTAFTER(U47,"Descrição do problema:</strong")) -> > Time tudo bem? Fizemos a cessão contratual desse cliente porém recebi esse email dele hoje: Boa tarde, Jessica, tudo bem? Novamente a NF 105031 foi emitida para o CNPJ da matriz. Precisamos que cancelem essa NF e emitam para o CNPJ da Bertolini Móveis: 87.556.560/0015-00. Ficamos no aguardo da correção. | W47: =_xlfn.CONCAT(D47:E47) -> 189737290 | X47: 46108 | Y47: =IF(X47="","Aberto","Encerrado") -> Encerrado | Z47: =IF(OR(L47="PENDENTE",L47="EM ANDAMENTO",L47="PENDENTE APROVAÇÃO CANCELAMENTO NF"),TODAY()-O47,X47-O47) -> 60 | AA47: =IF(Y47="Aberto",Z47+ROW()/100000,"") | AB47: =IF(ISNUMBER(FIND("@cielo.com.br",S47)),"Interno","Externo") -> Interno
B48: Pamela de Sá | C48: =VLOOKUP(I:I,'Referencias '!H:I,2,0) -> Cobrança e Contestação | D48: 18967500 | E48: 0 | F48: 2602615403575 | G48: =T48 | H48: =TRIM(_xlfn.TEXTBEFORE(_xlfn.TEXTAFTER(U48,"CNPJ/CPF:</strong>"),"</p>")) -> 61.763.443/0001-29 | I48: Contestação de cobrança | L48: EM ANDAMENTO | M48: Médio | N48: 1018 Financeiro | Desejo falar com o setor financeiro | Pedro Sales Queiroz Martins | pedro.martins@bateriasmoura.com | O48: 46048 | P48: 46114 | Q48: =TEXT(O48,"mmm/aaaa") -> jan/2026 | R48: Larissa QUIRINO CANUTO | S48: pedro.martins@bateriasmoura.com | U48: Olá, segue formulário enviado para Cielo E-commerce:<p><strong>Qual seu nome?:</strong> Pedro Sales Queiroz Martins</p><p><strong>Endereço de e-mail:</strong> pedro.martins@bateriasmoura.com</p><p><strong>CNPJ/CPF:</strong> 61.763.443/0001-29</p><p><strong>Telefone:</strong> (77) 99871-6054</p><p><strong>Assunto:</strong> COBRANÇA INDEVIDA, REEMBOLSO E CORREÇÃO</p><p><strong>Merchant ID/Estabelecimento Comercial (EC):</strong> 716283c1-f8fe-4af1-8067-ef838fd89204</p><p><strong>Sobre qual produto ou área deseja falar?:</strong> Financeiro</p><p><strong>Descrição do problema:</strong> Cliente desde o início recebendo cobranças de 99.00 no lugar dos 40,00 acordados para a marca BRASPAG. Favor realizar o levantamento desses meses e realizar o estorno/correção das taxas futuras de aluguel.</p><p><strong>Como podemos te ajudar?:</strong> Desejo falar com o setor financeiro</p><p><strong>GA Client ID:</strong> 1040538107.1769452831</p><p><strong>Lead Hash ID:</strong> 8389978c8d4397cc917a98f | V48: =IFERROR(_xlfn.TEXTBEFORE(_xlfn.TEXTAFTER(U48,"Descrição do problema:</strong"),"</p>"),_xlfn.TEXTAFTER(U48,"Descrição do problema:</strong")) -> > Cliente desde o início recebendo cobranças de 99.00 no lugar dos 40,00 acordados para a marca BRASPAG. Favor realizar o levantamento desses meses e realizar o estorno/correção das taxas futuras de aluguel. | W48: =_xlfn.CONCAT(D48:E48) -> 189675000 | Y48: =IF(X48="","Aberto","Encerrado") -> Aberto | Z48: =IF(OR(L48="PENDENTE",L48="EM ANDAMENTO",L48="PENDENTE APROVAÇÃO CANCELAMENTO NF"),TODAY()-O48,X48-O48) -> 242 | AA48: =IF(Y48="Aberto",Z48+ROW()/100000,"") -> 242.00048 | AB48: =IF(ISNUMBER(FIND("@cielo.com.br",S48)),"Interno","Externo") -> Externo
B49: Emilly Maria | C49: =VLOOKUP(I:I,'Referencias '!H:I,2,0) -> Cancelamento e Reemissão de Nota Fiscal | D49: 18983285 | E49: 0 | F49: 2602709414783 | G49: =VLOOKUP(H:H,'Referencias '!B:C,2,0) -> ECOFILLER LTDA | H49: =TRIM(_xlfn.TEXTBEFORE(_xlfn.TEXTAFTER(U49,"CNPJ/CPF:</strong>"),"</p>")) -> 63.936.441/0001-10 | I49: Cancelamento de NF / reemissão | L49: FINALIZADO | M49: Médio | N49: 1018 Financeiro | Desejo falar com o setor financeiro | Matheus Paulielo | matheus.psilva@cielo.com.br | O49: 46049 | P49: 46051 | Q49: =TEXT(O49,"mmm/aaaa") -> jan/2026 | R49: ECOMMERCE BP SUPORTE FINANCEIRO N2 | S49: matheus.psilva@cielo.com.br | T49: GRUPO ECOFILLER | U49: Olá, segue formulário enviado para Cielo E-commerce:<p><strong>Qual seu nome?:</strong> Matheus Paulielo</p><p><strong>Endereço de e-mail:</strong> matheus.psilva@cielo.com.br</p><p><strong>CNPJ/CPF:</strong> 63.936.441/0001-10</p><p><strong>Telefone:</strong> (13) 99140-2960</p><p><strong>Assunto:</strong> Cancelamento sem multa</p><p><strong>Merchant ID/Estabelecimento Comercial (EC):</strong> 63.936.441/0001-10</p><p><strong>Sobre qual produto ou área deseja falar?:</strong> Financeiro</p><p><strong>Como podemos te ajudar?:</strong> Desejo falar com o setor financeiro</p><p><strong>Descrição do problema:</strong> Time, bom dia! Espero que estejam bem. Foi efetuado um cancelamento de contrato, pois o antifraude foi inserido no contrato por equívoco durante o preenchimento da minuta padrão. O cliente não havia solicitado nem contratado essa solução. Para correção do escopo e reabertura do processo conforme orientação do time de implantação, será necessário o cancelamento integral do | V49: =IFERROR(_xlfn.TEXTBEFORE(_xlfn.TEXTAFTER(U49,"Descrição do problema:</strong"),"</p>"),_xlfn.TEXTAFTER(U49,"Descrição do problema:</strong")) -> > Time, bom dia! Espero que estejam bem. Foi efetuado um cancelamento de contrato, pois o antifraude foi inserido no contrato por equívoco durante o preenchimento da minuta padrão. O cliente não havia solicitado nem contratado essa solução. Para correção do escopo e reabertura do processo conforme orientação do time de implantação, será necessário o cancelamento integral do | W49: =_xlfn.CONCAT(D49:E49) -> 189832850 | X49: 46269 | Y49: =IF(X49="","Aberto","Encerrado") -> Encerrado | Z49: =IF(OR(L49="PENDENTE",L49="EM ANDAMENTO",L49="PENDENTE APROVAÇÃO CANCELAMENTO NF"),TODAY()-O49,X49-O49) -> 220 | AA49: =IF(Y49="Aberto",Z49+ROW()/100000,"") | AB49: =IF(ISNUMBER(FIND("@cielo.com.br",S49)),"Interno","Externo") -> Interno
B50: Emilly Maria | C50: =VLOOKUP(I:I,'Referencias '!H:I,2,0) -> Cancelamento e Reemissão de Nota Fiscal | D50: 19094173 | E50: 0 | F50: 2602914494650 | G50: =VLOOKUP(H:H,'Referencias '!B:C,2,0) -> AGRO-COMERCIAL AFUBRA LTDA | H50: =TRIM(_xlfn.TEXTBEFORE(_xlfn.TEXTAFTER(U50,"CNPJ/CPF:</strong>"),"</p>")) -> 74.072.513/0001-44 | I50: Cancelamento de NF / reemissão | L50: FINALIZADO | M50: Médio | N50: 1018 Financeiro | Desejo falar com o setor financeiro | AGRO-COMERCIAL AFUBRA LTDA | ariane.pasilva@cielo.com.br | O50: 46051 | P50: 46051 | Q50: =TEXT(O50,"mmm/aaaa") -> jan/2026 | R50: ECOMMERCE BP SUPORTE FINANCEIRO N2 | S50: ariane.pasilva@cielo.com.br | T50: AGRO COMERCIAL AFUBRA | U50: Olá, segue formulário enviado para Cielo E-commerce:<p><strong>Endereço de e-mail:</strong> ariane.pasilva@cielo.com.br</p><p><strong>CNPJ/CPF:</strong> 74.072.513/0001-44</p><p><strong>Qual seu nome?:</strong> AGRO-COMERCIAL AFUBRA LTDA</p><p><strong>Telefone:</strong> (11) 97707-1602</p><p><strong>Assunto:</strong> NF paga duplicada</p><p><strong>Merchant ID/Estabelecimento Comercial (EC):</strong> 74072513000144</p><p><strong>Descrição do problema:</strong> Por favor, como faremos com as NFS de dezembro duplicada? Mesmo produto, mesmo período, mesmo valor? Como iremos estornar para o cliente?</p><p><strong>ID da transação:</strong> </p><p><strong>Código do erro:</strong> </p><p><strong>Sobre qual produto ou área deseja falar?:</strong> Financeiro</p><p><strong>Como podemos te ajudar?:</strong> Desejo falar com o setor financeiro</p><p><strong>GA Client ID:</strong> 1401063149.1757524286</p><p><strong>Lead Hash ID:</strong> 2a07344672c93c9ca782cc07cf9dc37d0cd4c270e817a83b9f87f9b32f01 | V50: =IFERROR(_xlfn.TEXTBEFORE(_xlfn.TEXTAFTER(U50,"Descrição do problema:</strong"),"</p>"),_xlfn.TEXTAFTER(U50,"Descrição do problema:</strong")) -> > Por favor, como faremos com as NFS de dezembro duplicada? Mesmo produto, mesmo período, mesmo valor? Como iremos estornar para o cliente? | W50: =_xlfn.CONCAT(D50:E50) -> 190941730 | X50: 46240 | Y50: =IF(X50="","Aberto","Encerrado") -> Encerrado | Z50: =IF(OR(L50="PENDENTE",L50="EM ANDAMENTO",L50="PENDENTE APROVAÇÃO CANCELAMENTO NF"),TODAY()-O50,X50-O50) -> 189 | AA50: =IF(Y50="Aberto",Z50+ROW()/100000,"") | AB50: =IF(ISNUMBER(FIND("@cielo.com.br",S50)),"Interno","Externo") -> Interno
B51: Pamela de Sá | C51: =VLOOKUP(I:I,'Referencias '!H:I,2,0) -> Pagamentos, Boletos e Recebimentos | D51: 19076026 | E51: 0 | F51: 2602910481963 | G51: =VLOOKUP(H:H,'Referencias '!B:C,2,0) -> CLARO S.A. | H51: =TRIM(_xlfn.TEXTBEFORE(_xlfn.TEXTAFTER(U51,"CNPJ/CPF:</strong>"),"</p>")) -> 40.432.544/0062-69 | I51: Alteração de vencimento / prorrogação | L51: FINALIZADO | M51: Médio | N51: 1018 Financeiro | Desejo falar com o setor financeiro | CLARO S.A. | ariane.pasilva@cielo.com.br | O51: 46051 | P51: 46059 | Q51: =TEXT(O51,"mmm/aaaa") -> jan/2026 | R51: Larissa QUIRINO CANUTO | S51: ariane.pasilva@cielo.com.br | U51: Olá, segue formulário enviado para Cielo E-commerce:<p><strong>Qual seu nome?:</strong> CLARO S.A.</p><p><strong>Endereço de e-mail:</strong> ariane.pasilva@cielo.com.br</p><p><strong>CNPJ/CPF:</strong> 40.432.544/0062-69</p><p><strong>Telefone:</strong> (11) 97707-1602</p><p><strong>Assunto:</strong> Data de de emissão no mês de vencimento</p><p><strong>Merchant ID/Estabelecimento Comercial (EC):</strong> 40432544006269</p><p><strong>Descrição do problema:</strong> PO SUBSTITUIÇÃO fev/25 600660281 abr/25 600680581 jun/25 600697748 jul/25 600708919 set/25 600732907 out/25 600742360 Preciso que a data de emissão das seguintes NFS estejam no mesmo mês que o vencimento: 087139 090419 094211 095870 097871 099723 101659 103678</p><p><strong>ID da transação:</strong> </p><p><strong>Código do erro:</strong> </p><p><strong>Sobre qual produto ou área deseja falar?:</strong> Financeiro</p><p><strong>Como podemos te ajudar?:</strong> Desejo falar com o setor financeiro</p><p><strong>GA Client I | V51: =IFERROR(_xlfn.TEXTBEFORE(_xlfn.TEXTAFTER(U51,"Descrição do problema:</strong"),"</p>"),_xlfn.TEXTAFTER(U51,"Descrição do problema:</strong")) -> > PO SUBSTITUIÇÃO fev/25 600660281 abr/25 600680581 jun/25 600697748 jul/25 600708919 set/25 600732907 out/25 600742360 Preciso que a data de emissão das seguintes NFS estejam no mesmo mês que o vencimento: 087139 090419 094211 095870 097871 099723 101659 103678 | W51: =_xlfn.CONCAT(D51:E51) -> 190760260 | X51: 46234 | Y51: =IF(X51="","Aberto","Encerrado") -> Encerrado | Z51: =IF(OR(L51="PENDENTE",L51="EM ANDAMENTO",L51="PENDENTE APROVAÇÃO CANCELAMENTO NF"),TODAY()-O51,X51-O51) -> 183 | AA51: =IF(Y51="Aberto",Z51+ROW()/100000,"") | AB51: =IF(ISNUMBER(FIND("@cielo.com.br",S51)),"Interno","Externo") -> Interno
B52: Stephany Lima | C52: =VLOOKUP(I:I,'Referencias '!H:I,2,0) -> Cancelamento e Reemissão de Nota Fiscal | D52: 19068976 | E52: 0 | F52: 0 | G52: =VLOOKUP(H:H,'Referencias '!B:C,2,0) -> CINEMARK BRASIL S.A. | H52: =TRIM(_xlfn.TEXTBEFORE(_xlfn.TEXTAFTER(U52,"CNPJ/CPF:</strong>"),"</p>")) -> 00.779.721/0001-41 | I52: Cancelamento de NF / reemissão | L52: FINALIZADO | M52: Médio | N52: 1018 Financeiro | Desejo falar com o setor financeiro | CINEMARK BRASIL S.A. | ariane.pasilva@cielo.com.br | O52: 46051 | P52: 46073 | Q52: =TEXT(O52,"mmm/aaaa") -> jan/2026 | R52: STEPHANY LIMA DE LISBOA | S52: ariane.pasilva@cielo.com.br | U52: Olá, segue formulário enviado para Cielo E-commerce:<p><strong>Qual seu nome?:</strong> CINEMARK BRASIL S.A.</p><p><strong>Endereço de e-mail:</strong> ariane.pasilva@cielo.com.br</p><p><strong>CNPJ/CPF:</strong> 00.779.721/0001-41</p><p><strong>Telefone:</strong> (11) 97707-1602</p><p><strong>Assunto:</strong> PO SUBSTITUIÇÃO</p><p><strong>Merchant ID/Estabelecimento Comercial (EC):</strong> 00.779.721/0001-41</p><p><strong>Descrição do problema:</strong> Por favor, realizar substituição de NF. Adiciono o pedido do antifraude de dez/25. OC000743944 – R$46.109,23 Antifraude Dezembro 2025. Em anexo.</p><p><strong>ID da transação:</strong> </p><p><strong>Código do erro:</strong> </p><p><strong>Sobre qual produto ou área deseja falar?:</strong> Financeiro</p><p><strong>Como podemos te ajudar?:</strong> Desejo falar com o setor financeiro</p><p><strong>GA Client ID:</strong> 1401063149.1757524286</p><p><strong>Lead Hash ID:</strong> 2a07344672c93c9ca782cc07cf9dc37d0cd4c270e817a83b9f87f9b | V52: =IFERROR(_xlfn.TEXTBEFORE(_xlfn.TEXTAFTER(U52,"Descrição do problema:</strong"),"</p>"),_xlfn.TEXTAFTER(U52,"Descrição do problema:</strong")) -> > Por favor, realizar substituição de NF. Adiciono o pedido do antifraude de dez/25. OC000743944 – R$46.109,23 Antifraude Dezembro 2025. Em anexo. | W52: =_xlfn.CONCAT(D52:E52) -> 190689760 | X52: 46232 | Y52: =IF(X52="","Aberto","Encerrado") -> Encerrado | Z52: =IF(OR(L52="PENDENTE",L52="EM ANDAMENTO",L52="PENDENTE APROVAÇÃO CANCELAMENTO NF"),TODAY()-O52,X52-O52) -> 181 | AA52: =IF(Y52="Aberto",Z52+ROW()/100000,"") | AB52: =IF(ISNUMBER(FIND("@cielo.com.br",S52)),"Interno","Externo") -> Interno
B53: Vanessa Araujo | C53: =VLOOKUP(I:I,'Referencias '!H:I,2,0) -> Pagamentos, Boletos e Recebimentos | D53: 19318187 | E53: 0 | F53: 2603615657622 | G53: =VLOOKUP(H:H,'Referencias '!B:C,2,0) -> PNEUBRAS COMERCIO DE PNEUS LTDA | H53: =TRIM(_xlfn.TEXTBEFORE(_xlfn.TEXTAFTER(U53,"CNPJ/CPF:</strong>"),"</p>")) -> 08.678.386/0001-05 | I53: Alteração de vencimento / prorrogação | L53: FINALIZADO | M53: Médio | N53: 1018 Financeiro | Desejo falar com o setor financeiro | Yasmin Melo | yasmin.melo@pneubras.com | O53: 46058 | P53: 46073 | Q53: =TEXT(O53,"mmm/aaaa") -> fev/2026 | R53: Vanessa dos Santos Araujo | S53: yasmin.melo@pneubras.com | T53: PNEUBRAS | U53: Olá, segue formulário enviado para Cielo E-commerce:<p><strong>Qual seu nome?:</strong> Yasmin Melo</p><p><strong>Endereço de e-mail:</strong> yasmin.melo@pneubras.com</p><p><strong>CNPJ/CPF:</strong> 08.678.386/0001-05</p><p><strong>Telefone:</strong> (81) 9133-8500</p><p><strong>Assunto:</strong> Alteração de data de emissão dos boletos</p><p><strong>Sobre qual produto ou área deseja falar?:</strong> Financeiro</p><p><strong>Como podemos te ajudar?:</strong> Desejo falar com o setor financeiro</p><p><strong>Descrição do problema:</strong> Boa tarde! Referente a essa nova cobrança que chegou aqui para nós, eu só consigo entregar as notas emitidas dentro do mês até o dia 25 de cada mês apenas. Devido aos prazos internos que possuímos. Quero saber se é possível realizar o cancelamento desta nota e emitir essa cobrança no dia 02/02 por gentileza? Aguardo um retorno.</p><p><strong>Merchant ID/Estabelecimento Comercial (EC):</strong> 12f6759a-2a45-48dc-9edf-e01cca4836c8</p><p><strong>GA | V53: =IFERROR(_xlfn.TEXTBEFORE(_xlfn.TEXTAFTER(U53,"Descrição do problema:</strong"),"</p>"),_xlfn.TEXTAFTER(U53,"Descrição do problema:</strong")) -> > Boa tarde! Referente a essa nova cobrança que chegou aqui para nós, eu só consigo entregar as notas emitidas dentro do mês até o dia 25 de cada mês apenas. Devido aos prazos internos que possuímos. Quero saber se é possível realizar o cancelamento desta nota e emitir essa cobrança no dia 02/02 por gentileza? Aguardo um retorno. | W53: =_xlfn.CONCAT(D53:E53) -> 193181870 | X53: 46233 | Y53: =IF(X53="","Aberto","Encerrado") -> Encerrado | Z53: =IF(OR(L53="PENDENTE",L53="EM ANDAMENTO",L53="PENDENTE APROVAÇÃO CANCELAMENTO NF"),TODAY()-O53,X53-O53) -> 175 | AA53: =IF(Y53="Aberto",Z53+ROW()/100000,"") | AB53: =IF(ISNUMBER(FIND("@cielo.com.br",S53)),"Interno","Externo") -> Externo
B54: Stephany Lima | C54: =VLOOKUP(I:I,'Referencias '!H:I,2,0) -> Cancelamento e Reemissão de Nota Fiscal | D54: 19294254 | E54: 0 | F54: 2603610640508 | G54: =VLOOKUP(H:H,'Referencias '!B:C,2,0) -> ASSOCIACAO ESCOLA SUPERIOR DE PROPAGANDA E MARKETING | H54: =TRIM(_xlfn.TEXTBEFORE(_xlfn.TEXTAFTER(U54,"CNPJ/CPF:</strong>"),"</p>")) -> 61.825.675/0001-64 | I54: Cancelamento de NF / reemissão | L54: FINALIZADO | M54: Médio | N54: 1018 Financeiro | Desejo falar com o setor financeiro | Elaine Nascimento | elaine.nascimento@espm.br | O54: 46058 | P54: 46064 | Q54: =TEXT(O54,"mmm/aaaa") -> fev/2026 | R54: STEPHANY LIMA DE LISBOA | S54: elaine.nascimento@espm.br | T54: ESPM | U54: Olá, segue formulário enviado para Cielo E-commerce:<p><strong>Qual seu nome?:</strong> Elaine Nascimento</p><p><strong>Endereço de e-mail:</strong> elaine.nascimento@espm.br</p><p><strong>CNPJ/CPF:</strong> 61.825.675/0001-64</p><p><strong>Telefone:</strong> (11) 5058-6794</p><p><strong>Assunto:</strong> O contrato nº 430 foi encerrado</p><p><strong>Descrição do problema:</strong> O contrato nº 430 foi encerrado e, conforme e-mail anexo, a contagem do período de aviso teve início em 03/11/2025, data de recebimento da notificação. Assim, o valor devido pelos 90 dias subsequentes corresponderia a aproximadamente 3 parcelas de R$ 821,35, totalizando R$ 2.464,05. No entanto, foi realizada a cobrança do valor de R$ 1.642,71 por nota fiscal. Efetuamos o pagamento de duas NF’s (anexas), cada uma no valor de R$ 1.642,71, totalizando R$ 3.285,42. Ressaltamos que o valor correto a ser pago seria R$ 1.642,70. Dessa forma, entendemos que a NF nº 0105703 foi cobrada indevidamente e que há um créd | V54: =IFERROR(_xlfn.TEXTBEFORE(_xlfn.TEXTAFTER(U54,"Descrição do problema:</strong"),"</p>"),_xlfn.TEXTAFTER(U54,"Descrição do problema:</strong")) -> > O contrato nº 430 foi encerrado e, conforme e-mail anexo, a contagem do período de aviso teve início em 03/11/2025, data de recebimento da notificação. Assim, o valor devido pelos 90 dias subsequentes corresponderia a aproximadamente 3 parcelas de R$ 821,35, totalizando R$ 2.464,05. No entanto, foi realizada a cobrança do valor de R$ 1.642,71 por nota fiscal. Efetuamos o pagamento de duas NF’s (anexas), cada uma no valor de R$ 1.642,71, totalizando R$ 3.285,42. Ressaltamos que o valor correto a ser pago seria R$ 1.642,70. Dessa forma, entendemos que a NF nº 0105703 foi cobrada indevidamente e que há um créd | W54: =_xlfn.CONCAT(D54:E54) -> 192942540 | X54: 46289 | Y54: =IF(X54="","Aberto","Encerrado") -> Encerrado | Z54: =IF(OR(L54="PENDENTE",L54="EM ANDAMENTO",L54="PENDENTE APROVAÇÃO CANCELAMENTO NF"),TODAY()-O54,X54-O54) -> 231 | AA54: =IF(Y54="Aberto",Z54+ROW()/100000,"") | AB54: =IF(ISNUMBER(FIND("@cielo.com.br",S54)),"Interno","Externo") -> Externo
B55: Pamela de Sá | C55: =VLOOKUP(I:I,'Referencias '!H:I,2,0) -> Contratos, Comercial e Cadastro | D55: 19334708 | E55: 0 | F55: 2603709669813 | G55: =VLOOKUP(H:H,'Referencias '!B:C,2,0) -> MASTER CARGAS BRASIL LTDA | H55: =TRIM(_xlfn.TEXTBEFORE(_xlfn.TEXTAFTER(U55,"CNPJ/CPF:</strong>"),"</p>")) -> 03.537.589/0001-50 | I55: Cancelamento contrato (produto) / NF | L55: FINALIZADO | M55: Médio | N55: 1018 Financeiro | Desejo falar com o setor financeiro | Giulia | giuliac@cielo.com.br | O55: 46059 | P55: 46063 | Q55: =TEXT(O55,"mmm/aaaa") -> fev/2026 | R55: Emilly Maria Sousa Almeida | S55: giuliac@cielo.com.br | T55: MASTER CARGAS BRASIL | U55: Olá, segue formulário enviado para Cielo E-commerce:<p><strong>Qual seu nome?:</strong> Giulia</p><p><strong>Endereço de e-mail:</strong> giuliac@cielo.com.br</p><p><strong>CNPJ/CPF:</strong> 03.537.589/0001-50</p><p><strong>Telefone:</strong> (11) 99104-1320</p><p><strong>Assunto:</strong> Cancelamento Parcial Sem Multa</p><p><strong>Merchant ID/Estabelecimento Comercial (EC):</strong> 03.537.589/0001-50</p><p><strong>Descrição do problema:</strong> Cliente contratou os produtos Gateway e 3DS, porem não conseguiu integrar o 3DS pela versão de sua plataforma não ser compatível. Como não temos essa especificação na documentação, precisamos cancelar apenas esse produto sem multa e cancelar as cobranças desse produto ja emitidas. Tenho o D.A da diretoria.</p><p><strong>ID da transação:</strong> </p><p><strong>Código do erro:</strong> </p><p><strong>Sobre qual produto ou área deseja falar?:</strong> Financeiro</p><p><strong>Como podemos te ajudar?:</strong> Desejo falar com o setor finance | V55: =IFERROR(_xlfn.TEXTBEFORE(_xlfn.TEXTAFTER(U55,"Descrição do problema:</strong"),"</p>"),_xlfn.TEXTAFTER(U55,"Descrição do problema:</strong")) -> > Cliente contratou os produtos Gateway e 3DS, porem não conseguiu integrar o 3DS pela versão de sua plataforma não ser compatível. Como não temos essa especificação na documentação, precisamos cancelar apenas esse produto sem multa e cancelar as cobranças desse produto ja emitidas. Tenho o D.A da diretoria. | W55: =_xlfn.CONCAT(D55:E55) -> 193347080 | X55: 46233 | Y55: =IF(X55="","Aberto","Encerrado") -> Encerrado | Z55: =IF(OR(L55="PENDENTE",L55="EM ANDAMENTO",L55="PENDENTE APROVAÇÃO CANCELAMENTO NF"),TODAY()-O55,X55-O55) -> 174 | AA55: =IF(Y55="Aberto",Z55+ROW()/100000,"") | AB55: =IF(ISNUMBER(FIND("@cielo.com.br",S55)),"Interno","Externo") -> Interno
B56: Stephany Lima | C56: =VLOOKUP(I:I,'Referencias '!H:I,2,0) -> Cancelamento e Reemissão de Nota Fiscal | D56: 19332816 | E56: 0 | F56: 2603709668429 | G56: =T56 -> SERASA SA | H56: =TRIM(_xlfn.TEXTBEFORE(_xlfn.TEXTAFTER(U56,"CNPJ/CPF:</strong>"),"</p>")) -> 62.173.620/0093-06 | I56: Cancelamento de NF / reemissão | L56: FINALIZADO | M56: Médio | N56: 1018 Financeiro | Desejo falar com o setor financeiro | SERASA S.A. | ariane.pasilva@cielo.com.br | O56: 46059 | P56: 46086 | Q56: =TEXT(O56,"mmm/aaaa") -> fev/2026 | R56: Larissa QUIRINO CANUTO | S56: ariane.pasilva@cielo.com.br | T56: SERASA SA | U56: Olá, segue formulário enviado para Cielo E-commerce:<p><strong>CNPJ/CPF:</strong> 62.173.620/0093-06</p><p><strong>Endereço de e-mail:</strong> ariane.pasilva@cielo.com.br</p><p><strong>Qual seu nome?:</strong> SERASA S.A.</p><p><strong>Telefone:</strong> (11) 97707-1602</p><p><strong>Assunto:</strong> Cancelamento de NF</p><p><strong>Merchant ID/Estabelecimento Comercial (EC):</strong> 62173620009306</p><p><strong>Descrição do problema:</strong> Prezados, bom dia. Tudo bem? Por favor seguir com o cancelamento das NFS do SERASA CNPJ 62173620009306.</p><p><strong>ID da transação:</strong> </p><p><strong>Código do erro:</strong> </p><p><strong>Sobre qual produto ou área deseja falar?:</strong> Financeiro</p><p><strong>Como podemos te ajudar?:</strong> Desejo falar com o setor financeiro</p><p><strong>GA Client ID:</strong> 1401063149.1757524286</p><p><strong>Lead Hash ID:</strong> 2a07344672c93c9ca782cc07cf9dc37d0cd4c270e817a83b9f87f9b32f0130a9</p><p><strong>Lead Form ID:</strong> 2a0734 | V56: =IFERROR(_xlfn.TEXTBEFORE(_xlfn.TEXTAFTER(U56,"Descrição do problema:</strong"),"</p>"),_xlfn.TEXTAFTER(U56,"Descrição do problema:</strong")) -> > Prezados, bom dia. Tudo bem? Por favor seguir com o cancelamento das NFS do SERASA CNPJ 62173620009306. | W56: =_xlfn.CONCAT(D56:E56) -> 193328160 | X56: 46233 | Y56: =IF(X56="","Aberto","Encerrado") -> Encerrado | Z56: =IF(OR(L56="PENDENTE",L56="EM ANDAMENTO",L56="PENDENTE APROVAÇÃO CANCELAMENTO NF"),TODAY()-O56,X56-O56) -> 174 | AA56: =IF(Y56="Aberto",Z56+ROW()/100000,"") | AB56: =IF(ISNUMBER(FIND("@cielo.com.br",S56)),"Interno","Externo") -> Interno
B57: Emilly Maria | C57: =VLOOKUP(I:I,'Referencias '!H:I,2,0) -> Cancelamento e Reemissão de Nota Fiscal | D57: 19467621 | E57: 0 | F57: 2604118768702 | G57: =T57 | H57: =TRIM(_xlfn.TEXTBEFORE(_xlfn.TEXTAFTER(U57,"CNPJ/CPF:</strong>"),"</p>")) -> 02.916.265/0298-18 | I57: Cancelamento de NF / reemissão | L57: FINALIZADO | M57: Médio | N57: 1018 Financeiro | Desejo falar com o setor financeiro | Mariane Oliveira dos Santos | marianeodossantos@gmail.com | O57: 46063 | P57: 46064 | Q57: =TEXT(O57,"mmm/aaaa") -> fev/2026 | R57: ECOMMERCE BP SUPORTE FINANCEIRO N2 | S57: marianeodossantos@gmail.com | U57: Olá, segue formulário enviado para Cielo E-commerce:<p><strong>Qual seu nome?:</strong> Mariane Oliveira dos Santos</p><p><strong>Endereço de e-mail:</strong> marianeodossantos@gmail.com</p><p><strong>CNPJ/CPF:</strong> 02.916.265/0298-18</p><p><strong>Telefone:</strong> (11) 98407-1789</p><p><strong>Assunto:</strong> Emissão NFS</p><p><strong>Sobre qual produto ou área deseja falar?:</strong> Financeiro</p><p><strong>Como podemos te ajudar?:</strong> Desejo falar com o setor financeiro</p><p><strong>Descrição do problema:</strong> Boa tarde, pessoal! Tudo bem? A JBS nunca pagou suas faturas, entramos em contato para entender o motivo e o cliente disse que não pode receber fatura no CNPJ cadastrado na Braspag. Com isso, o jurídico elaborou um documento para formalizar a alteração do CNPJ, segue o documento assinado em anexo. Precisamos seguir com a emissão das NFs no CNPJ correto</p><p><strong>Merchant ID/Estabelecimento Comercial (EC):</strong> 02.916.265/0298-18</p><p><strong>GA Clie | V57: =IFERROR(_xlfn.TEXTBEFORE(_xlfn.TEXTAFTER(U57,"Descrição do problema:</strong"),"</p>"),_xlfn.TEXTAFTER(U57,"Descrição do problema:</strong")) -> > Boa tarde, pessoal! Tudo bem? A JBS nunca pagou suas faturas, entramos em contato para entender o motivo e o cliente disse que não pode receber fatura no CNPJ cadastrado na Braspag. Com isso, o jurídico elaborou um documento para formalizar a alteração do CNPJ, segue o documento assinado em anexo. Precisamos seguir com a emissão das NFs no CNPJ correto | W57: =_xlfn.CONCAT(D57:E57) -> 194676210 | X57: 46233 | Y57: =IF(X57="","Aberto","Encerrado") -> Encerrado | Z57: =IF(OR(L57="PENDENTE",L57="EM ANDAMENTO",L57="PENDENTE APROVAÇÃO CANCELAMENTO NF"),TODAY()-O57,X57-O57) -> 170 | AA57: =IF(Y57="Aberto",Z57+ROW()/100000,"") | AB57: =IF(ISNUMBER(FIND("@cielo.com.br",S57)),"Interno","Externo") -> Externo
B58: Emilly Maria | C58: =VLOOKUP(I:I,'Referencias '!H:I,2,0) -> Contratos, Comercial e Cadastro | D58: 19467525 | E58: 0 | F58: 2604118768638 | G58: =VLOOKUP(H:H,'Referencias '!B:C,2,0) -> ALFA AGENCIA DE VIAGENS LTDA | H58: =TRIM(_xlfn.TEXTBEFORE(_xlfn.TEXTAFTER(U58,"CNPJ/CPF:</strong>"),"</p>")) -> 07.141.168/0001-66 | I58: Congelamento de contrato | L58: FINALIZADO | M58: Médio | N58: 1018 Financeiro | Desejo falar com o setor financeiro | ALFA AGENCIA DE VIAGENS LTDA | bordini@cielo.com.br | O58: 46063 | P58: 46064 | Q58: =TEXT(O58,"mmm/aaaa") -> fev/2026 | R58: ECOMMERCE BP SUPORTE FINANCEIRO N2 | S58: bordini@cielo.com.br | U58: Olá, segue formulário enviado para Cielo E-commerce:<p><strong>Qual seu nome?:</strong> ALFA AGENCIA DE VIAGENS LTDA</p><p><strong>CNPJ/CPF:</strong> 07.141.168/0001-66</p><p><strong>Endereço de e-mail:</strong> bordini@cielo.com.br</p><p><strong>Telefone:</strong> (11) 94008-6890</p><p><strong>Assunto:</strong> Congelamento de Contrato</p><p><strong>Merchant ID/Estabelecimento Comercial (EC):</strong> 07.141.168/0001-66</p><p><strong>Descrição do problema:</strong> Boa tarde, time, espero que estejam bem! Cliente deseja congelar o contrato , dos produtos de AF mínimo mensal e Analista dedicado mensal Cyber, sendo assim segue documento assinado por todos. Atenciosamente.</p><p><strong>ID da transação:</strong> </p><p><strong>Código do erro:</strong> </p><p><strong>Sobre qual produto ou área deseja falar?:</strong> Financeiro</p><p><strong>Como podemos te ajudar?:</strong> Desejo falar com o setor financeiro</p><p><strong>Data e hora do erro:</strong> 10-02-2026 18:07</p><p><strong>G | V58: =IFERROR(_xlfn.TEXTBEFORE(_xlfn.TEXTAFTER(U58,"Descrição do problema:</strong"),"</p>"),_xlfn.TEXTAFTER(U58,"Descrição do problema:</strong")) -> > Boa tarde, time, espero que estejam bem! Cliente deseja congelar o contrato , dos produtos de AF mínimo mensal e Analista dedicado mensal Cyber, sendo assim segue documento assinado por todos. Atenciosamente. | W58: =_xlfn.CONCAT(D58:E58) -> 194675250 | X58: 46233 | Y58: =IF(X58="","Aberto","Encerrado") -> Encerrado | Z58: =IF(OR(L58="PENDENTE",L58="EM ANDAMENTO",L58="PENDENTE APROVAÇÃO CANCELAMENTO NF"),TODAY()-O58,X58-O58) -> 170 | AA58: =IF(Y58="Aberto",Z58+ROW()/100000,"") | AB58: =IF(ISNUMBER(FIND("@cielo.com.br",S58)),"Interno","Externo") -> Interno
B59: Emilly Maria | C59: =VLOOKUP(I:I,'Referencias '!H:I,2,0) -> Cobrança e Contestação | D59: 19443812 | E59: 0 | F59: 2604112751267 | G59: =VLOOKUP(H:H,'Referencias '!B:C,2,0) -> ASSOCIACAO ESCOLA SUPERIOR DE PROPAGANDA E MARKETING | H59: =TRIM(_xlfn.TEXTBEFORE(_xlfn.TEXTAFTER(U59,"CNPJ/CPF:</strong>"),"</p>")) -> 61.825.675/0001-64 | I59: Contestação de cobrança | L59: FINALIZADO | M59: Médio | N59: 1001 Split de Pagamento | Carta de cancelamento Split | Elaine Nascimento | elaine.nascimento@espm.br | O59: 46063 | P59: 46064 | Q59: =TEXT(O59,"mmm/aaaa") -> fev/2026 | R59: ECOMMERCE BP SUPORTE FINANCEIRO N2 | S59: elaine.nascimento@espm.br | U59: Olá, segue formulário enviado para Cielo E-commerce:<p><strong>Qual seu nome?:</strong> Elaine Nascimento</p><p><strong>Endereço de e-mail:</strong> elaine.nascimento@espm.br</p><p><strong>CNPJ/CPF:</strong> 61.825.675/0001-64</p><p><strong>Telefone:</strong> (11) 5058-6794</p><p><strong>Assunto:</strong> O contrato nº 430 foi encerrado</p><p><strong>Merchant ID/Estabelecimento Comercial (EC):</strong> O contrato nº 430 foi encerrado</p><p><strong>Descrição do problema:</strong> Bom dia! Prezados, O contrato nº 430 foi encerrado e, conforme e-mail anexo, a contagem do período de aviso teve início em 03/11/2025, data de recebimento da notificação. Assim, o valor devido pelos 90 dias subsequentes corresponderia a aproximadamente 3 parcelas de R$ 821,35, totalizando R$ 2.464,05. No entanto, foi realizada a cobrança do valor de R$ 1.642,71 por nota fiscal. Efetuamos o pagamento de duas NF’s (anexas), cada uma no valor de R$ 1.642,71, totalizando R$ 3.285,42. Ressaltamos que o valor corre | V59: =IFERROR(_xlfn.TEXTBEFORE(_xlfn.TEXTAFTER(U59,"Descrição do problema:</strong"),"</p>"),_xlfn.TEXTAFTER(U59,"Descrição do problema:</strong")) -> > Bom dia! Prezados, O contrato nº 430 foi encerrado e, conforme e-mail anexo, a contagem do período de aviso teve início em 03/11/2025, data de recebimento da notificação. Assim, o valor devido pelos 90 dias subsequentes corresponderia a aproximadamente 3 parcelas de R$ 821,35, totalizando R$ 2.464,05. No entanto, foi realizada a cobrança do valor de R$ 1.642,71 por nota fiscal. Efetuamos o pagamento de duas NF’s (anexas), cada uma no valor de R$ 1.642,71, totalizando R$ 3.285,42. Ressaltamos que o valor corre | W59: =_xlfn.CONCAT(D59:E59) -> 194438120 | X59: 46269 | Y59: =IF(X59="","Aberto","Encerrado") -> Encerrado | Z59: =IF(OR(L59="PENDENTE",L59="EM ANDAMENTO",L59="PENDENTE APROVAÇÃO CANCELAMENTO NF"),TODAY()-O59,X59-O59) -> 206 | AA59: =IF(Y59="Aberto",Z59+ROW()/100000,"") | AB59: =IF(ISNUMBER(FIND("@cielo.com.br",S59)),"Interno","Externo") -> Externo
A60: Aberto antigos | B60: Pamela de Sá | C60: =VLOOKUP(I:I,'Referencias '!H:I,2,0) -> #N/A | D60: 19555123 | E60: 0 | F60: 2604317832446 | G60: =VLOOKUP(H:H,'Referencias '!B:C,2,0) -> BRF S.A. | H60: =TRIM(_xlfn.TEXTBEFORE(_xlfn.TEXTAFTER(U60,"CNPJ/CPF:</strong>"),"</p>")) -> 01.838.723/0001-27 | I60: questionar a volumetria cobrada referente ao produto 3DS | L60: EM ANDAMENTO | M60: Alta | N60: 1018 Financeiro | Desejo falar com o setor financeiro | Mariane Oliveira dos Santos | mariane.santos@cielo.com.br | O60: 46065 | P60: 12/02/2026 | Q60: =TEXT(O60,"mmm/aaaa") -> fev/2026 | R60: ECOMMERCE BP SUPORTE FINANCEIRO N2 | S60: mariane.santos@cielo.com.br | U60: Olá, segue formulário enviado para Cielo E-commerce:<p><strong>Qual seu nome?:</strong> Mariane Oliveira dos Santos</p><p><strong>Endereço de e-mail:</strong> mariane.santos@cielo.com.br</p><p><strong>CNPJ/CPF:</strong> 01.838.723/0001-27</p><p><strong>Telefone:</strong> (11) 98407-1789</p><p><strong>Assunto:</strong> Consumo 3ds</p><p><strong>Merchant ID/Estabelecimento Comercial (EC):</strong> 02.916.265/0298-18</p><p><strong>Descrição do problema:</strong> Boa tarde, pessoal! tudo bem? A BRF nos acionou recentemente para questionar a volumetria cobrada referente ao produto 3DS, considerando que hoje eles não possuem visibilidade do consumo diretamente no portal. O cliente abriu um chamado, e nosso time técnico disponibilizou o relatório de 3DS. No entanto, a BRF não consegue utilizá-lo para realizar o de/para com as transações exibidas no Admin, pois não há nenhum campo que permita vincular o relatório enviado às transações autenticadas. Além disso, nas situações em que a transação | V60: =IFERROR(_xlfn.TEXTBEFORE(_xlfn.TEXTAFTER(U60,"Descrição do problema:</strong"),"</p>"),_xlfn.TEXTAFTER(U60,"Descrição do problema:</strong")) -> > Boa tarde, pessoal! tudo bem? A BRF nos acionou recentemente para questionar a volumetria cobrada referente ao produto 3DS, considerando que hoje eles não possuem visibilidade do consumo diretamente no portal. O cliente abriu um chamado, e nosso time técnico disponibilizou o relatório de 3DS. No entanto, a BRF não consegue utilizá-lo para realizar o de/para com as transações exibidas no Admin, pois não há nenhum campo que permita vincular o relatório enviado às transações autenticadas. Além disso, nas situações em que a transação | W60: =_xlfn.CONCAT(D60:E60) -> 195551230 | Y60: =IF(X60="","Aberto","Encerrado") -> Aberto | Z60: =IF(OR(L60="PENDENTE",L60="EM ANDAMENTO",L60="PENDENTE APROVAÇÃO CANCELAMENTO NF"),TODAY()-O60,X60-O60) -> 225 | AA60: =IF(Y60="Aberto",Z60+ROW()/100000,"") -> 225.0006 | AB60: =IF(ISNUMBER(FIND("@cielo.com.br",S60)),"Interno","Externo") -> Interno
A61: Aberto antigos | B61: Pamela de Sá | C61: =VLOOKUP(I:I,'Referencias '!H:I,2,0) -> Cobrança e Contestação | D61: 19575216 | E61: 0 | F61: 2604411846581 | G61: =VLOOKUP(H:H,'Referencias '!B:C,2,0) -> CENTER MEGA COMERCIO DE MATERIAIS PARA CONSTRUCAO LTDA | H61: =TRIM(_xlfn.TEXTBEFORE(_xlfn.TEXTAFTER(U61,"CNPJ/CPF:</strong>"),"</p>")) -> 05.164.667/0007-39 | I61: Contestação de cobrança | L61: EM ANDAMENTO | M61: Alta | N61: 1018 Financeiro | Desejo falar com o setor financeiro | Caroline Mendes | carolineal@cielo.com.br | O61: 46066 | P61: 13/04/2026 | Q61: =TEXT(O61,"mmm/aaaa") -> fev/2026 | R61: FABIANA DE JESUS MARTINS LISBOA | S61: carolineal@cielo.com.br | U61: Olá, segue formulário enviado para Cielo E-commerce:<p><strong>Qual seu nome?:</strong> Caroline Mendes</p><p><strong>Endereço de e-mail:</strong> carolineal@cielo.com.br</p><p><strong>CNPJ/CPF:</strong> 05.164.667/0007-39</p><p><strong>Telefone:</strong> (11) 94503-1458</p><p><strong>Assunto:</strong> Ajuste anual contrato</p><p><strong>Merchant ID/Estabelecimento Comercial (EC):</strong> 61.233.151/0005-08</p><p><strong>Descrição do problema:</strong> Time, o cliente Covabra identificou uma inconsistência na cobrança e nos questionou sobre a divergência entre o valor das notas e o contrato, especialmente considerando que ainda não havia completado um ano da renegociação realizada em janeiro de 2025. Em janeiro/2025, o cliente renegociou os valores e teve seu contrato atualizado. Porém, nossos provedores de antifraude, no caso da Covabra, a Cybersource, utilizam como referência a data da assinatura do contrato original de aquisição do produto, independentemente de aditivos ou novas co | V61: =IFERROR(_xlfn.TEXTBEFORE(_xlfn.TEXTAFTER(U61,"Descrição do problema:</strong"),"</p>"),_xlfn.TEXTAFTER(U61,"Descrição do problema:</strong")) -> > Time, o cliente Covabra identificou uma inconsistência na cobrança e nos questionou sobre a divergência entre o valor das notas e o contrato, especialmente considerando que ainda não havia completado um ano da renegociação realizada em janeiro de 2025. Em janeiro/2025, o cliente renegociou os valores e teve seu contrato atualizado. Porém, nossos provedores de antifraude, no caso da Covabra, a Cybersource, utilizam como referência a data da assinatura do contrato original de aquisição do produto, independentemente de aditivos ou novas co | W61: =_xlfn.CONCAT(D61:E61) -> 195752160 | Y61: =IF(X61="","Aberto","Encerrado") -> Aberto | Z61: =IF(OR(L61="PENDENTE",L61="EM ANDAMENTO",L61="PENDENTE APROVAÇÃO CANCELAMENTO NF"),TODAY()-O61,X61-O61) -> 224 | AA61: =IF(Y61="Aberto",Z61+ROW()/100000,"") -> 224.00061 | AB61: =IF(ISNUMBER(FIND("@cielo.com.br",S61)),"Interno","Externo") -> Interno
B62: Stephany Lima | C62: =VLOOKUP(I:I,'Referencias '!H:I,2,0) -> Contratos, Comercial e Cadastro | D62: 19754719 | E62: 0 | F62: 2605409978915 | G62: =VLOOKUP(H:H,'Referencias '!B:C,2,0) -> CENTRAL DO CARNAVAL PRODUCOES ARTISTICAS LTDA | H62: =TRIM(_xlfn.TEXTBEFORE(_xlfn.TEXTAFTER(U62,"CNPJ/CPF:</strong>"),"</p>")) -> 03.951.956/0001-67 | I62: Congelamento de contrato | L62: FINALIZADO | M62: Médio | N62: 1018 Financeiro | Desejo falar com o setor financeiro | Clarissa | clarissa.rissi@cielo.com.br | O62: 46076 | P62: 46129 | Q62: =TEXT(O62,"mmm/aaaa") -> fev/2026 | R62: Larissa QUIRINO CANUTO | S62: clarissa.rissi@cielo.com.br | U62: Olá, segue formulário enviado para Cielo E-commerce:<p><strong>Qual seu nome?:</strong> Clarissa</p><p><strong>Endereço de e-mail:</strong> clarissa.rissi@cielo.com.br</p><p><strong>CNPJ/CPF:</strong> 03.951.956/0001-67</p><p><strong>Telefone:</strong> (11) 97261-4151</p><p><strong>Assunto:</strong> Congelamento de contrato</p><p><strong>Merchant ID/Estabelecimento Comercial (EC):</strong> 03.951.956/0001-67</p><p><strong>Descrição do problema:</strong> Pessoal, tudo bem? Conforme previsto no aditivo contratual da Central do Carnaval, precisamos realizar o congelamento da cobrança do analista. Dessa forma, a última nota a ser emitida será em março, referente ao consumo de fevereiro. Em anexo envio os aditivos que formalizam esse congelamento.</p><p><strong>ID da transação:</strong> </p><p><strong>Código do erro:</strong> </p><p><strong>Sobre qual produto ou área deseja falar?:</strong> Financeiro</p><p><strong>Como podemos te ajudar?:</strong> Desejo falar com o setor financeiro</p> | V62: =IFERROR(_xlfn.TEXTBEFORE(_xlfn.TEXTAFTER(U62,"Descrição do problema:</strong"),"</p>"),_xlfn.TEXTAFTER(U62,"Descrição do problema:</strong")) -> > Pessoal, tudo bem? Conforme previsto no aditivo contratual da Central do Carnaval, precisamos realizar o congelamento da cobrança do analista. Dessa forma, a última nota a ser emitida será em março, referente ao consumo de fevereiro. Em anexo envio os aditivos que formalizam esse congelamento. | W62: =_xlfn.CONCAT(D62:E62) -> 197547190 | X62: 46232 | Y62: =IF(X62="","Aberto","Encerrado") -> Encerrado | Z62: =IF(OR(L62="PENDENTE",L62="EM ANDAMENTO",L62="PENDENTE APROVAÇÃO CANCELAMENTO NF"),TODAY()-O62,X62-O62) -> 156 | AA62: =IF(Y62="Aberto",Z62+ROW()/100000,"") | AB62: =IF(ISNUMBER(FIND("@cielo.com.br",S62)),"Interno","Externo") -> Interno
B63: Emilly Maria | C63: =VLOOKUP(I:I,'Referencias '!H:I,2,0) -> Contratos, Comercial e Cadastro | D63: 19754066 | E63: 0 | F63: 2605409978402 | G63: =VLOOKUP(H:H,'Referencias '!B:C,2,0) -> DSC PRODUCOES E EVENTOS LTDA | H63: =TRIM(_xlfn.TEXTBEFORE(_xlfn.TEXTAFTER(U63,"CNPJ/CPF:</strong>"),"</p>")) -> 34.546.535/0001-84 | I63: Congelamento de contrato | L63: FINALIZADO | M63: Médio | N63: 1018 Financeiro | Desejo falar com o setor financeiro | Clarissa | clarissa.rissi@cielo.com.br | O63: 46076 | P63: 46175 | Q63: =TEXT(O63,"mmm/aaaa") -> fev/2026 | R63: Emilly Maria Sousa Almeida | S63: clarissa.rissi@cielo.com.br | T63: Bloco do Urso DSC | U63: Olá, segue formulário enviado para Cielo E-commerce:<p><strong>Qual seu nome?:</strong> Clarissa</p><p><strong>Endereço de e-mail:</strong> clarissa.rissi@cielo.com.br</p><p><strong>CNPJ/CPF:</strong> 34.546.535/0001-84</p><p><strong>Telefone:</strong> (11) 97261-4151</p><p><strong>Assunto:</strong> Congelamento de contrato</p><p><strong>Merchant ID/Estabelecimento Comercial (EC):</strong> 34.546.535/0001-84</p><p><strong>Descrição do problema:</strong> Pessoal, bom dia! Tudo bem? Conforme alinhado em reunião com o time financeiro e formalizado no aditivo contratual celebrado com a DSC, seguiremos com o congelamento da cobrança do Antifraude. Não devemos emitir novas cobranças referentes ao mínimo mensal nem ao custo do analista dedicado nos períodos em que não houver utilização efetiva do serviço, conforme estipulado para a operação sazonal da cliente. Permanece válida apenas a cobrança caso haja transações ou uso efetivo da solução durante os meses não sazonais, conforme tabela vi | V63: =IFERROR(_xlfn.TEXTBEFORE(_xlfn.TEXTAFTER(U63,"Descrição do problema:</strong"),"</p>"),_xlfn.TEXTAFTER(U63,"Descrição do problema:</strong")) -> > Pessoal, bom dia! Tudo bem? Conforme alinhado em reunião com o time financeiro e formalizado no aditivo contratual celebrado com a DSC, seguiremos com o congelamento da cobrança do Antifraude. Não devemos emitir novas cobranças referentes ao mínimo mensal nem ao custo do analista dedicado nos períodos em que não houver utilização efetiva do serviço, conforme estipulado para a operação sazonal da cliente. Permanece válida apenas a cobrança caso haja transações ou uso efetivo da solução durante os meses não sazonais, conforme tabela vi | W63: =_xlfn.CONCAT(D63:E63) -> 197540660 | X63: 46238 | Y63: =IF(X63="","Aberto","Encerrado") -> Encerrado | Z63: =IF(OR(L63="PENDENTE",L63="EM ANDAMENTO",L63="PENDENTE APROVAÇÃO CANCELAMENTO NF"),TODAY()-O63,X63-O63) -> 162 | AA63: =IF(Y63="Aberto",Z63+ROW()/100000,"") | AB63: =IF(ISNUMBER(FIND("@cielo.com.br",S63)),"Interno","Externo") -> Interno
B64: Emilly Maria | C64: =VLOOKUP(I:I,'Referencias '!H:I,2,0) -> Cancelamento e Reemissão de Nota Fiscal | D64: 19809905 | E64: 0 | F64: 2605511021859 | G64: =T64 | H64: =TRIM(_xlfn.TEXTBEFORE(_xlfn.TEXTAFTER(U64,"CNPJ/CPF:</strong>"),"</p>")) -> 21.570.535/0001-78 | I64: Cancelamento de NF | L64: FINALIZADO | M64: Médio | N64: 1018 Financeiro | Desejo falar com o setor financeiro | Júlia Angelolozzi | julia.djesus@cielo.com.br | O64: 46077 | P64: 46077 | Q64: =TEXT(O64,"mmm/aaaa") -> fev/2026 | R64: ECOMMERCE BP SUPORTE FINANCEIRO N2 | S64: julia.djesus@cielo.com.br | U64: Olá, segue formulário enviado para Cielo E-commerce:<p><strong>Qual seu nome?:</strong> Júlia Angelolozzi</p><p><strong>Endereço de e-mail:</strong> julia.djesus@cielo.com.br</p><p><strong>CNPJ/CPF:</strong> 21.570.535/0001-78</p><p><strong>Telefone:</strong> (11) 94452-6362</p><p><strong>Assunto:</strong> Cancelamento de cobranças</p><p><strong>Merchant ID/Estabelecimento Comercial (EC):</strong> ab2cf439-ccf0-438e-9664-a9915e0ee1fa</p><p><strong>Descrição do problema:</strong> Boa tarde, time! Espero que se encontrem bem. Sou a gerente comercial do cliente PHARMADELLE FORMULAS LTDA e solicito a isenção das cobranças e notas em aberto atreladas ao CNPJ 21.570.535/0001-78. Explico que as cobranças são indevida referente às NF´s emitidas visando o pedido de cancelamento formalizado em 2023.</p><p><strong>ID da transação:</strong> </p><p><strong>Código do erro:</strong> </p><p><strong>Sobre qual produto ou área deseja falar?:</strong> Financeiro</p><p><strong>Como podemos te ajudar?:</s | V64: =IFERROR(_xlfn.TEXTBEFORE(_xlfn.TEXTAFTER(U64,"Descrição do problema:</strong"),"</p>"),_xlfn.TEXTAFTER(U64,"Descrição do problema:</strong")) -> > Boa tarde, time! Espero que se encontrem bem. Sou a gerente comercial do cliente PHARMADELLE FORMULAS LTDA e solicito a isenção das cobranças e notas em aberto atreladas ao CNPJ 21.570.535/0001-78. Explico que as cobranças são indevida referente às NF´s emitidas visando o pedido de cancelamento formalizado em 2023. | W64: =_xlfn.CONCAT(D64:E64) -> 198099050 | X64: 46247 | Y64: =IF(X64="","Aberto","Encerrado") -> Encerrado | Z64: =IF(OR(L64="PENDENTE",L64="EM ANDAMENTO",L64="PENDENTE APROVAÇÃO CANCELAMENTO NF"),TODAY()-O64,X64-O64) -> 170 | AA64: =IF(Y64="Aberto",Z64+ROW()/100000,"") | AB64: =IF(ISNUMBER(FIND("@cielo.com.br",S64)),"Interno","Externo") -> Interno
B65: Pamela de Sá | C65: =VLOOKUP(I:I,'Referencias '!H:I,2,0) -> Atendimento Administrativo e Suporte | D65: 20009201 | E65: 0 | F65: 2606116169975 | G65: =VLOOKUP(H:H,'Referencias '!B:C,2,0) -> DROGARIA VITORIA LTDA | H65: =TRIM(_xlfn.TEXTBEFORE(_xlfn.TEXTAFTER(U65,"CNPJ/CPF:</strong>"),"</p>")) -> 12.471.470/0005-46 | I65: Outros | L65: FINALIZADO | M65: Médio | N65: 1018 Financeiro | Desejo falar com o setor financeiro | Joice Rosa | joice.dsilva@cielo.com.br | O65: 46083 | P65: 46160 | Q65: =TEXT(O65,"mmm/aaaa") -> mar/2026 | R65: STEPHANY LIMA DE LISBOA | S65: joice.dsilva@cielo.com.br | U65: Olá, segue formulário enviado para Cielo E-commerce:<p><strong>Qual seu nome?:</strong> Joice Rosa</p><p><strong>Endereço de e-mail:</strong> joice.dsilva@cielo.com.br</p><p><strong>CNPJ/CPF:</strong> 12.471.470/0005-46</p><p><strong>Telefone:</strong> (11) 99187-5666</p><p><strong>Assunto:</strong> Cliente recebendo cobrança sem ter contrato ativo</p><p><strong>Merchant ID/Estabelecimento Comercial (EC):</strong> Não tem</p><p><strong>Descrição do problema:</strong> Boa tarde, Time! A cliente está recebendo cobranças da Braspag a alguns meses, porém verifiquei que é uma loja que ainda não assinou o contrato.</p><p><strong>ID da transação:</strong> </p><p><strong>Código do erro:</strong> </p><p><strong>Sobre qual produto ou área deseja falar?:</strong> Financeiro</p><p><strong>Como podemos te ajudar?:</strong> Desejo falar com o setor financeiro</p><p><strong>GA Client ID:</strong> 1399705651.1768504352</p><p><strong>Lead Hash ID:</strong> 5e64847c3d2b573ff63770f69d658c8491e6e780a5ac31 | V65: =IFERROR(_xlfn.TEXTBEFORE(_xlfn.TEXTAFTER(U65,"Descrição do problema:</strong"),"</p>"),_xlfn.TEXTAFTER(U65,"Descrição do problema:</strong")) -> > Boa tarde, Time! A cliente está recebendo cobranças da Braspag a alguns meses, porém verifiquei que é uma loja que ainda não assinou o contrato. | W65: =_xlfn.CONCAT(D65:E65) -> 200092010 | X65: 46233 | Y65: =IF(X65="","Aberto","Encerrado") -> Encerrado | Z65: =IF(OR(L65="PENDENTE",L65="EM ANDAMENTO",L65="PENDENTE APROVAÇÃO CANCELAMENTO NF"),TODAY()-O65,X65-O65) -> 150 | AA65: =IF(Y65="Aberto",Z65+ROW()/100000,"") | AB65: =IF(ISNUMBER(FIND("@cielo.com.br",S65)),"Interno","Externo") -> Interno
B66: Stephany Lima | C66: =VLOOKUP(I:I,'Referencias '!H:I,2,0) -> Cancelamento e Reemissão de Nota Fiscal | D66: 20000723 | E66: 0 | F66: 2606114163429 | G66: =T66 -> LACLO INDUSTRIA E COMERCIO DE MO | H66: =TRIM(_xlfn.TEXTBEFORE(_xlfn.TEXTAFTER(U66,"CNPJ/CPF:</strong>"),"</p>")) -> 55.012.418/0001-00 | I66: Cancelamento de NF / reemissão | L66: FINALIZADO | M66: Médio | N66: 1018 Financeiro | Desejo falar com o setor financeiro | Clarissa | clarissa.rissi@cielo.com.br | O66: 46083 | P66: 46127 | Q66: =TEXT(O66,"mmm/aaaa") -> mar/2026 | R66: Larissa QUIRINO CANUTO | S66: clarissa.rissi@cielo.com.br | T66: LACLO INDUSTRIA E COMERCIO DE MO | U66: Olá, segue formulário enviado para Cielo E-commerce:<p><strong>Qual seu nome?:</strong> Clarissa</p><p><strong>Endereço de e-mail:</strong> clarissa.rissi@cielo.com.br</p><p><strong>CNPJ/CPF:</strong> 55.012.418/0001-00</p><p><strong>Telefone:</strong> (11) 97261-4151</p><p><strong>Assunto:</strong> Notas em duplicidade</p><p><strong>Merchant ID/Estabelecimento Comercial (EC):</strong> 55.012.418/0001‑00</p><p><strong>Descrição do problema:</strong> Pessoal, boa tarde, tudo bem? Acredito que tenhamos emitido em duplicidade a nota da multa rescisória da Laclô. Notas fiscais: 0108142 – 342,86 0109042 – 342,86 0108143 – 477,55 0109043 – 477,55 Podem por gentileza atuar na correção? Obrigada.</p><p><strong>ID da transação:</strong> </p><p><strong>Código do erro:</strong> </p><p><strong>Sobre qual produto ou área deseja falar?:</strong> Financeiro</p><p><strong>Como podemos te ajudar?:</strong> Desejo falar com o setor financeiro</p><p><strong>GA Client ID:</strong> 477416359.176045 | V66: =IFERROR(_xlfn.TEXTBEFORE(_xlfn.TEXTAFTER(U66,"Descrição do problema:</strong"),"</p>"),_xlfn.TEXTAFTER(U66,"Descrição do problema:</strong")) -> > Pessoal, boa tarde, tudo bem? Acredito que tenhamos emitido em duplicidade a nota da multa rescisória da Laclô. Notas fiscais: 0108142 – 342,86 0109042 – 342,86 0108143 – 477,55 0109043 – 477,55 Podem por gentileza atuar na correção? Obrigada. | W66: =_xlfn.CONCAT(D66:E66) -> 200007230 | X66: 46233 | Y66: =IF(X66="","Aberto","Encerrado") -> Encerrado | Z66: =IF(OR(L66="PENDENTE",L66="EM ANDAMENTO",L66="PENDENTE APROVAÇÃO CANCELAMENTO NF"),TODAY()-O66,X66-O66) -> 150 | AA66: =IF(Y66="Aberto",Z66+ROW()/100000,"") | AB66: =IF(ISNUMBER(FIND("@cielo.com.br",S66)),"Interno","Externo") -> Interno
B67: Emilly Maria | C67: =VLOOKUP(I:I,'Referencias '!H:I,2,0) -> Cancelamento e Reemissão de Nota Fiscal | D67: 20000132 | E67: 0 | F67: 2606114162959 | G67: =VLOOKUP(H:H,'Referencias '!B:C,2,0) -> AUTOPASS S.A. | H67: =TRIM(_xlfn.TEXTBEFORE(_xlfn.TEXTAFTER(U67,"CNPJ/CPF:</strong>"),"</p>")) -> 07.140.538/0001-40 | I67: Cancelamento de NF / reemissão | L67: FINALIZADO | M67: Médio | N67: 1018 Financeiro | Desejo falar com o setor financeiro | Renata Sombra | renata.sombra@autopass.com.br | O67: 46083 | P67: 46099 | Q67: =TEXT(O67,"mmm/aaaa") -> mar/2026 | R67: ECOMMERCE BP SUPORTE FINANCEIRO N2 | S67: renata.sombra@autopass.com.br | T67: TARIFA TRANSP METRA | U67: Olá, segue formulário enviado para Cielo E-commerce:<p><strong>Qual seu nome?:</strong> Renata Sombra</p><p><strong>Endereço de e-mail:</strong> renata.sombra@autopass.com.br</p><p><strong>CNPJ/CPF:</strong> 07.140.538/0001-40</p><p><strong>Telefone:</strong> (11) 96191-9323</p><p><strong>Assunto:</strong> NFS-e 098096 - Pendente de cancelamento</p><p><strong>Descrição do problema:</strong> Prezados, boa tarde! Em 29/09/2025 foi emitida a nota fiscal nº 098096 no valor de R$ 41.913,06. Foi solicitado o cancelamento por não prestação de serviços, mas a nota fiscal continua ativa na prefeitura. Poderia verificar, por favor? Atenciosamente, Renata Sombra</p><p><strong>Merchant ID/Estabelecimento Comercial (EC):</strong> não sei</p><p><strong>Sobre qual produto ou área deseja falar?:</strong> Financeiro</p><p><strong>Como podemos te ajudar?:</strong> Desejo falar com o setor financeiro</p><p><strong>GA Client ID:</strong> 742816356.1772472667</p><p><strong>Lead Hash ID:</strong> 5c623511 | V67: =IFERROR(_xlfn.TEXTBEFORE(_xlfn.TEXTAFTER(U67,"Descrição do problema:</strong"),"</p>"),_xlfn.TEXTAFTER(U67,"Descrição do problema:</strong")) -> > Prezados, boa tarde! Em 29/09/2025 foi emitida a nota fiscal nº 098096 no valor de R$ 41.913,06. Foi solicitado o cancelamento por não prestação de serviços, mas a nota fiscal continua ativa na prefeitura. Poderia verificar, por favor? Atenciosamente, Renata Sombra | W67: =_xlfn.CONCAT(D67:E67) -> 200001320 | X67: 46233 | Y67: =IF(X67="","Aberto","Encerrado") -> Encerrado | Z67: =IF(OR(L67="PENDENTE",L67="EM ANDAMENTO",L67="PENDENTE APROVAÇÃO CANCELAMENTO NF"),TODAY()-O67,X67-O67) -> 150 | AA67: =IF(Y67="Aberto",Z67+ROW()/100000,"") | AB67: =IF(ISNUMBER(FIND("@cielo.com.br",S67)),"Interno","Externo") -> Externo
